Workbook
Name AbodeFlag: '2441'!$R$60
Name Additional_Income: 'Sch. 1'!$AC$43
Name AdditionalCTC: '8812'!$AS$80
Name Address: '1040'!$B$14
Name Adj_Gross_Inc: '1040'!$AC$47
Name AdjustToIncome: 'Sch. 1'!$AC$86
Name AgPMT_Disaster: '1099-G'!$I$31
Name AgPMT_Other: '1099-G'!$I$32
Name Alaska: '1040'!$BC$7
Name AlimonyPaid: 'Sch. 1'!$AC$56
Name AlimonyRcvd: 'Sch. 1'!$AC$12
Name AltMinTaxInc: '6251'!$M$38
Name AMT: '6251'!$R$62
Name AMTExemption: '6251'!$AC$169
Name AMTExemptionFlag: '6251'!$AH$70
Name AO_Credit: '8863'!$AE$33
Name AOC_1: '8863'!$AE$111
Name AOC_2: '8863'!$AE$170
Name AOC_3: '8863'!$AE$229
Name AOC_4: '8863'!$AE$288
Name Apt_No.: '1040'!$W$14
Name ArcherMSADeduct: 'Sch. 1'!$AC$62
Name BadBirthdate_Spouse: '1040'!$AZ$122
Name BadBirthdate_Yours: '1040'!$AZ$102
Name BadDeathDate: '1040'!$BG$121
Name BASE_A1: 'Tax Table'!$U$7
Name BASE_A2: 'Tax Table'!$U$8
Name BASE_A3: 'Tax Table'!$U$9
Name BASE_A4: 'Tax Table'!$U$10
Name BASE_A5: 'Tax Table'!$U$11
Name BASE_A6: 'Tax Table'!$U$12
Name BASE_A7: 'Tax Table'!$U$13
Name BASE_B1: 'Tax Table'!$U$17
Name BASE_B2: 'Tax Table'!$U$18
Name BASE_B3: 'Tax Table'!$U$19
Name BASE_B4: 'Tax Table'!$U$20
Name BASE_B5: 'Tax Table'!$U$21
Name BASE_B6: 'Tax Table'!$U$22
Name BASE_B7: 'Tax Table'!$U$23
Name BASE_C1: 'Tax Table'!$U$27
Name BASE_C2: 'Tax Table'!$U$28
Name BASE_C3: 'Tax Table'!$U$29
Name BASE_C4: 'Tax Table'!$U$30
Name BASE_C5: 'Tax Table'!$U$31
Name BASE_C6: 'Tax Table'!$U$32
Name BASE_C7: 'Tax Table'!$U$33
Name BASE_D1: 'Tax Table'!$U$38
Name BASE_D2: 'Tax Table'!$U$39
Name BASE_D3: 'Tax Table'!$U$40
Name BASE_D4: 'Tax Table'!$U$41
Name BASE_D5: 'Tax Table'!$U$42
Name BASE_D6: 'Tax Table'!$U$43
Name BASE_D7: 'Tax Table'!$U$44
Name BeginningOfTaxYear: '1040'!$AX$2
Name Birthday_Needed: '1040'!$AX$113
Name BOTT_A1: 'Tax Table'!$T$7
Name BOTT_A2: 'Tax Table'!$T$8
Name BOTT_A3: 'Tax Table'!$T$9
Name BOTT_A4: 'Tax Table'!$T$10
Name BOTT_A5: 'Tax Table'!$T$11

Sheet Coversheet
D1: Revision Date/Time: | E1: =RevDateTime -> 46003.399
B2: -- DISCLAIMER -- These spreadsheets are provided "as is", with no warranty of any kind, expressed or implied, and in no event will Glenn Reeves be liable for direct, indirect, incidental, or consequential damages resulting from the use of any of these spreadsheets. Glenn Reeves specifically disclaims the role of tax adviser. These spreadsheets attempt to perform the mechanics of tax preparation in accordance with IRS forms and instructions. The user must assume responsibility as to the correctness and appropriateness of any and all amounts entered and results produced.
B12: No password is needed. If you find a data entry cell to be protected, it is because it is a calculated value using input from another location in the spreadsheet. Read the instructions for that line to determine where the values are derived. However, for most calculated cells, a manual override cell is provided if you need to override the calculated value. After a while, you will figure out that the spreadsheet is completely functional without needing to unprotect it.
B22: Errors If you find an error, first check the revision date/time above against the revision number of the latest spreadsheet to be published at:
E24: https://sites.google.com/view/incometaxspreadsheet/home/changes
C25: If you find you're using an earlier version, review the changes made since your version
C26: to determine if the problem you've encountered has has already been fixed.
C27: If so, please download the latest version and begin again. (There is no simple way to migrate...)
C28: If you cannot determine (or you're not sure) as to whether or not the problem(s) you've found
C29: has been corrected, please do your fellow taxpayers a favor by reporting the problem to:
E30: incometaxspreadsheet@gmail.com
B33: SUMMARY
B34: Adjusted Gross Income | E34: =Adj_Gross_Inc -> 0 | G34: Form 1040, Line 11 | M34: Single | N34: =IF(Taxable_Inc="","---",IF(Taxable_Inc<BOTT_A2,TEXT(RATE_A1,"0%"),IF(Taxable_Inc<BOTT_A3,TEXT(RATE_A2,"0%"),IF(Taxable_Inc<BOTT_A4,TEXT(RATE_A3,"0%"),IF(Taxable_Inc<BOTT_A5,TEXT(RATE_A4,"0%"),IF(Taxable_Inc<BOTT_A6,TEXT(RATE_A5,"0%"),IF(Taxable_Inc<BOTT_A7,TEXT(RATE_A6,"0%"),TEXT(RATE_A7,"0.0%")))))))) -> 10%
B35: Total Deductions | E35: =TotalDeductions -> 0 | G35: Form 1040, Line 14
B36: Taxable Income | E36: =Taxable_Inc -> 0 | G36: Form 1040, Line 15 | M36: MFJ or QW | N36: =IF(Taxable_Inc="","---",IF(Taxable_Inc<BOTT_B2,TEXT(RATE_B1,"0%"),IF(Taxable_Inc<BOTT_B3,TEXT(RATE_B2,"0%"),IF(Taxable_Inc<BOTT_B4,TEXT(RATE_B3,"0%"),IF(Taxable_Inc<BOTT_B5,TEXT(RATE_B4,"0%"),IF(Taxable_Inc<BOTT_B6,TEXT(RATE_B5,"0%"),IF(Taxable_Inc<BOTT_B7,TEXT(RATE_B6,"0%"),TEXT(RATE_B7,"0.0%")))))))) -> 10%
B37: Total Tax | E37: =Tot_Tax -> 0 | G37: Form 1040, Line 24 | M37: MFS | N37: =IF(Taxable_Inc="","---",IF(Taxable_Inc<BOTT_C2,TEXT(RATE_C1,"0%"),IF(Taxable_Inc<BOTT_C3,TEXT(RATE_C2,"0%"),IF(Taxable_Inc<BOTT_C4,TEXT(RATE_C3,"0%"),IF(Taxable_Inc<BOTT_C5,TEXT(RATE_C4,"0%"),IF(Taxable_Inc<BOTT_C6,TEXT(RATE_C5,"0%"),IF(Taxable_Inc<BOTT_C7,TEXT(RATE_C6,"0%"),TEXT(RATE_C7,"0.0%")))))))) -> 10%
B38: Total Payments/Credits | E38: =Tot_Payments -> 0 | G38: Form 1040, Line 33 | M38: HOH | N38: =IF(Taxable_Inc="","---",IF(Taxable_Inc<BOTT_D2,TEXT(RATE_D1,"0%"),IF(Taxable_Inc<BOTT_D3,TEXT(RATE_D2,"0%"),IF(Taxable_Inc<BOTT_D4,TEXT(RATE_D3,"0%"),IF(Taxable_Inc<BOTT_D5,TEXT(RATE_D4,"0%"),IF(Taxable_Inc<BOTT_D6,TEXT(RATE_D5,"0%"),IF(Taxable_Inc<BOTT_D7,TEXT(RATE_D6,"0%"),TEXT(RATE_D7,"0.0%")))))))) -> 10%
B39: =IF(Overpaid>0,"Amount You Overpaid",IF(AND(E39<>"",E39>0),"Amount You Underpaid","")) | E39: =IF(Overpaid>0,Overpaid,IF(SUM(Tot_Tax,-Tot_Payments)>0,SUM(Tot_Tax,-Tot_Payments),"")) | G39: =IF(Overpaid>0,"Form 1040, Line 34","")
B40: =IF(TaxPenalty>0,"Penalty/Interest","") | E40: =IF(TaxPenalty>0,TaxPenalty,"") | G40: =IF(TaxPenalty>0,"Form 1040, Line 38","")
B41: =IF(Overpaid>0,"Amount To be Refunded","Amount You Owe") -> Amount You Owe | E41: =IF(Overpaid>0,Overpaid,You_Owe) -> 0 | G41: =IF(Overpaid>0,"Form 1040, Line 35a","Form 1040, Line 37") -> Form 1040, Line 37
B43: Tax Bracket | E43: =IF(File_Single<>"",N34,IF(OR(File_Marr_Joint<>"",File_Qual_Widow<>""),N36,IF(File_Marr_Sep<>"",N37,IF(File_Head<>"",N38,"---")))) -> ---
B47: This spreadsheet is free. However, if you would like to show your appreciation, you may make a contribution by clicking one of the following links and sending money as indicated.
C52: PayPal | E52: Zelle (App)
C53: https://paypal.me/incometaxspreadsheet | E53: https://www.zellepay.com/
C54: (Send to: IncomeTaxSpreadsheet@gmail.com ) | E54: (Send to: IncomeTaxSpreadsheet@gmail.com )
C56: Google Pay | E56: Popmoney
C57: https://pay.google.com/payments/ | E57: https://www.popmoney.com/
C58: (Send to: IncomeTaxSpreadsheet@gmail.com ) | E58: (Send to: IncomeTaxSpreadsheet@gmail.com )
C60: US Mail:
C61: Glenn Reeves
C62: (Tax Calculator)
C63: 4802 N 124th Ct
C64: Kansas City, KS 66109-3809
D66: Thank you for using my spreadsheet and for any money you decide to send!

Sheet Table of Contents
C2: Sheet Name (with hyperlink)
D3: Federal Income Tax Spreadsheet | M3: Updated
D4: Table of Contents | H4: Draft IRS | I4: Updated | J4: Final IRS | K4: Draft IRS | L4: Final IRS | M4: Final
D5: ="© Glenn Reeves, "&TaxYear+1 -> © Glenn Reeves, 2022 | G5: Form | H5: Form | I5: Draft Form | J5: Form | K5: Instruction | L5: Instruction
D6: Title / Description | G6: Last checked | H6: 44498
C7: Coversheet | D7: Possible tax return coversheet which includes a disclaimer, important notes, and a summary.
C8: Table of Contents | D8: Table of contents with links to the sheets included in this spreadsheet.
C9: Instructions | D9: Important notes, general notes, and instructions to help you get started.
C10: W-2s | D10: Form W-2, Wage and Tax Statement | F10: 1 | G10: =C10 -> W-2s
C11: 1099-INT | D11: Form 1099-INT, Interest Income | F11: 2 | G11: =C11 -> 1099-INT
C12: 1099-DIV | D12: Form 1099-DIV, Dividend Income | F12: 3 | G12: =C12 -> 1099-DIV
C13: 1099-G | D13: Form 1099-G, Certain Government Payments | F13: 4 | G13: =C13 -> 1099-G
C14: 1099-MISC | D14: Form 1099-MISC, Miscellaneous Income (Way too complicated -- included for information) | F14: 5 | G14: =C14 -> 1099-MISC
C15: 1099-R | D15: Form 1099-R, Distributions From Pensions, Annuities, Retirement or Profit-Sharing Plans, IRAs, Insurance Contracts, etc. | F15: 6 | G15: =C15 -> 1099-R
C16: SSA-1099 | D16: Form SSA-1099, Social Security Benefit Statement and IRS Notice 703, To See If Your Social Security Benefits May Be Taxable | F16: 7 | G16: =C16 -> SSA-1099
C17: 1040 | D17: Form 1040, U.S. Individual Income Tax Return | F17: 8 | G17: =C17 -> 1040 | H17: 44398 | I17: 44500 | J17: 44539 | K17: 44237 | L17: 44552 | M17: 44567
C18: Sch. 1 | D18: Schedule 1, Additional Income and Adjustments to Income | F18: 9 | G18: =C18 -> Sch. 1 | H18: 44398 | J18: 44533 | M18: 44568
C19: Sch. 1, Line 1 (SALT) | D19: State and Local Income Tax Refund Worksheet — Line 1 | F19: 17 | G19: =C19 -> Sch. 1, Line 1 (SALT) | M19: 44568
C20: Sch. 1 Line 20 (IRA) | D20: IRA Deduction Worksheet — Schedule 1, Line 20 | F20: 22 | G20: =C20 -> Sch. 1 Line 20 (IRA) | M20: 44578
C21: Sch. 1 Line 21 (Stu Loan) | D21: Student Loan Interest Deduction Worksheet — Schedule 1, Line 21 | F21: 23 | G21: =C21 -> Sch. 1 Line 21 (Stu Loan) | M21: 44578
C22: Sch. 2 | D22: Schedule 2, Additional Taxes | F22: 11 | G22: =C22 -> Sch. 2 | H22: 44398 | J22: 44533 | M22: 44568
C23: Sch. 3 | D23: Schedule 3, Nonrefundable Credits | F23: 12 | G23: =C23 -> Sch. 3 | H23: 44495 | I23: 44500 | J23: 44533 | M23: 44568
C24: Earned Inc WS | D24: Earned Income Worksheet — Used as input to Line 9 (SD Depnts), Line 13a (CTC), & Form 8812. | F24: 13 | G24: =C24 -> Earned Inc WS
C25: Lines 5ab (Simplified Meth WS) | D25: Simplified Method Worksheet—Lines 5a and 5b -- to determine taxable amount of retirement pension or annuity. | F25: 14 | G25: =C25 -> Lines 5ab (Simplified Meth WS) | M25: 44578
C26: Line 6ab (SS Bene) | D26: Social Security Benefits Worksheet – Lines 6a and 6b -- to determine taxable amount of Social Security benefits. | F26: 15 | G26: =C26 -> Line 6ab (SS Bene) | M26: 44571
C27: Line 12 (SD Depnts) | D27: Standard Deduction Worksheet for Dependents — Line 12 | F27: 16 | G27: =C27 -> Line 12 (SD Depnts) | M27: 44571
C28: Line 16 (QDCG Tax) | D28: Qualified Dividends and Capital Gain Tax Worksheet—Line 12a | F28: 18 | G28: =C28 -> Line 16 (QDCG Tax) | M28: 44571
C29: Line 27 (EIC) | D29: Line 27 — Earned Income Credit Worksheet — Spreadsheet provides assistance in completing this. | F29: 20 | G29: =C29 -> Line 27 (EIC)
C30: Line 30 (Rebate Credit) | D30: Recovery Rebate Credit Worksheet—Line 30 | F30: 21 | G30: =C30 -> Line 30 (Rebate Credit) | M30: 44575
C31: Sch. A | D31: Schedule A, Itemized Deductions | F31: 24 | G31: =C31 -> Sch. A | H31: 44426 | J31: 44550 | L31: 44566 | M31: 44578
C32: Sch. B | D32: Schedule B, Interest and Ordinary Dividends | F32: 25 | G32: =C32 -> Sch. B | H32: 44369 | J32: 44503 | K32: 44399 | L32: 44539 | M32: 44578
C33: Sch. C | D33: Schedule C, Profit or Loss from Business (Two Schedule C's are included) | F33: 26 | G33: =C33 -> Sch. C | H33: 44364 | J33: 44494 | K33: 44489 | L33: 44552 | M33: 44579
C34: Sch. D | D34: Schedule D, Capital Gains and Losses | F34: 27 | G34: =C34 -> Sch. D | H34: 44426 | J34: 44540 | K34: 44489 | L34: 44544 | M34: 44579
C35: Sch. D WS | D35: Schedule D Worksheets - Capital Loss Carryover Worksheet—Schedule D, Lines 6 and 14 - 28% Rate Gain Worksheet—Schedule D, Line 18 - Schedule D Tax Worksheet | F35: 28 | G35: =C35 -> Sch. D WS | M35: 44581
C36: Sch. E | D36: Schedule E, Supplemental Income and Loss (2 forms) | F36: 29 | G36: =C36 -> Sch. E | H36: 44364 | J36: 44494 | K36: 44467 | L36: 44545 | M36: 44498 | N36: Check against instructions.
C37: Sch. E (2) | D37: Schedule E, Supplemental Income and Loss (2 forms) | F37: 29 | G37: =C37 -> Sch. E (2) | H37: 44364 | J37: 44494 | K37: 44467 | L37: 44545 | M37: 44498 | N37: Check against instructions.
C38: Sch. F | D38: Schedule F, Profit or Loss from Farming | F38: 30 | G38: =C38 -> Sch. F | H38: 44497 | J38: 44551 | L38: 44553 | M38: 44575
C39: Sch. R | D39: Schedule R, Credit for the Elderly or the Disabled | F39: 31 | G39: =C39 -> Sch. R | H39: 44400 | J39: 44494 | K39: 44446 | L39: 44494 | M39: 44576
C40: Sch. SE | D40: Schedule SE, Self-Employement Tax (Two Schedule SE's are included) | F40: 32 | G40: =C40 -> Sch. SE | H40: 44363 | J40: 44494 | L40: 44536 | M40: 44499 | N40: Check against instructions.
C41: 1116 | D41: Form 1116, Foreign Tax Credit | F41: 33 | G41: =C41 -> 1116 | H41: 44454 | J41: 44544 | M41: 44576
C42: 2210 | D42: Form 2210, Underpayment of Estimated Tax by Individuals, Estates, and Trusts < Not finished. > | F42: 34 | G42: =C42 -> 2210 | H42: 44231 | I42: 44495 | J42: 44572 | K42: 44552 | L42: 44579 | N42: Not yet working.
C43: 2441 | D43: Form 2441, Child and Dependent Care Expenses | F43: 35 | G43: =C43 -> 2441 | H43: 44456 | J43: 44545 | K43: 44495 | L43: 44547 | M43: 44577
C44: 2555 | D44: Form 2555, Foreign Earned Income | F44: 36 | G44: =C44 -> 2555 | H44: 44404 | J44: 44510 | K44: 44405 | L44: 44510 | M44: 44581
C45: 4562 | D45: Form 4562, Depreciation and Amortization | F45: 37 | G45: =C45 -> 4562 | H45: 44377 | J45: 44550 | K45: 44217 | L45: 44572 | M45: 44581
C46: 6251 | D46: Form 6251, Alternative Minimum Tax—Individuals | F46: 38 | G46: =C46 -> 6251 | H46: 44460 | I46: 44502 | J46: 44571 | K46: 44439 | L46: 44573 | M46: 44581
C47: 8283 | D47: Form 8283, Noncash Charitable Contributions | F47: 39 | G47: =C47 -> 8283 | H47: 44447 | J47: 44505 | K47: 44119 | L47: 44565 | M47: 44581
C48: 8606 | D48: Form 8606, Nondeductible IRAs | F48: 40 | G48: =C48 -> 8606 | H48: 44427 | J48: 44558 | K48: 44470 | L48: 44572 | M48: 44582
C49: 8812 | D49: Schedule 8812, Additional Child Tax Credit | F49: 41 | G49: =C49 -> 8812 | H49: 44504 | J49: 44543 | M49: 44575
C50: 8829 | D50: Form 8829, Expenses for Business Use of Your Home | F50: 42 | G50: =C50 -> 8829 | H50: 44461 | J50: 44540 | L50: 44545 | M50: 44582
C51: 8863 | D51: Form 8863, Education Credits (American Opportunity and Lifetime Learning Credits) | F51: 42 | G51: =C51 -> 8863 | H51: 44461 | J51: 44540 | L51: 44545 | M51: 44582
C52: 8880 | D52: Form 8880, Credit for Qualified Retirement Savings Contributions | F52: 43 | G52: =C52 -> 8880 | H52: 44404 | J52: 44547 | L52: 44573 | M52: 44582
C53: 8889 | D53: Form 8889, Health Savings Accounts | F53: 43 | G53: =C53 -> 8889 | H53: 44404 | J53: 44547 | L53: 44573 | M53: 44582
C54: 8949A | D54: Form 8949, Sales and Other Dispositions of Capital Assets | F54: 44 | G54: =C54 -> 8949A | H54: 44400 | J54: 44543 | L54: 44571 | M54: 44582
C55: 8949B | D55: Form 8949, Sales and Other Dispositions of Capital Assets | F55: 45 | G55: =C55 -> 8949B | H55: --- | J55: --- | K55: --- | L55: --- | M55: 44582
C56: 8949C | D56: Form 8949, Sales and Other Dispositions of Capital Assets | F56: 46 | G56: =C56 -> 8949C | H56: --- | J56: --- | K56: --- | L56: --- | M56: 44582
C57: 8949D | D57: Form 8949, Sales and Other Dispositions of Capital Assets | F57: 47 | G57: =C57 -> 8949D | H57: --- | J57: --- | K57: --- | L57: --- | M57: 44582
C58: 8959 | D58: Form 8959, Additional Medicare Tax | F58: 48 | G58: =C58 -> 8959 | H58: 44431 | I58: 44503 | J58: 44516 | K58: 44462 | L58: 44531 | M58: 44583
C59: 8960 | D59: Form 8960, Net Investment Income Tax—Individuals, Estates, and Trusts | F59: 49 | G59: =C59 -> 8960 | H59: 44400 | J59: 44538 | K59: 44473 | L59: 44544 | M59: 44583
C60: 8962 | D60: Form 8962, Premium Tax Credit | F60: 50 | G60: =C60 -> 8962 | H60: 44420 | J60: 44543 | K60: 44448 | L60: 44543 | M60: 44584
C61: 8995 | D61: Form 8995, Qualified Business Income Deduction Simplified Computation | F61: 51 | G61: =C61 -> 8995 | H61: 44488 | J61: 44571 | K61: 44448 | L61: 44574 | M61: 44582
C62: EIC Table | D62: Earned Income Credit (EIC) Table (From Form 1040, General Instructions) | F62: 52 | G62: =C62 -> EIC Table | M62: 44568
C63: Tax Table | D63: Tax Table (From Form 1040, General Instructions) | F63: 53 | G63: =C63 -> Tax Table | H63: 44469 | L63: 44547 | M63: 44465
C64: Changes | D64: Changes made to this spreadsheet since it's first publication this tax year | G64: =C64 -> Changes | H64: N/A | I64: N/A | J64: N/A | K64: N/A | L64: N/A | M64: ---

Sheet Instructions
A2: Excel1040 -- Income Tax Spreadsheet
A3: Instructions for Use
B5: IMPORTANT NOTES:
B6: 1. | C6: The purpose of this spreadsheet is to help U.S. taxpayers calculate their own federal income tax returns.
C7: The spreadsheet attempts to perform the mechanics of tax preparation (i.e. 'do the math') in accordance
C8: with IRS forms and instructions.
B10: 2. | C10: This spreadsheet is designed for taxpayers who are capable of preparing their own federal income tax returns.
C11: Users of this spreadsheet must know what information needs to be entered and where to enter it.
C12: Users of this spreadsheet must also be sufficiently familiar with the IRS forms and instructions that apply to
C13: their tax return in order to detect and correct any and all user and spreadsheet errors that might occur.
C14: Although some error checking is included, this spreadsheet will not prevent you from making mistakes.
B16: 3. | C16: The user must assume full responsibility as to the correctness and appropriateness of any and all amounts
C17: entered and results produced. Be sure to use current copies of actual IRS forms and instructions when
C18: validating the spreadsheet's results. IRS forms and instructions: | I18: https://www.irs.gov/downloads/irs-pdf
B20: 4. | C20: It is vitally important that all spreadsheet users promptly report any error(s) they find so that the spreadsheet
C21: can be corrected. | F21: Report errors to: | G21: incometaxspreadsheet@gmail.com
B23: GENERAL NOTES:
B24: 1. | C24: Unprotected data entry cells have a light blue fill color.
C25: Cells containing calculated amounts are usually protected and have a darker blue fill color.
C26: Form and worksheet areas are protected. However, users are able to adjust printing properties.
B28: 2. | C28: "Manual override" cells are available for many calculated cells. The use of override cells is discouraged
C29: because manual overrides can defeat the spreadsheet's automatic updating feature. If you are having
C30: to use a manual override because of a spreadsheet error, be sure to report the error as soon as possible.
C32: NOTE: To clear data from an override cell, highlight it and then press the <Delete> key.
C33: Do not press the <space> bar because, although it is invisible, the <space> character is treated the
C34: same as any visible character.
B36: 3. | C36: To check a checkbox, simply type an 'X' (any character will work) in the box and press <Enter>.
C38: NOTE: To clear an 'X' from an checkbox, highlight it and then press the <Delete> key.
C39: Do not press the <space> bar because, although it is invisible, the <space> character is treated the
C40: same as any visible character.
B42: 4. | C42: Prior to printing, to remove colors from all forms and worksheets, place an 'X' in Cell AK2 on the '1040' sheet.
C43: Likewise, to remove social security numbers from all forms and worksheets, place an "X" in Cell AK3 on the '1040' sheet.
B45: 5. | C45: If using copy/paste to copy information from another source, be sure to paste using 'Paste-Values'.
C46: Otherwise, cell properties could be inadvertently changed. (e.g. A normally unprotected cell could become
C47: protected.)
B49: 6. | C49: DO NOT DELETE UNUSED SHEETS. This spreadsheet employs references and links that tie one sheet to
C50: one or more other sheets which ultimately feed to the Form 1040. Deleting any sheet will most likely cause the
C51: spreadsheet to completely stop functioning.
B53: 7. | C53: On Form 1040, to save time, it's generally okay to enter alternate information (e.g. SSN = 111-22-3333).
C54: Be aware, to perform an accurate tax calculation, the spreadsheet will need reasonably accurate birthdate,
C55: accurate state of residence, and a valid SSN. Don't leave these cells blank.
B57: INSTRUCTIONS:
B58: 1. | C58: Click on the tab labeled '1040' and enter all of the information required for Form 1040, Page 1.
B59: 2. | C59: Enter your birthdate and, if filing Married - Filing Jointly, enter your spouse's birthdate to the right of the Form 1040.
B60: 3. | C60: Click on the tab labeled 'W-2s' and enter any employment income reported to you on Form W-2.
C61: Be sure to enter your information in Rows 2 through 24 and your spouse's information into Rows 31 through 53.
B62: 4. | C62: Click on the tab labeled '1099-INT' and enter any interest income reported to you on Form 1099-INT.
C63: (Interest income information will automatically appear on Schedule B, Line 1.)
B64: 5. | C64: Click on the tab labeled '1099-DIV' and enter any dividend income reported on Form 1099-DIV.
C65: (Dividend income information will automatically appear on Schedule B, Line 5.)
B66: 6. | C66: Click on the tab labeled '1099-R' and enter any IRA/pension/annuity income reported to you on Form 1099-R.
C67: Be sure to enter 'IRA', 'P/A', or 'CONV' at the top of each row to let the spreadsheet know if the income is from
C68: an Individual Retirement Account, Pension/Annuity, or Conversion (from an IRA to a Roth IRA).
B69: 7. | C69: Click on the tab labeled 'SSA-1099' and enter any Social Security income reported to you on Form SSA-1099.
B70: 8. | C70: Begin a careful, line-by-line, review of the sheet labeled '1040'. If additional information is needed for a
C71: particular line, then look for a sheet associated with that line (e.g. "Line 9 (QBID)") to determine if additional
C72: information needs to be entered.
C73: HINT: Recommend regularly checking and saving your spreadsheet.
B74: 9. | C74: Review every tab to determine its applicability to your tax return and make sure each sheet is completed.
C75: NOTE: At any time, you may change the tab color by right-mouse clicking on the tab. Also, at any time,
C76: you may click and drag sheet tabs to be arranged in any order you desire. Doing so will not affect
C77: the function of the spreadsheet.
B78: 10. | C78: Recommend printing your return and reviewing the printed copy against actual IRS forms and instructions.
B79: 11. | C79: Transfer results to an electronic filing service or hard copies of the forms.
B81: INSTRUCTIONS for LibreOffice Users:
B82: 1. | C82: To save a copy of this spreadsheet in .ods format, perform the following steps:
C83: 1). Load the spreadsheet as an .xlsx file, then save it as an .fods file.
C84: 2). Close the .fods file. Then re-open the .fods file
C85: 3). Save the .fods file as an .ods file.
C86: 4) Close the .ods file. Then, re-open the .ods file.
C89: Table of Contents

Sheet W-2s
B1: Information from Form W-2, Wage and Tax Statement | F1: Maximum SS Tax Earnings: | G1: 142800 | H1: SS Tax Rate: | I1: 0.062 | K1: Max. SS Tax: | L1: =MaxSSTaxEarnings*SSTaxRate -> 8853.6 | M1: per person | O1: Notes
B2: =IF(Name_1st_Yours="","Enter your name on the"&CHAR(10)&"sheet labeled '1040'",NameYours) -> Enter your name on the sheet labeled '1040' | C2: Employer #1 | D2: Employer #2 | E2: Employer #3 | F2: Employer #4 | G2: Employer #5 | H2: Employer #6 | I2: Total | J2: Excess | L2: Used at: | O2: Date
A3: 1 | B3: Wages, tips, other compensation | I3: =SUM(ROUND(C3,0),ROUND(D3,0),ROUND(E3,0),ROUND(F3,0),ROUND(G3,0),ROUND(H3,0)) -> 0 | N3: =130000 -> 130000
A4: 2 | B4: Federal income tax withheld | I4: =SUM(ROUND(C4,0),ROUND(D4,0),ROUND(E4,0),ROUND(F4,0),ROUND(G4,0),ROUND(H4,0)) -> 0 | N4: =0.13*N3 -> 16900
A5: 3 | B5: Social security wages | I5: =SUM(ROUND(C5,0),ROUND(D5,0),ROUND(E5,0),ROUND(F5,0),ROUND(G5,0),ROUND(H5,0)) -> 0 | L5: Sch. SE, Line 8a | N5: =MIN(N3,MaxSSTaxEarnings) -> 130000
A6: 4 | B6: Social security tax withheld | I6: =SUM(C6:H6) -> 0 | J6: =IF(EmployerCountYou<2,0,IF(AND(EmployerCountYou>1,SUM(I6,-MaxSSTax)>0),SUM(I6,-MaxSSTax),0)) -> 0 | N6: =MIN(SSTaxRate*N3,MaxSSTax) -> 8060
A7: 5 | B7: Medicare wages and tips | I7: =SUM(ROUND(C7,0),ROUND(D7,0),ROUND(E7,0),ROUND(F7,0),ROUND(G7,0),ROUND(H7,0)) -> 0 | N7: =N3 -> 130000
A8: 6 | B8: Medicare tax withheld | I8: =SUM(ROUND(C8,0),ROUND(D8,0),ROUND(E8,0),ROUND(F8,0),ROUND(G8,0),ROUND(H8,0)) -> 0 | L8: Only bolded amounts are used in this spreadsheet. | N8: =0.0145*N7 -> 1885
A9: 7 | B9: Social Security Tips | I9: =SUM(ROUND(C9,0),ROUND(D9,0),ROUND(E9,0),ROUND(F9,0),ROUND(G9,0),ROUND(H9,0)) -> 0 | L9: Sch. SE, Line 8a
A10: 8 | B10: Allocated Tips | I10: =SUM(ROUND(C10,0),ROUND(D10,0),ROUND(E10,0),ROUND(F10,0),ROUND(G10,0),ROUND(H10,0)) -> 0
A11: 10 | B11: Dependent Care Benefits | I11: =SUM(ROUND(C11,0),ROUND(D11,0),ROUND(E11,0),ROUND(F11,0),ROUND(G11,0),ROUND(H11,0)) -> 0
A12: 11 | B12: Nonqualified plans | I12: =SUM(ROUND(C12,0),ROUND(D12,0),ROUND(E12,0),ROUND(F12,0),ROUND(G12,0),ROUND(H12,0)) -> 0
A13: 12a | B13: See instructions for box 12 | I13: =SUM(ROUND(C13,0),ROUND(D13,0),ROUND(E13,0),ROUND(F13,0),ROUND(G13,0),ROUND(H13,0)) -> 0
A14: 12b | I14: =SUM(ROUND(C14,0),ROUND(D14,0),ROUND(E14,0),ROUND(F14,0),ROUND(G14,0),ROUND(H14,0)) -> 0
A15: 12c | I15: =SUM(ROUND(C15,0),ROUND(D15,0),ROUND(E15,0),ROUND(F15,0),ROUND(G15,0),ROUND(H15,0)) -> 0
A16: 12d | I16: =SUM(ROUND(C16,0),ROUND(D16,0),ROUND(E16,0),ROUND(F16,0),ROUND(G16,0),ROUND(H16,0)) -> 0
A17: 13 | B17: Stat Emp / Retire / 3rd Party Sick | I17: =SUM(ROUND(C17,0),ROUND(D17,0),ROUND(E17,0),ROUND(F17,0),ROUND(G17,0),ROUND(H17,0)) -> 0
A18: 14 | B18: Other | I18: =SUM(ROUND(C18,0),ROUND(D18,0),ROUND(E18,0),ROUND(F18,0),ROUND(G18,0),ROUND(H18,0)) -> 0
A19: 14 | B19: Railroad retire (RRTA) compensation | I19: =SUM(ROUND(C19,0),ROUND(D19,0),ROUND(E19,0),ROUND(F19,0),ROUND(G19,0),ROUND(H19,0)) -> 0
A20: 14 | B20: RRTA medicare tax withheld (see Form CT-2) | I20: =SUM(ROUND(C20,0),ROUND(D20,0),ROUND(E20,0),ROUND(F20,0),ROUND(G20,0),ROUND(H20,0)) -> 0
A21: 16 | B21: State wages, tips, etc. | I21: =SUM(ROUND(C21,0),ROUND(D21,0),ROUND(E21,0),ROUND(F21,0),ROUND(G21,0),ROUND(H21,0)) -> 0
A22: 17 | B22: State income tax | I22: =SUM(ROUND(C22,0),ROUND(D22,0),ROUND(E22,0),ROUND(F22,0),ROUND(G22,0),ROUND(H22,0)) -> 0 | N22: =0.05*N3 -> 6500
A23: 18 | B23: Local wages, tips, etc. | I23: =SUM(ROUND(C23,0),ROUND(D23,0),ROUND(E23,0),ROUND(F23,0),ROUND(G23,0),ROUND(H23,0)) -> 0
A24: 19 | B24: Local income tax | I24: =SUM(ROUND(C24,0),ROUND(D24,0),ROUND(E24,0),ROUND(F24,0),ROUND(G24,0),ROUND(H24,0)) -> 0
B25: Employer count (You) | C25: =IF(AND(C6<>"",C6<>0),1,0) -> 0 | D25: =IF(AND(D6<>"",D6<>0),1,0) -> 0 | E25: =IF(AND(E6<>"",E6<>0),1,0) -> 0 | F25: =IF(AND(F6<>"",F6<>0),1,0) -> 0 | G25: =IF(AND(G6<>"",G6<>0),1,0) -> 0 | H25: =IF(AND(H6<>"",H6<>0),1,0) -> 0 | I25: =SUM(C25:H25) -> 0
B26: ="Medicare wages and tip > "&TEXT('8959'!$H$24,"$0,000") -> Medicare wages and tip > $200,000 | C26: =IF(C7>'8959'!$H$24,TRUE,FALSE) -> FALSE | D26: =IF(D7>'8959'!$H$24,TRUE,FALSE) -> FALSE | E26: =IF(E7>'8959'!$H$24,TRUE,FALSE) -> FALSE | F26: =IF(F7>'8959'!$H$24,TRUE,FALSE) -> FALSE | G26: =IF(G7>'8959'!$H$24,TRUE,FALSE) -> FALSE | H26: =IF(H7>'8959'!$H$24,TRUE,FALSE) -> FALSE
B27: ="RRTA > "&TEXT('8959'!$H$24,"$0,000") -> RRTA > $200,000 | C27: =IF(C19>'8959'!$H$24,TRUE,FALSE) -> FALSE | D27: =IF(D19>'8959'!$H$24,TRUE,FALSE) -> FALSE | E27: =IF(E19>'8959'!$H$24,TRUE,FALSE) -> FALSE | F27: =IF(F19>'8959'!$H$24,TRUE,FALSE) -> FALSE | G27: =IF(G19>'8959'!$H$24,TRUE,FALSE) -> FALSE | H27: =IF(H19>'8959'!$H$24,TRUE,FALSE) -> FALSE
C28: =IF(AND(I6>MaxSSTax,EmployerCountYou=1),"Notify your employer that they withheld "&TEXT(SUM(I6,-MaxSSTax),"$0.00")&" too much Social Security Tax or file Form 843, Claim for Refund and Request for Abatement.","")
B29: =IF(OR(AND(C7="",C8<>""),AND(D7="",D8<>""),AND(E7="",E8<>""),AND(F7="",F8<>"")),"CAUTION: Entering an amount into Line 6 without entering an amount into Line 5 will result in a tax calculation error.","")
B30: Information from Form W-2, Wage and Tax Statement
B31: =IF(Name_1st_Sp="","Enter your spouse's name on"&CHAR(10)&"the sheet labeled '1040'",NameSpouse) -> Enter your spouse's name on the sheet labeled '1040' | C31: Employer #1 | D31: Employer #2 | E31: Employer #3 | F31: Employer #4 | G31: Employer #5 | H31: Employer #6 | I31: Total | J31: Excess | L31: Used at:
A32: 1 | B32: Wages, tips, other compensation | I32: =SUM(ROUND(C32,0),ROUND(D32,0),ROUND(E32,0),ROUND(F32,0),ROUND(G32,0),ROUND(H32,0)) -> 0
A33: 2 | B33: Federal income tax withheld | I33: =SUM(ROUND(C33,0),ROUND(D33,0),ROUND(E33,0),ROUND(F33,0),ROUND(G33,0),ROUND(H33,0)) -> 0
A34: 3 | B34: Social security wages | I34: =SUM(ROUND(C34,0),ROUND(D34,0),ROUND(E34,0),ROUND(F34,0),ROUND(G34,0),ROUND(H34,0)) -> 0 | L34: Sch. SE, Line 8a
A35: 4 | B35: Social security tax withheld | I35: =SUM(C35:H35) -> 0 | J35: =IF(EmployerCountSpouse<2,0,IF(AND(EmployerCountSpouse>1,SUM(I35,-MaxSSTax)>0),SUM(I35,-MaxSSTax),0)) -> 0
A36: 5 | B36: Medicare wages and tips | I36: =SUM(ROUND(C36,0),ROUND(D36,0),ROUND(E36,0),ROUND(F36,0),ROUND(G36,0),ROUND(H36,0)) -> 0
A37: 6 | B37: Medicare tax withheld | I37: =SUM(ROUND(C37,0),ROUND(D37,0),ROUND(E37,0),ROUND(F37,0),ROUND(G37,0),ROUND(H37,0)) -> 0 | L37: Only bolded amounts are used in this spreadsheet.
A38: 7 | B38: Social Security Tips | I38: =SUM(ROUND(C38,0),ROUND(D38,0),ROUND(E38,0),ROUND(F38,0),ROUND(G38,0),ROUND(H38,0)) -> 0 | L38: Sch. SE, Line 8a
A39: 8 | B39: Allocated Tips | I39: =SUM(ROUND(C39,0),ROUND(D39,0),ROUND(E39,0),ROUND(F39,0),ROUND(G39,0),ROUND(H39,0)) -> 0
A40: 10 | B40: Dependent Care Benefits | I40: =SUM(ROUND(C40,0),ROUND(D40,0),ROUND(E40,0),ROUND(F40,0),ROUND(G40,0),ROUND(H40,0)) -> 0
A41: 11 | B41: Nonqualified plans | I41: =SUM(ROUND(C41,0),ROUND(D41,0),ROUND(E41,0),ROUND(F41,0),ROUND(G41,0),ROUND(H41,0)) -> 0
A42: 12a | B42: See instructions for box 12 | I42: =SUM(ROUND(C42,0),ROUND(D42,0),ROUND(E42,0),ROUND(F42,0),ROUND(G42,0),ROUND(H42,0)) -> 0
A43: 12b | I43: =SUM(ROUND(C43,0),ROUND(D43,0),ROUND(E43,0),ROUND(F43,0),ROUND(G43,0),ROUND(H43,0)) -> 0
A44: 12c | I44: =SUM(ROUND(C44,0),ROUND(D44,0),ROUND(E44,0),ROUND(F44,0),ROUND(G44,0),ROUND(H44,0)) -> 0
A45: 12d | I45: =SUM(ROUND(C45,0),ROUND(D45,0),ROUND(E45,0),ROUND(F45,0),ROUND(G45,0),ROUND(H45,0)) -> 0
A46: 13 | B46: Stat Emp / Retire / 3rd Party Sick | I46: =SUM(ROUND(C46,0),ROUND(D46,0),ROUND(E46,0),ROUND(F46,0),ROUND(G46,0),ROUND(H46,0)) -> 0
A47: 14 | B47: Other | I47: =SUM(ROUND(C47,0),ROUND(D47,0),ROUND(E47,0),ROUND(F47,0),ROUND(G47,0),ROUND(H47,0)) -> 0
A48: 14 | B48: Railroad retire (RRTA) compensation | I48: =SUM(ROUND(C48,0),ROUND(D48,0),ROUND(E48,0),ROUND(F48,0),ROUND(G48,0),ROUND(H48,0)) -> 0
A49: 14 | B49: RRTA medicare tax withheld (see Form CT-2) | I49: =SUM(ROUND(C49,0),ROUND(D49,0),ROUND(E49,0),ROUND(F49,0),ROUND(G49,0),ROUND(H49,0)) -> 0
A50: 16 | B50: State wages, tips, etc. | I50: =SUM(ROUND(C50,0),ROUND(D50,0),ROUND(E50,0),ROUND(F50,0),ROUND(G50,0),ROUND(H50,0)) -> 0
A51: 17 | B51: State income tax | I51: =SUM(ROUND(C51,0),ROUND(D51,0),ROUND(E51,0),ROUND(F51,0),ROUND(G51,0),ROUND(H51,0)) -> 0
A52: 18 | B52: Local wages, tips, etc. | I52: =SUM(ROUND(C52,0),ROUND(D52,0),ROUND(E52,0),ROUND(F52,0),ROUND(G52,0),ROUND(H52,0)) -> 0
A53: 19 | B53: Local income tax | I53: =SUM(ROUND(C53,0),ROUND(D53,0),ROUND(E53,0),ROUND(F53,0),ROUND(G53,0),ROUND(H53,0)) -> 0
B54: Employer count (Spouse) | C54: =IF(AND(C35<>"",C35<>0),1,0) -> 0 | D54: =IF(AND(D35<>"",D35<>0),1,0) -> 0 | E54: =IF(AND(E35<>"",E35<>0),1,0) -> 0 | F54: =IF(AND(F35<>"",F35<>0),1,0) -> 0 | G54: =IF(AND(G35<>"",G35<>0),1,0) -> 0 | H54: =IF(AND(H35<>"",H35<>0),1,0) -> 0 | I54: =SUM(C54:H54) -> 0
B55: ="Medicare wages and tip > "&TEXT('8959'!$H$24,"$0,000") -> Medicare wages and tip > $200,000 | C55: =IF(C36>'8959'!$H$24,TRUE,FALSE) -> FALSE | D55: =IF(D36>'8959'!$H$24,TRUE,FALSE) -> FALSE | E55: =IF(E36>'8959'!$H$24,TRUE,FALSE) -> FALSE | F55: =IF(F36>'8959'!$H$24,TRUE,FALSE) -> FALSE | G55: =IF(G36>'8959'!$H$24,TRUE,FALSE) -> FALSE | H55: =IF(H36>'8959'!$H$24,TRUE,FALSE) -> FALSE | I55: =OR(C26:H26,C55:H55) -> FALSE
B56: ="RRTA > "&TEXT('8959'!$H$24,"$0,000") -> RRTA > $200,000 | C56: =IF(C48>'8959'!$H$24,TRUE,FALSE) -> FALSE | D56: =IF(D48>'8959'!$H$24,TRUE,FALSE) -> FALSE | E56: =IF(E48>'8959'!$H$24,TRUE,FALSE) -> FALSE | F56: =IF(F48>'8959'!$H$24,TRUE,FALSE) -> FALSE | G56: =IF(G48>'8959'!$H$24,TRUE,FALSE) -> FALSE | H56: =IF(H48>'8959'!$H$24,TRUE,FALSE) -> FALSE | I56: =OR(C27:H27,C56:H56) -> FALSE
C57: =IF(AND(I35>MaxSSTax,EmployerCountSpouse=1),"Notify your employer that they withheld "&TEXT(SUM(I35,-MaxSSTax),"$0.00")&" too much Social Security Tax or file Form 843, Claim for Refund and Request for Abatement.","")
B58: =IF(OR(AND(C36="",C37<>""),AND(D36="",D37<>""),AND(E36="",E37<>""),AND(F36="",F37<>"")),"CAUTION: Entering an amount into Line 6 without entering an amount into Line 5 will resutl in a tax calculation error.","")
B59: TOTALs | C59: TOTALs | D59: Used at: | J59: Excess Soc. Sec. Tax Withheld | L59: Used at:
A60: 1 | B60: Wages, tips, other compensation | C60: =SUM(I3,I32) -> 0 | D60: Form 1040, Line 1.
A61: 2 | B61: Federal income tax withheld | C61: =SUM(I4,I33) -> 0 | D61: Form 1040, Line 25a | L61: Only bolded amounts are used in this spreadsheet.
A62: 3 | B62: Social security wages | C62: =SUM(I5,I34) -> 0 | D62: Sch. SE, Line 8a
A63: 4 | B63: Social security tax withheld | C63: =SUM(ROUND(I6,0),ROUND(I35,0)) -> 0 | D63: Line 13a (CTC), Child Tax Credit W/S, Line 11 W/S, Line 6; Form 8812, Line 9 W/S, Line 1 | J63: =ROUND(SUM(J6,J35),0) -> 0 | L63: Sch. 3 (Form 1040), Line 10
A64: 5 | B64: Medicare wages and tips | C64: =SUM(I7,I36) -> 0 | D64: Form 8959, Who Must File, Criterion 3; Form 8959, Additional Medicare Tax, Line 1
A65: 6 | B65: Medicare tax withheld | C65: =SUM(I8,I37) -> 0 | D65: Line 13a, Child Tax Credit Worksheet, Line 14 Worksheet, Line 7; Form 8812, Line 9 W/S, Line 2; Form 8959, Additional Medicare Tax, Line 19
A66: 7 | B66: Social Security Tips | C66: =SUM(I9,I38) -> 0
A67: 8 | B67: Allocated Tips | C67: =SUM(I10,I39) -> 0
A68: 10 | B68: Dependent Care Benefits | C68: =SUM(I11,I40) -> 0 | D68: Form 2441, Part III, Line 12
A69: 11 | B69: Nonqualified plans | C69: =SUM(I12,I41) -> 0
A70: 12a | B70: See instructions for box 12 | C70: =SUM(I13,I42) -> 0
A71: 12b | C71: =SUM(I14,I43) -> 0
A72: 12c | C72: =SUM(I15,I44) -> 0
A73: 12d | C73: =SUM(I16,I45) -> 0
A74: 13 | B74: Stat Emp / Retire / 3rd Party Sick | C74: =SUM(I17,I46) -> 0
A75: 14 | B75: Other | C75: =SUM(I18,I47) -> 0
A76: 14 | B76: Railroad retire (RRTA) compensation | C76: =SUM(I19,I48) -> 0 | D76: Form 8959, Additional Medicare Tax, Who Must File, Criterion 2 and 4; Line 14
A77: 14 | B77: RRTA medicare tax withheld (see Form CT-2) | C77: =SUM(I20,I49) -> 0 | D77: Form 8959, Additional Medicare Tax, Line 23
A78: 16 | B78: State wages, tips, etc. | C78: =SUM(I21,I50) -> 0
A79: 17 | B79: State income tax | C79: =SUM(I22,I51) -> 0 | D79: Sch. A, Line 5
A80: 18 | B80: Local wages, tips, etc. | C80: =SUM(I23,I52) -> 0
A81: 19 | B81: Local income tax | C81: =SUM(I24,I53) -> 0 | D81: Sch. A, Line 5
B85: Table of Contents

Sheet 1099-INT
B1: Information from Form 1099-INT, Interest Income | K1: Notes
C2: =IF(Name_1st_Yours="","Enter your name(s) on the"&CHAR(10)&"sheet lableled '1040'",IF(File_Marr_Joint<>"",NameYours&CHAR(10)&" and "&NameSpouse,NameYours)) -> Enter your name(s) on the sheet lableled '1040' | D2: Payer #1 | E2: Payer #2 | F2: Payer #3 | G2: Payer #4 | H2: Payer #5 | K2: Date:
C3: PAYER's name
C4: PAYER's Federal ID number
C5: Account number
B6: 1 | C6: Interest income | AA6: =ROUND(D6,0) -> 0 | AB6: =ROUND(E6,0) -> 0 | AC6: =ROUND(F6,0) -> 0 | AD6: =ROUND(G6,0) -> 0 | AE6: =ROUND(H6,0) -> 0
B7: 2 | C7: Early withdrawal penalty | AA7: =ROUND(D7,0) -> 0 | AB7: =ROUND(E7,0) -> 0 | AC7: =ROUND(F7,0) -> 0 | AD7: =ROUND(G7,0) -> 0 | AE7: =ROUND(H7,0) -> 0
B8: 3 | C8: Interest on U.S. Savings Bonds & Treas. Obligations | AA8: =ROUND(D8,0) -> 0 | AB8: =ROUND(E8,0) -> 0 | AC8: =ROUND(F8,0) -> 0 | AD8: =ROUND(G8,0) -> 0 | AE8: =ROUND(H8,0) -> 0
B9: 3A | C9: Include Line 3 on Schedule B, Line 1? (Y / N) | D9: N | E9: N | F9: N | G9: N | H9: N
B10: 4 | C10: Federal income tax withheld | AA10: =ROUND(D10,0) -> 0 | AB10: =ROUND(E10,0) -> 0 | AC10: =ROUND(F10,0) -> 0 | AD10: =ROUND(G10,0) -> 0 | AE10: =ROUND(H10,0) -> 0
B11: 5 | C11: Investment expenses | AA11: =ROUND(D11,0) -> 0 | AB11: =ROUND(E11,0) -> 0 | AC11: =ROUND(F11,0) -> 0 | AD11: =ROUND(G11,0) -> 0 | AE11: =ROUND(H11,0) -> 0
B12: 6 | C12: Foreign tax paid | I12: =IF(SUM(D12:H12)>0,"Check Form 1116, Foreign Tax Credit","") | AA12: =ROUND(D12,0) -> 0 | AB12: =ROUND(E12,0) -> 0 | AC12: =ROUND(F12,0) -> 0 | AD12: =ROUND(G12,0) -> 0 | AE12: =ROUND(H12,0) -> 0
B13: 7 | C13: Foreign country or U.S. possession | AA13: =ROUND(D13,0) -> 0 | AB13: =ROUND(E13,0) -> 0 | AC13: =ROUND(F13,0) -> 0 | AD13: =ROUND(G13,0) -> 0 | AE13: =ROUND(H13,0) -> 0
B14: 8 | C14: Tax-exempt interest | AA14: =ROUND(D14,0) -> 0 | AB14: =ROUND(E14,0) -> 0 | AC14: =ROUND(F14,0) -> 0 | AD14: =ROUND(G14,0) -> 0 | AE14: =ROUND(H14,0) -> 0
B15: 9 | C15: Specified private activity bond interest | AA15: =ROUND(D15,0) -> 0 | AB15: =ROUND(E15,0) -> 0 | AC15: =ROUND(F15,0) -> 0 | AD15: =ROUND(G15,0) -> 0 | AE15: =ROUND(H15,0) -> 0
B17: 10 | C17: Market discount | AA17: =ROUND(D17,0) -> 0 | AB17: =ROUND(E17,0) -> 0 | AC17: =ROUND(F17,0) -> 0 | AD17: =ROUND(G17,0) -> 0 | AE17: =ROUND(H17,0) -> 0
B18: 11 | C18: Bond premium | AA18: =ROUND(D18,0) -> 0 | AB18: =ROUND(E18,0) -> 0 | AC18: =ROUND(F18,0) -> 0 | AD18: =ROUND(G18,0) -> 0 | AE18: =ROUND(H18,0) -> 0
B19: 12 | C19: Bond premium on Treasury obligations | AA19: =ROUND(D19,0) -> 0 | AB19: =ROUND(E19,0) -> 0 | AC19: =ROUND(F19,0) -> 0 | AD19: =ROUND(G19,0) -> 0 | AE19: =ROUND(H19,0) -> 0
B20: 13 | C20: Bond premium on tax–exempt bond | AA20: =ROUND(D20,0) -> 0 | AB20: =ROUND(E20,0) -> 0 | AC20: =ROUND(F20,0) -> 0 | AD20: =ROUND(G20,0) -> 0 | AE20: =ROUND(H20,0) -> 0
B21: 14 | C21: Tax-exempt and tax credit bond CUSIP no. | AA21: =ROUND(D21,0) -> 0 | AB21: =ROUND(E21,0) -> 0 | AC21: =ROUND(F21,0) -> 0 | AD21: =ROUND(G21,0) -> 0 | AE21: =ROUND(H21,0) -> 0
B22: 15 | C22: State
B23: 17 | C23: State identification no.
B24: 17 | C24: State tax withheld | AA24: =ROUND(D24,0) -> 0 | AB24: =ROUND(E24,0) -> 0 | AC24: =ROUND(F24,0) -> 0 | AD24: =ROUND(G24,0) -> 0 | AE24: =ROUND(H24,0) -> 0
B25: Only bolded amounts are used in this spreadsheet.
D26: =IF(OR(LEFT(D9,1)="Y",LEFT(D9,1)="y"),D8,"") | E26: =IF(OR(LEFT(E9,1)="Y",LEFT(E9,1)="y"),E8,"") | F26: =IF(OR(LEFT(F9,1)="Y",LEFT(F9,1)="y"),F8,"") | G26: =IF(OR(LEFT(G9,1)="Y",LEFT(G9,1)="y"),G8,"") | H26: =IF(OR(LEFT(H9,1)="Y",LEFT(H9,1)="y"),H8,"")
D27: =IF(D3<>"",D3,"") | E27: =IF(E3<>"",E3,"") | F27: =IF(F3<>"",F3,"") | G27: =IF(G3<>"",G3,"") | H27: =IF(H3<>"",H3,"")
D28: =IF(D4<>"", " - "&D4,"") | E28: =IF(E4<>"", " - "&E4,"") | F28: =IF(F4<>"", " - "&F4,"") | G28: =IF(G4<>"", " - "&G4,"") | H28: =IF(H4<>"", " - "&H4,"")
D29: =IF(D5<>""," - "&D5,"") | E29: =IF(E5<>""," - "&E5,"") | F29: =IF(F5<>""," - "&F5,"") | G29: =IF(G5<>""," - "&G5,"") | H29: =IF(H5<>""," - "&H5,"")
D30: =D27&D28&D29 | E30: =E27&E28&E29 | F30: =F27&F28&F29 | G30: =G27&G28&G29 | H30: =H27&H28&H29
C31: =IF(Name_1st_Yours="","Enter your name(s) on the"&CHAR(10)&"sheet lableled '1040'",IF(File_Marr_Joint<>"",NameYours&CHAR(10)&" and "&NameSpouse,NameYours)) -> Enter your name(s) on the sheet lableled '1040' | D31: Payer #6 | E31: Payer #7 | F31: Payer #8 | G31: Payer #9 | H31: Payer #10
C32: PAYER's name
C33: PAYER's Federal ID number
C34: Account number
B35: 1 | C35: Interest income | AA35: =ROUND(D35,0) -> 0 | AB35: =ROUND(E35,0) -> 0 | AC35: =ROUND(F35,0) -> 0 | AD35: =ROUND(G35,0) -> 0 | AE35: =ROUND(H35,0) -> 0
B36: 2 | C36: Early withdrawal penalty | AA36: =ROUND(D36,0) -> 0 | AB36: =ROUND(E36,0) -> 0 | AC36: =ROUND(F36,0) -> 0 | AD36: =ROUND(G36,0) -> 0 | AE36: =ROUND(H36,0) -> 0
B37: 3 | C37: Interest on U.S. Savings Bonds & Treas. Obligations | AA37: =ROUND(D37,0) -> 0 | AB37: =ROUND(E37,0) -> 0 | AC37: =ROUND(F37,0) -> 0 | AD37: =ROUND(G37,0) -> 0 | AE37: =ROUND(H37,0) -> 0
B38: 3A | C38: Include Line 3 on Schedule B, Line 1? (Y / N) | D38: N | E38: N | F38: N | G38: N | H38: N
B39: 4 | C39: Federal income tax withheld | AA39: =ROUND(D39,0) -> 0 | AB39: =ROUND(E39,0) -> 0 | AC39: =ROUND(F39,0) -> 0 | AD39: =ROUND(G39,0) -> 0 | AE39: =ROUND(H39,0) -> 0
B40: 5 | C40: Investment expenses | AA40: =ROUND(D40,0) -> 0 | AB40: =ROUND(E40,0) -> 0 | AC40: =ROUND(F40,0) -> 0 | AD40: =ROUND(G40,0) -> 0 | AE40: =ROUND(H40,0) -> 0
B41: 6 | C41: Foreign tax paid | I41: =IF(SUM(D41:H41)>0,"Check Form 1116, Foreign Tax Credit","") | AA41: =ROUND(D41,0) -> 0 | AB41: =ROUND(E41,0) -> 0 | AC41: =ROUND(F41,0) -> 0 | AD41: =ROUND(G41,0) -> 0 | AE41: =ROUND(H41,0) -> 0
B42: 7 | C42: Foreign country or U.S. possession | AA42: =ROUND(D42,0) -> 0 | AB42: =ROUND(E42,0) -> 0 | AC42: =ROUND(F42,0) -> 0 | AD42: =ROUND(G42,0) -> 0 | AE42: =ROUND(H42,0) -> 0
B43: 8 | C43: Tax-exempt interest | AA43: =ROUND(D43,0) -> 0 | AB43: =ROUND(E43,0) -> 0 | AC43: =ROUND(F43,0) -> 0 | AD43: =ROUND(G43,0) -> 0 | AE43: =ROUND(H43,0) -> 0
B44: 9 | C44: Specified private activity bond interest | AA44: =ROUND(D44,0) -> 0 | AB44: =ROUND(E44,0) -> 0 | AC44: =ROUND(F44,0) -> 0 | AD44: =ROUND(G44,0) -> 0 | AE44: =ROUND(H44,0) -> 0
B46: 10 | C46: Market discount | AA46: =ROUND(D46,0) -> 0 | AB46: =ROUND(E46,0) -> 0 | AC46: =ROUND(F46,0) -> 0 | AD46: =ROUND(G46,0) -> 0 | AE46: =ROUND(H46,0) -> 0
B47: 11 | C47: Bond premium | AA47: =ROUND(D47,0) -> 0 | AB47: =ROUND(E47,0) -> 0 | AC47: =ROUND(F47,0) -> 0 | AD47: =ROUND(G47,0) -> 0 | AE47: =ROUND(H47,0) -> 0
B48: 12 | C48: Bond premium on Treasury obligations | AA48: =ROUND(D48,0) -> 0 | AB48: =ROUND(E48,0) -> 0 | AC48: =ROUND(F48,0) -> 0 | AD48: =ROUND(G48,0) -> 0 | AE48: =ROUND(H48,0) -> 0
B49: 13 | C49: Bond premium on tax–exempt bond | AA49: =ROUND(D49,0) -> 0 | AB49: =ROUND(E49,0) -> 0 | AC49: =ROUND(F49,0) -> 0 | AD49: =ROUND(G49,0) -> 0 | AE49: =ROUND(H49,0) -> 0
B50: 14 | C50: Tax-exempt and tax credit bond CUSIP no. | AA50: =ROUND(D50,0) -> 0 | AB50: =ROUND(E50,0) -> 0 | AC50: =ROUND(F50,0) -> 0 | AD50: =ROUND(G50,0) -> 0 | AE50: =ROUND(H50,0) -> 0
B51: 15 | C51: State
B52: 17 | C52: State identification no.
B53: 17 | C53: State tax withheld | AA53: =ROUND(D53,0) -> 0 | AB53: =ROUND(E53,0) -> 0 | AC53: =ROUND(F53,0) -> 0 | AD53: =ROUND(G53,0) -> 0 | AE53: =ROUND(H53,0) -> 0
B54: Only bolded amounts are used in this spreadsheet.
D55: =IF(OR(LEFT(D38,1)="Y",LEFT(D38,1)="y"),D37,"") | E55: =IF(OR(LEFT(E38,1)="Y",LEFT(E38,1)="y"),E37,"") | F55: =IF(OR(LEFT(F38,1)="Y",LEFT(F38,1)="y"),F37,"") | G55: =IF(OR(LEFT(G38,1)="Y",LEFT(G38,1)="y"),G37,"") | H55: =IF(OR(LEFT(H38,1)="Y",LEFT(H38,1)="y"),H37,"")
D56: =IF(D32<>"",D32,"") | E56: =IF(E32<>"",E32,"") | F56: =IF(F32<>"",F32,"") | G56: =IF(G32<>"",G32,"") | H56: =IF(H32<>"",H32,"")
D57: =IF(D33<>"", " - "&D33,"") | E57: =IF(E33<>"", " - "&E33,"") | F57: =IF(F33<>"", " - "&F33,"") | G57: =IF(G33<>"", " - "&G33,"") | H57: =IF(H33<>"", " - "&H33,"")
D58: =IF(D34<>""," - "&D34,"") | E58: =IF(E34<>""," - "&E34,"") | F58: =IF(F34<>""," - "&F34,"") | G58: =IF(G34<>""," - "&G34,"") | H58: =IF(H34<>""," - "&H34,"")
D59: =D56&D57&D58 | E59: =E56&E57&E58 | F59: =F56&F57&F58 | G59: =G56&G57&G58 | H59: =H56&H57&H58
B60: Information from Form 1099-INT, Interest Income
C61: =IF(Name_1st_Yours="","Enter your name(s) on the"&CHAR(10)&"sheet lableled '1040'",IF(File_Marr_Joint<>"",NameYours&CHAR(10)&" and "&NameSpouse,NameYours)) -> Enter your name(s) on the sheet lableled '1040' | D61: Payer #11 | E61: Payer #12 | F61: Payer #13 | G61: Payer #14 | H61: Payer #15 | I61: Total | J61: Used at:
C62: PAYER's name
C63: PAYER's Federal ID number
C64: Account number | J64: =IF(AND(ForeignTaxPaid<>"",ForeignTaxPaid>0),"Check Form 1116, Foreign Tax Credit","")
B65: 1 | C65: Interest income | I65: =SUM(AA6:AE6,AA35:AE35,AA65:AE65) -> 0 | J65: Sch. B, Line 1 | AA65: =ROUND(D65,0) -> 0 | AB65: =ROUND(E65,0) -> 0 | AC65: =ROUND(F65,0) -> 0 | AD65: =ROUND(G65,0) -> 0 | AE65: =ROUND(H65,0) -> 0
B66: 2 | C66: Early withdrawal penalty | I66: =SUM(AA7:AE7,AA36:AE36,AA66:AE66) -> 0 | J66: Form 1040, Sch. 1, Line 30 | AA66: =ROUND(D66,0) -> 0 | AB66: =ROUND(E66,0) -> 0 | AC66: =ROUND(F66,0) -> 0 | AD66: =ROUND(G66,0) -> 0 | AE66: =ROUND(H66,0) -> 0
B67: 3 | C67: Interest on U.S. Savings Bonds & Treas. Obligations | I67: =SUM(AA8:AE8,AA37:AE37,AA67:AE67) -> 0 | J67: Sch. B, Line 1 (If line 3A is "Y") | AA67: =ROUND(D67,0) -> 0 | AB67: =ROUND(E67,0) -> 0 | AC67: =ROUND(F67,0) -> 0 | AD67: =ROUND(G67,0) -> 0 | AE67: =ROUND(H67,0) -> 0
B68: 3A | C68: Include Line 3 on Schedule B, Line 1? (Y / N) | D68: N | E68: N | F68: N | G68: N | H68: N
B69: 4 | C69: Federal income tax withheld | I69: =SUM(AA10:AE10,AA39:AE39,AA69:AE69) -> 0 | J69: Form 1040, Line 25b | AA69: =ROUND(D69,0) -> 0 | AB69: =ROUND(E69,0) -> 0 | AC69: =ROUND(F69,0) -> 0 | AD69: =ROUND(G69,0) -> 0 | AE69: =ROUND(H69,0) -> 0
B70: 5 | C70: Investment expenses | I70: =SUM(AA11:AE11,AA40:AE40,AA70:AE70) -> 0 | J70: Consideration (by you) in Sch. A, Line 9 | AA70: =ROUND(D70,0) -> 0 | AB70: =ROUND(E70,0) -> 0 | AC70: =ROUND(F70,0) -> 0 | AD70: =ROUND(G70,0) -> 0 | AE70: =ROUND(H70,0) -> 0
B71: 6 | C71: Foreign tax paid | I71: =SUM(AA12:AE12,AA41:AE41,AA71:AE71) -> 0 | J71: Sch. 3, Line 48 OR Form 1116 (Cell A8) | AA71: =ROUND(D71,0) -> 0 | AB71: =ROUND(E71,0) -> 0 | AC71: =ROUND(F71,0) -> 0 | AD71: =ROUND(G71,0) -> 0 | AE71: =ROUND(H71,0) -> 0
B72: 7 | C72: Foreign country or U.S. possession | I72: =" - - - -" -> - - - - | J72: =IF(ForeignTaxPaid_INT>0,"Check Form 1116, Foreign Tax Credit","") | AA72: =ROUND(D72,0) -> 0 | AB72: =ROUND(E72,0) -> 0 | AC72: =ROUND(F72,0) -> 0 | AD72: =ROUND(G72,0) -> 0 | AE72: =ROUND(H72,0) -> 0
B73: 8 | C73: Tax-exempt interest | I73: =SUM(AA14:AE14,AA43:AE43,AA73:AE73) -> 0 | J73: Form 1040, Line 2a | AA73: =ROUND(D73,0) -> 0 | AB73: =ROUND(E73,0) -> 0 | AC73: =ROUND(F73,0) -> 0 | AD73: =ROUND(G73,0) -> 0 | AE73: =ROUND(H73,0) -> 0
B74: 9 | C74: Specified private activity bond interest | I74: =SUM(AA15:AE15,AA44:AE44,AA74:AE74) -> 0 | J74: Form 6251, Line 2g | AA74: =ROUND(D74,0) -> 0 | AB74: =ROUND(E74,0) -> 0 | AC74: =ROUND(F74,0) -> 0 | AD74: =ROUND(G74,0) -> 0 | AE74: =ROUND(H74,0) -> 0
I75: =SUM(AA16:AE16,AA45:AE45,AA75:AE75) -> 0
B76: 10 | C76: Market discount | I76: =SUM(AA17:AE17,AA46:AE46,AA76:AE76) -> 0 | J76: Sch. B, Line 1 | AA76: =ROUND(D76,0) -> 0 | AB76: =ROUND(E76,0) -> 0 | AC76: =ROUND(F76,0) -> 0 | AD76: =ROUND(G76,0) -> 0 | AE76: =ROUND(H76,0) -> 0
B77: 11 | C77: Bond premium | I77: =SUM(AA18:AE18,AA47:AE47,AA77:AE77) -> 0 | AA77: =ROUND(D77,0) -> 0 | AB77: =ROUND(E77,0) -> 0 | AC77: =ROUND(F77,0) -> 0 | AD77: =ROUND(G77,0) -> 0 | AE77: =ROUND(H77,0) -> 0
B78: 12 | C78: Bond premium on Treasury obligations | I78: =SUM(AA19:AE19,AA48:AE48,AA78:AE78) -> 0 | AA78: =ROUND(D78,0) -> 0 | AB78: =ROUND(E78,0) -> 0 | AC78: =ROUND(F78,0) -> 0 | AD78: =ROUND(G78,0) -> 0 | AE78: =ROUND(H78,0) -> 0
B79: 13 | C79: Bond premium on tax–exempt bond | I79: =" - - - -" -> - - - - | AA79: =ROUND(D79,0) -> 0 | AB79: =ROUND(E79,0) -> 0 | AC79: =ROUND(F79,0) -> 0 | AD79: =ROUND(G79,0) -> 0 | AE79: =ROUND(H79,0) -> 0
B80: 14 | C80: Tax-exempt and tax credit bond CUSIP no. | I80: =" - - - -" -> - - - - | AA80: =ROUND(D80,0) -> 0 | AB80: =ROUND(E80,0) -> 0 | AC80: =ROUND(F80,0) -> 0 | AD80: =ROUND(G80,0) -> 0 | AE80: =ROUND(H80,0) -> 0
B81: 15 | C81: State | I81: =" - - - -" -> - - - -
B82: 17 | C82: State identification no. | I82: =" - - - -" -> - - - -
B83: 17 | C83: State tax withheld | I83: =SUM(D24:H24,D53:H53,D83:H83) -> 0 | J83: Sch. A, Line 5a and Form 8960, Line 9b | AA83: =ROUND(D83,0) -> 0 | AB83: =ROUND(E83,0) -> 0 | AC83: =ROUND(F83,0) -> 0 | AD83: =ROUND(G83,0) -> 0 | AE83: =ROUND(H83,0) -> 0
B84: Only bolded amounts are used in this spreadsheet.
D85: =IF(OR(LEFT(D68,1)="Y",LEFT(D68,1)="y"),D67,"") | E85: =IF(OR(LEFT(E68,1)="Y",LEFT(E68,1)="y"),E67,"") | F85: =IF(OR(LEFT(F68,1)="Y",LEFT(F68,1)="y"),F67,"") | G85: =IF(OR(LEFT(G68,1)="Y",LEFT(G68,1)="y"),G67,"") | H85: =IF(OR(LEFT(H68,1)="Y",LEFT(H68,1)="y"),H67,"")
D86: =IF(D62<>"",D62,"") | E86: =IF(E62<>"",E62,"") | F86: =IF(F62<>"",F62,"") | G86: =IF(G62<>"",G62,"") | H86: =IF(H62<>"",H62,"")
D87: =IF(D63<>"", " - "&D63,"") | E87: =IF(E63<>"", " - "&E63,"") | F87: =IF(F63<>"", " - "&F63,"") | G87: =IF(G63<>"", " - "&G63,"") | H87: =IF(H63<>"", " - "&H63,"")
D88: =IF(D64<>""," - "&D64,"") | E88: =IF(E64<>""," - "&E64,"") | F88: =IF(F64<>""," - "&F64,"") | G88: =IF(G64<>""," - "&G64,"") | H88: =IF(H64<>""," - "&H64,"")
D89: =D86&D87&D88 | E89: =E86&E87&E88 | F89: =F86&F87&F88 | G89: =G86&G87&G88 | H89: =H86&H87&H88
C93: Table of Contents

Sheet 1099-DIV
B1: Information from Form 1099-DIV, Dividends and Distributions | K1: Notes
C2: =IF(Name_1st_Yours="","Enter your name(s) on the"&CHAR(10)&"sheet labeled '1040'",Names) -> Enter your name(s) on the sheet labeled '1040' | D2: Payer #1 | E2: Payer #2 | F2: Payer #3 | G2: Payer #4 | H2: Payer #5 | K2: Date:
C3: PAYER's name
C4: PAYER's Federal ID number
C5: Account number
B6: 1a | C6: Total ordinary dividends | I6: =IF(I25,"Error: All qualified dividends must be included in","") | AA6: =ROUND(D6,2) -> 0 | AB6: =ROUND(E6,2) -> 0 | AC6: =ROUND(F6,2) -> 0 | AD6: =ROUND(G6,2) -> 0 | AE6: =ROUND(H6,2) -> 0
B7: 1b | C7: Qualified dividends | I7: =IF(I25,"the Total ordinary dividend amount.","") | AA7: =ROUND(D7,2) -> 0 | AB7: =ROUND(E7,2) -> 0 | AC7: =ROUND(F7,2) -> 0 | AD7: =ROUND(G7,2) -> 0 | AE7: =ROUND(H7,2) -> 0
B8: 2a | C8: Total capital gain distr. | AA8: =ROUND(D8,2) -> 0 | AB8: =ROUND(E8,2) -> 0 | AC8: =ROUND(F8,2) -> 0 | AD8: =ROUND(G8,2) -> 0 | AE8: =ROUND(H8,2) -> 0
B9: 2b | C9: Unrecap. Sec. 1250 gain | AA9: =ROUND(D9,2) -> 0 | AB9: =ROUND(E9,2) -> 0 | AC9: =ROUND(F9,2) -> 0 | AD9: =ROUND(G9,2) -> 0 | AE9: =ROUND(H9,2) -> 0
B10: 2c | C10: Section 1202 gain | AA10: =ROUND(D10,2) -> 0 | AB10: =ROUND(E10,2) -> 0 | AC10: =ROUND(F10,2) -> 0 | AD10: =ROUND(G10,2) -> 0 | AE10: =ROUND(H10,2) -> 0
B11: 2d | C11: Collectibles (28%) gain | AA11: =ROUND(D11,2) -> 0 | AB11: =ROUND(E11,2) -> 0 | AC11: =ROUND(F11,2) -> 0 | AD11: =ROUND(G11,2) -> 0 | AE11: =ROUND(H11,2) -> 0
B12: 3 | C12: Nondividend distributions | AA12: =ROUND(D12,2) -> 0 | AB12: =ROUND(E12,2) -> 0 | AC12: =ROUND(F12,2) -> 0 | AD12: =ROUND(G12,2) -> 0 | AE12: =ROUND(H12,2) -> 0
B13: 4 | C13: Federal income tax withheld | AA13: =ROUND(D13,2) -> 0 | AB13: =ROUND(E13,2) -> 0 | AC13: =ROUND(F13,2) -> 0 | AD13: =ROUND(G13,2) -> 0 | AE13: =ROUND(H13,2) -> 0
B14: 5 | C14: Section 199A dividends | AA14: =ROUND(D14,2) -> 0 | AB14: =ROUND(E14,2) -> 0 | AC14: =ROUND(F14,2) -> 0 | AD14: =ROUND(G14,2) -> 0 | AE14: =ROUND(H14,2) -> 0
B15: 6 | C15: Investment expenses | AA15: =ROUND(D15,2) -> 0 | AB15: =ROUND(E15,2) -> 0 | AC15: =ROUND(F15,2) -> 0 | AD15: =ROUND(G15,2) -> 0 | AE15: =ROUND(H15,2) -> 0
B16: 7 | C16: Foreign tax paid | I16: =IF(SUM(D16:H16)>0,"Check Form 1116, Foreign Tax Credit","") | AA16: =ROUND(D16,2) -> 0 | AB16: =ROUND(E16,2) -> 0 | AC16: =ROUND(F16,2) -> 0 | AD16: =ROUND(G16,2) -> 0 | AE16: =ROUND(H16,2) -> 0
B17: 8 | C17: Foreign country or U.S. possession
B18: 9 | C18: Cash liquidation distributions | AA18: =ROUND(D18,2) -> 0 | AB18: =ROUND(E18,2) -> 0 | AC18: =ROUND(F18,2) -> 0 | AD18: =ROUND(G18,2) -> 0 | AE18: =ROUND(H18,2) -> 0
B19: 10 | C19: Noncash liquidation distributions | AA19: =ROUND(D19,2) -> 0 | AB19: =ROUND(E19,2) -> 0 | AC19: =ROUND(F19,2) -> 0 | AD19: =ROUND(G19,2) -> 0 | AE19: =ROUND(H19,2) -> 0
B20: 11 | C20: Exempt-interest dividends | AA20: =ROUND(D20,2) -> 0 | AB20: =ROUND(E20,2) -> 0 | AC20: =ROUND(F20,2) -> 0 | AD20: =ROUND(G20,2) -> 0 | AE20: =ROUND(H20,2) -> 0
B21: 12 | C21: Specified private activity bond interest dividends | AA21: =ROUND(D21,2) -> 0 | AB21: =ROUND(E21,2) -> 0 | AC21: =ROUND(F21,2) -> 0 | AD21: =ROUND(G21,2) -> 0 | AE21: =ROUND(H21,2) -> 0
B22: 13 | C22: State
B23: 14 | C23: State identification no.
B24: 15 | C24: State tax withheld | AA24: =ROUND(D24,2) -> 0 | AB24: =ROUND(E24,2) -> 0 | AC24: =ROUND(F24,2) -> 0 | AD24: =ROUND(G24,2) -> 0 | AE24: =ROUND(H24,2) -> 0
B25: Only bolded amounts are used in this spreadsheet. | D25: =D7>D6 -> FALSE | E25: =E7>E6 -> FALSE | F25: =F7>F6 -> FALSE | G25: =G7>G6 -> FALSE | H25: =H7>H6 -> FALSE | I25: =OR(D25:H25) -> FALSE
D26: =IF(D3<>"",D3,"") | E26: =IF(E3<>"",E3,"") | F26: =IF(F3<>"",F3,"") | G26: =IF(G3<>"",G3,"") | H26: =IF(H3<>"",H3,"")
D27: =IF(D4<>"", " - "&D4,"") | E27: =IF(E4<>"", " - "&E4,"") | F27: =IF(F4<>"", " - "&F4,"") | G27: =IF(G4<>"", " - "&G4,"") | H27: =IF(H4<>"", " - "&H4,"")
D28: =IF(D5<>""," - "&D5,"") | E28: =IF(E5<>""," - "&E5,"") | F28: =IF(F5<>""," - "&F5,"") | G28: =IF(G5<>""," - "&G5,"") | H28: =IF(H5<>""," - "&H5,"")
D29: =IF(D6="","",D26&D27&D28) | E29: =IF(E6="","",E26&E27&E28) | F29: =IF(F6="","",F26&F27&F28) | G29: =IF(G6="","",G26&G27&G28) | H29: =IF(H6="","",H26&H27&H28)
C30: =IF(Name_1st_Yours="","Enter your name(s) on the"&CHAR(10)&"sheet labeled '1040'",Names) -> Enter your name(s) on the sheet labeled '1040' | D30: Payer #6 | E30: Payer #7 | F30: Payer #8 | G30: Payer #9 | H30: Payer #10
C31: PAYER's name
C32: PAYER's Federal ID number
C33: Account number
B34: 1a | C34: Total ordinary dividends | I34: =IF(I53,"Error: All qualified dividends must be included in","") | AA34: =ROUND(D34,2) -> 0 | AB34: =ROUND(E34,2) -> 0 | AC34: =ROUND(F34,2) -> 0 | AD34: =ROUND(G34,2) -> 0 | AE34: =ROUND(H34,2) -> 0
B35: 1b | C35: Qualified dividends | I35: =IF(I53,"the Total ordinary dividend amount.","") | AA35: =ROUND(D35,2) -> 0 | AB35: =ROUND(E35,2) -> 0 | AC35: =ROUND(F35,2) -> 0 | AD35: =ROUND(G35,2) -> 0 | AE35: =ROUND(H35,2) -> 0
B36: 2a | C36: Total capital gain distr. | AA36: =ROUND(D36,2) -> 0 | AB36: =ROUND(E36,2) -> 0 | AC36: =ROUND(F36,2) -> 0 | AD36: =ROUND(G36,2) -> 0 | AE36: =ROUND(H36,2) -> 0
B37: 2b | C37: Unrecap. Sec. 1250 gain | AA37: =ROUND(D37,2) -> 0 | AB37: =ROUND(E37,2) -> 0 | AC37: =ROUND(F37,2) -> 0 | AD37: =ROUND(G37,2) -> 0 | AE37: =ROUND(H37,2) -> 0
B38: 2c | C38: Section 1202 gain | AA38: =ROUND(D38,2) -> 0 | AB38: =ROUND(E38,2) -> 0 | AC38: =ROUND(F38,2) -> 0 | AD38: =ROUND(G38,2) -> 0 | AE38: =ROUND(H38,2) -> 0
B39: 2d | C39: Collectibles (28%) gain | AA39: =ROUND(D39,2) -> 0 | AB39: =ROUND(E39,2) -> 0 | AC39: =ROUND(F39,2) -> 0 | AD39: =ROUND(G39,2) -> 0 | AE39: =ROUND(H39,2) -> 0
B40: 3 | C40: Nondividend distributions | AA40: =ROUND(D40,2) -> 0 | AB40: =ROUND(E40,2) -> 0 | AC40: =ROUND(F40,2) -> 0 | AD40: =ROUND(G40,2) -> 0 | AE40: =ROUND(H40,2) -> 0
B41: 4 | C41: Federal income tax withheld | AA41: =ROUND(D41,2) -> 0 | AB41: =ROUND(E41,2) -> 0 | AC41: =ROUND(F41,2) -> 0 | AD41: =ROUND(G41,2) -> 0 | AE41: =ROUND(H41,2) -> 0
B42: 5 | C42: Section 199A dividends | AA42: =ROUND(D42,2) -> 0 | AB42: =ROUND(E42,2) -> 0 | AC42: =ROUND(F42,2) -> 0 | AD42: =ROUND(G42,2) -> 0 | AE42: =ROUND(H42,2) -> 0
B43: 6 | C43: Investment expenses | AA43: =ROUND(D43,2) -> 0 | AB43: =ROUND(E43,2) -> 0 | AC43: =ROUND(F43,2) -> 0 | AD43: =ROUND(G43,2) -> 0 | AE43: =ROUND(H43,2) -> 0
B44: 7 | C44: Foreign tax paid | I44: =IF(SUM(D44:H44)>0,"Check Form 1116, Foreign Tax Credit","") | AA44: =ROUND(D44,2) -> 0 | AB44: =ROUND(E44,2) -> 0 | AC44: =ROUND(F44,2) -> 0 | AD44: =ROUND(G44,2) -> 0 | AE44: =ROUND(H44,2) -> 0
B45: 8 | C45: Foreign country or U.S. possession
B46: 9 | C46: Cash liquidation distributions | AA46: =ROUND(D46,2) -> 0 | AB46: =ROUND(E46,2) -> 0 | AC46: =ROUND(F46,2) -> 0 | AD46: =ROUND(G46,2) -> 0 | AE46: =ROUND(H46,2) -> 0
B47: 10 | C47: Noncash liquidation distributions | AA47: =ROUND(D47,2) -> 0 | AB47: =ROUND(E47,2) -> 0 | AC47: =ROUND(F47,2) -> 0 | AD47: =ROUND(G47,2) -> 0 | AE47: =ROUND(H47,2) -> 0
B48: 11 | C48: Exempt-interest dividends | AA48: =ROUND(D48,2) -> 0 | AB48: =ROUND(E48,2) -> 0 | AC48: =ROUND(F48,2) -> 0 | AD48: =ROUND(G48,2) -> 0 | AE48: =ROUND(H48,2) -> 0
B49: 12 | C49: Specified private activity bond interest dividends | AA49: =ROUND(D49,2) -> 0 | AB49: =ROUND(E49,2) -> 0 | AC49: =ROUND(F49,2) -> 0 | AD49: =ROUND(G49,2) -> 0 | AE49: =ROUND(H49,2) -> 0
B50: 13 | C50: State
B51: 14 | C51: State identification no.
B52: 15 | C52: State tax withheld | AA52: =ROUND(D52,2) -> 0 | AB52: =ROUND(E52,2) -> 0 | AC52: =ROUND(F52,2) -> 0 | AD52: =ROUND(G52,2) -> 0 | AE52: =ROUND(H52,2) -> 0
B53: Only bolded amounts are used in this spreadsheet. | D53: =D35>D34 -> FALSE | E53: =E35>E34 -> FALSE | F53: =F35>F34 -> FALSE | G53: =G35>G34 -> FALSE | H53: =H35>H34 -> FALSE | I53: =OR(D53:H53) -> FALSE
D54: =IF(D31<>"",D31,"") | E54: =IF(E31<>"",E31,"") | F54: =IF(F31<>"",F31,"") | G54: =IF(G31<>"",G31,"") | H54: =IF(H31<>"",H31,"")
D55: =IF(D32<>"", " - "&D32,"") | E55: =IF(E32<>"", " - "&E32,"") | F55: =IF(F32<>"", " - "&F32,"") | G55: =IF(G32<>"", " - "&G32,"") | H55: =IF(H32<>"", " - "&H32,"")
D56: =IF(D33<>""," - "&D33,"") | E56: =IF(E33<>""," - "&E33,"") | F56: =IF(F33<>""," - "&F33,"") | G56: =IF(G33<>""," - "&G33,"") | H56: =IF(H33<>""," - "&H33,"")
D57: =IF(D34="","",D54&D55&D56) | E57: =IF(E34="","",E54&E55&E56) | F57: =IF(F34="","",F54&F55&F56) | G57: =IF(G34="","",G54&G55&G56) | H57: =IF(H34="","",H54&H55&H56)
C58: =IF(Name_1st_Yours="","Enter your name(s) on the"&CHAR(10)&"sheet labeled '1040'",Names) -> Enter your name(s) on the sheet labeled '1040' | D58: Payer #11 | E58: Payer #12 | F58: Payer #13 | G58: Payer #14 | H58: Payer #15
C59: PAYER's name
C60: PAYER's Federal ID number
C61: Account number
B62: 1a | C62: Total ordinary dividends | I62: =IF(I81,"Error: All qualified dividends must be included in","") | AA62: =ROUND(D62,2) -> 0 | AB62: =ROUND(E62,2) -> 0 | AC62: =ROUND(F62,2) -> 0 | AD62: =ROUND(G62,2) -> 0 | AE62: =ROUND(H62,2) -> 0
B63: 1b | C63: Qualified dividends | I63: =IF(I81,"the Total ordinary dividend amount.","") | AA63: =ROUND(D63,2) -> 0 | AB63: =ROUND(E63,2) -> 0 | AC63: =ROUND(F63,2) -> 0 | AD63: =ROUND(G63,2) -> 0 | AE63: =ROUND(H63,2) -> 0
B64: 2a | C64: Total capital gain distr. | AA64: =ROUND(D64,2) -> 0 | AB64: =ROUND(E64,2) -> 0 | AC64: =ROUND(F64,2) -> 0 | AD64: =ROUND(G64,2) -> 0 | AE64: =ROUND(H64,2) -> 0
B65: 2b | C65: Unrecap. Sec. 1250 gain | AA65: =ROUND(D65,2) -> 0 | AB65: =ROUND(E65,2) -> 0 | AC65: =ROUND(F65,2) -> 0 | AD65: =ROUND(G65,2) -> 0 | AE65: =ROUND(H65,2) -> 0
B66: 2c | C66: Section 1202 gain | AA66: =ROUND(D66,2) -> 0 | AB66: =ROUND(E66,2) -> 0 | AC66: =ROUND(F66,2) -> 0 | AD66: =ROUND(G66,2) -> 0 | AE66: =ROUND(H66,2) -> 0
B67: 2d | C67: Collectibles (28%) gain | AA67: =ROUND(D67,2) -> 0 | AB67: =ROUND(E67,2) -> 0 | AC67: =ROUND(F67,2) -> 0 | AD67: =ROUND(G67,2) -> 0 | AE67: =ROUND(H67,2) -> 0
B68: 3 | C68: Nondividend distributions | AA68: =ROUND(D68,2) -> 0 | AB68: =ROUND(E68,2) -> 0 | AC68: =ROUND(F68,2) -> 0 | AD68: =ROUND(G68,2) -> 0 | AE68: =ROUND(H68,2) -> 0
B69: 4 | C69: Federal income tax withheld | AA69: =ROUND(D69,2) -> 0 | AB69: =ROUND(E69,2) -> 0 | AC69: =ROUND(F69,2) -> 0 | AD69: =ROUND(G69,2) -> 0 | AE69: =ROUND(H69,2) -> 0
B70: 5 | C70: Section 199A dividends | AA70: =ROUND(D70,2) -> 0 | AB70: =ROUND(E70,2) -> 0 | AC70: =ROUND(F70,2) -> 0 | AD70: =ROUND(G70,2) -> 0 | AE70: =ROUND(H70,2) -> 0
B71: 6 | C71: Investment expenses | AA71: =ROUND(D71,2) -> 0 | AB71: =ROUND(E71,2) -> 0 | AC71: =ROUND(F71,2) -> 0 | AD71: =ROUND(G71,2) -> 0 | AE71: =ROUND(H71,2) -> 0
B72: 7 | C72: Foreign tax paid | I72: =IF(SUM(D72:H72)>0,"Check Form 1116, Foreign Tax Credit","") | AA72: =ROUND(D72,2) -> 0 | AB72: =ROUND(E72,2) -> 0 | AC72: =ROUND(F72,2) -> 0 | AD72: =ROUND(G72,2) -> 0 | AE72: =ROUND(H72,2) -> 0
B73: 8 | C73: Foreign country or U.S. possession
B74: 9 | C74: Cash liquidation distributions | AA74: =ROUND(D74,2) -> 0 | AB74: =ROUND(E74,2) -> 0 | AC74: =ROUND(F74,2) -> 0 | AD74: =ROUND(G74,2) -> 0 | AE74: =ROUND(H74,2) -> 0
B75: 10 | C75: Noncash liquidation distributions | AA75: =ROUND(D75,2) -> 0 | AB75: =ROUND(E75,2) -> 0 | AC75: =ROUND(F75,2) -> 0 | AD75: =ROUND(G75,2) -> 0 | AE75: =ROUND(H75,2) -> 0
B76: 11 | C76: Exempt-interest dividends | AA76: =ROUND(D76,2) -> 0 | AB76: =ROUND(E76,2) -> 0 | AC76: =ROUND(F76,2) -> 0 | AD76: =ROUND(G76,2) -> 0 | AE76: =ROUND(H76,2) -> 0
B77: 12 | C77: Specified private activity bond interest dividends | AA77: =ROUND(D77,2) -> 0 | AB77: =ROUND(E77,2) -> 0 | AC77: =ROUND(F77,2) -> 0 | AD77: =ROUND(G77,2) -> 0 | AE77: =ROUND(H77,2) -> 0
B78: 13 | C78: State
B79: 14 | C79: State identification no.
B80: 15 | C80: State tax withheld | AA80: =ROUND(D80,2) -> 0 | AB80: =ROUND(E80,2) -> 0 | AC80: =ROUND(F80,2) -> 0 | AD80: =ROUND(G80,2) -> 0 | AE80: =ROUND(H80,2) -> 0
B81: Only bolded amounts are used in this spreadsheet. | D81: =D63>D62 -> FALSE | E81: =E63>E62 -> FALSE | F81: =F63>F62 -> FALSE | G81: =G63>G62 -> FALSE | H81: =H63>H62 -> FALSE | I81: =OR(D81:H81) -> FALSE
D82: =IF(D59<>"",D59,"") | E82: =IF(E59<>"",E59,"") | F82: =IF(F59<>"",F59,"") | G82: =IF(G59<>"",G59,"") | H82: =IF(H59<>"",H59,"")
D83: =IF(D60<>"", " - "&D60,"") | E83: =IF(E60<>"", " - "&E60,"") | F83: =IF(F60<>"", " - "&F60,"") | G83: =IF(G60<>"", " - "&G60,"") | H83: =IF(H60<>"", " - "&H60,"")
D84: =IF(D61<>""," - "&D61,"") | E84: =IF(E61<>""," - "&E61,"") | F84: =IF(F61<>""," - "&F61,"") | G84: =IF(G61<>""," - "&G61,"") | H84: =IF(H61<>""," - "&H61,"")
D85: =IF(D62="","",D82&D83&D84) | E85: =IF(E62="","",E82&E83&E84) | F85: =IF(F62="","",F82&F83&F84) | G85: =IF(G62="","",G82&G83&G84) | H85: =IF(H62="","",H82&H83&H84)
C86: =IF(Name_1st_Yours="","Enter your name(s) on the"&CHAR(10)&"sheet labeled '1040'",Names) -> Enter your name(s) on the sheet labeled '1040' | D86: Payer #16 | E86: Payer #17 | F86: Payer #18 | G86: Payer #19 | H86: Total | I86: Used at:
C87: PAYER's name
C88: PAYER's Federal ID number
C89: Account number | I89: =SUM(ForeignTaxPaid_INT,ForeignTaxPaid_DIV) -> 0
B90: 1a | C90: Total ordinary dividends | H90: =SUM(AA6:AE6,AA34:AE34,AA62:AE62,AA90:AD90) -> 0 | I90: =IF(I109,"Error: All qualified dividends must be included in","Sch. B, Line 5") -> Sch. B, Line 5 | AA90: =ROUND(D90,2) -> 0 | AB90: =ROUND(E90,2) -> 0 | AC90: =ROUND(F90,2) -> 0 | AD90: =ROUND(G90,2) -> 0
B91: 1b | C91: Qualified dividends | H91: =SUM(AA7:AE7,AA35:AE35,AA63:AE63,AA91:AD91) -> 0 | I91: =IF(I109,"the Total ordinary dividend amount.","Form 1040, Line 3a and 3b") -> Form 1040, Line 3a and 3b | AA91: =ROUND(D91,2) -> 0 | AB91: =ROUND(E91,2) -> 0 | AC91: =ROUND(F91,2) -> 0 | AD91: =ROUND(G91,2) -> 0
B92: 2a | C92: Total capital gain distr. | H92: =SUM(AA8:AE8,AA36:AE36,AA64:AE64,AA92:AD92) -> 0 | I92: Sch. D, Line 13 | AA92: =ROUND(D92,2) -> 0 | AB92: =ROUND(E92,2) -> 0 | AC92: =ROUND(F92,2) -> 0 | AD92: =ROUND(G92,2) -> 0
B93: 2b | C93: Unrecap. Sec. 1250 gain | H93: =SUM(AA9:AE9,AA37:AE37,AA65:AE65,AA93:AD93) -> 0 | AA93: =ROUND(D93,2) -> 0 | AB93: =ROUND(E93,2) -> 0 | AC93: =ROUND(F93,2) -> 0 | AD93: =ROUND(G93,2) -> 0
B94: 2c | C94: Section 1202 gain | H94: =SUM(AA10:AE10,AA38:AE38,AA66:AE66,AA94:AD94) -> 0 | AA94: =ROUND(D94,2) -> 0 | AB94: =ROUND(E94,2) -> 0 | AC94: =ROUND(F94,2) -> 0 | AD94: =ROUND(G94,2) -> 0
B95: 2d | C95: Collectibles (28%) gain | H95: =SUM(AA11:AE11,AA39:AE39,AA67:AE67,AA95:AD95) -> 0 | I95: Sch. D. WS, 28% Rate Gain WS, Line 4 | AA95: =ROUND(D95,2) -> 0 | AB95: =ROUND(E95,2) -> 0 | AC95: =ROUND(F95,2) -> 0 | AD95: =ROUND(G95,2) -> 0
B96: 3 | C96: Nondividend distributions | H96: =SUM(AA12:AE12,AA40:AE40,AA68:AE68,AA96:AD96) -> 0 | AA96: =ROUND(D96,2) -> 0 | AB96: =ROUND(E96,2) -> 0 | AC96: =ROUND(F96,2) -> 0 | AD96: =ROUND(G96,2) -> 0
B97: 4 | C97: Federal income tax withheld | H97: =SUM(AA13:AE13,AA41:AE41,AA69:AE69,AA97:AD97) -> 0 | I97: 1040, line 25b | AA97: =ROUND(D97,2) -> 0 | AB97: =ROUND(E97,2) -> 0 | AC97: =ROUND(F97,2) -> 0 | AD97: =ROUND(G97,2) -> 0
B98: 5 | C98: Section 199A dividends | H98: =SUM(AA14:AE14,AA42:AE42,AA70:AE70,AA98:AD98) -> 0 | I98: Form 8995, QBID, Line 6 | AA98: =ROUND(D98,2) -> 0 | AB98: =ROUND(E98,2) -> 0 | AC98: =ROUND(F98,2) -> 0 | AD98: =ROUND(G98,2) -> 0
B99: 6 | C99: Investment expenses | H99: =SUM(AA15:AE15,AA43:AE43,AA71:AE71,AA99:AD99) -> 0 | AA99: =ROUND(D99,2) -> 0 | AB99: =ROUND(E99,2) -> 0 | AC99: =ROUND(F99,2) -> 0 | AD99: =ROUND(G99,2) -> 0
B100: 7 | C100: Foreign tax paid | H100: =SUM(AA16:AE16,AA44:AE44,AA72:AE72,AA100:AD100) -> 0 | I100: Form 1116 | AA100: =ROUND(D100,2) -> 0 | AB100: =ROUND(E100,2) -> 0 | AC100: =ROUND(F100,2) -> 0 | AD100: =ROUND(G100,2) -> 0
...

Sheet 1099-G
B1: Form 1099-G, Certain Government Payments | E1: =IF(FALSE,"After Form 1040 and Schedule 1 are complete,"&CHAR(10)&" be sure to review 'Sch. 1 Line 8 WS', line 1.",IF(FALSE,"'Sch. 1 Line 8 WS', line 1, has been Updated.","")) | L1: Notes
C2: =IF(Name_1st_Yours="","Enter your name on the"&CHAR(10)&"sheet labeled '1040'",NameYours) -> Enter your name on the sheet labeled '1040' | D2: Payer #1 | E2: Payer #2 | F2: Payer #3 | G2: Payer #4 | H2: Payer #5 | I2: Your Total | J2: Used at:
C3: PAYER's name
C4: PAYER's TIN
C5: Account number
B6: 1 | C6: Unemployment Compensation | I6: =ROUND(SUM(D6:H6),0) -> 0 | J6: Sch. 1 Line 8 WS', line 7
B7: 2 | C7: State or local income tax refunds, credits, offsets | I7: =ROUND(SUM(D7:H7),0) -> 0 | J7: =IF(Needs_SALT," See sheet labeled"," 'Sch. 1, Line 1 (SALT)', line 1 [State & local tax]") -> 'Sch. 1, Line 1 (SALT)', line 1 [State & local tax]
B8: 3 | C8: Box 2 amount is for tax year | I8: --- | J8: =IF(Needs_SALT,"'Sch. 1, Line 1 (SALT)'. (State & Local Tax)","")
B9: 4 | C9: Federal income tax withheld | I9: =ROUND(SUM(D9:H9),0) -> 0
B10: 5 | C10: RTAA Payments | I10: =ROUND(SUM(D10:H10),0) -> 0
B11: 6 | C11: Taxable grants | I11: =ROUND(SUM(D11:H11),0) -> 0
B12: 7a | C12: Agriculture payments - Disaster payments | I12: =ROUND(SUM(D12:H12),0) -> 0
B13: 7b | C13: Agriculture payments - Other payments | I13: =ROUND(SUM(D13:H13),0) -> 0 | J13: =AND(D13="",E13="",F13="",G13="",I13="") -> FALSE
B14: 8 | C14: Check if box 2 is trade or business income
B15: 9 | C15: Market gain | I15: =ROUND(SUM(D15:H15),0) -> 0 | J15: =AND(D15="",E15="",F15="",G15="",I15="") -> FALSE
B16: 10a | C16: State
B17: 10b | C17: State identification no.
B18: 11 | C18: State income tax withheld | I18: =ROUND(SUM(D18:H18),0) -> 0
B19: Only bolded amounts are used in this spreadsheet.
I20: =IF(I3<>"",I3,"")
C21: =IF(Name_1st_Sp="","Enter your spouse's name on"&CHAR(10)&"the sheet labeled '1040'",NameSpouse) -> Enter your spouse's name on the sheet labeled '1040' | D21: Payer #1 | E21: Payer #2 | F21: Payer #3 | G21: Payer #4 | H21: Spouse Total | I21: Total | J21: Used at:
C22: PAYER's name
C23: PAYER's Federal ID number
C24: Account number | J24: =SUM(ForeignTaxPaid_INT,ForeignTaxPaid_DIV) -> 0
B25: 1 | C25: Unemployment Compensation | H25: =ROUND(SUM(D25:G25),0) -> 0 | I25: =SUM(UCE_You,UCE_Spouse) -> 0 | J25: Sch. 1 Line 8 WS', line 8 / Sch. 1, line 7
B26: 2 | C26: State or local income tax refunds, credits, offsets | H26: =ROUND(SUM(D26:G26),0) -> 0 | I26: =SUM(I7,H26) -> 0 | J26: =IF(Needs_SALT," See sheet labeled"," 'Sch. 1, Line 1 (SALT)', line 1 [State & local tax]") -> 'Sch. 1, Line 1 (SALT)', line 1 [State & local tax]
B27: 3 | C27: Box 2 amount is for tax year | H27: --- | I27: --- | J27: =IF(Needs_SALT," 'Sch. 1, Line 1 (SALT)'. (State & Local Tax)","")
B28: 4 | C28: Federal income tax withheld | H28: =ROUND(SUM(D28:G28),0) -> 0 | I28: =SUM(I9,H28) -> 0 | J28: 1040, line 25b
B29: 5 | C29: RTAA Payments | H29: =ROUND(SUM(D29:G29),0) -> 0 | I29: =SUM(I10,H29) -> 0 | J29: Sch. 1, line 8
B30: 6 | C30: Taxable grants | H30: =ROUND(SUM(D30:G30),0) -> 0 | I30: =SUM(I11,H30) -> 0 | J30: Sch. 1, line 8 and 'Earned Inc WS', line 4a
B31: 7a | C31: Agriculture payments - Disaster payments | H31: =ROUND(SUM(D31:G31),0) -> 0 | I31: =SUM(I12,H31) -> 0 | J31: Sch. F, Line 6a
B32: 7b | C32: Agriculture payments - Other payments | H32: =ROUND(SUM(D32:G32),0) -> 0 | I32: =SUM(I13,H32) -> 0 | J32: Sch. F, Line 4a
B33: 8 | C33: Check if box 2 is trade or business income | J33: =AND(J13,D31="",E31="",F31="",G31="") -> FALSE
B34: 9 | C34: Market gain | H34: =ROUND(SUM(D34:G34),0) -> 0 | I34: =SUM(I15,H34) -> 0 | J34: Sch. F, Line 4a
B35: 10a | C35: State | J35: =AND(J15,D33="",E33="",F33="",G33="") -> FALSE
B36: 10b | C36: State identification no.
B37: 11 | C37: State income tax withheld | H37: =ROUND(SUM(D37:G37),0) -> 0 | I37: =SUM(I18,H37) -> 0 | J37: Sch. A, Line 5a
B38: Only bolded amounts are used in this spreadsheet.
C43: Table of Contents

Sheet 1099-MISC
C3: This form has yet to be implemented.
C5: Download and follow IRS instructions for where the information and amounts should be entered.
C7: NOTE: | D7: Amounts of more than $600 will NOT typically be reported on Schedule 1 (Form 1040), Line 8.
C9: ="Instructions for Form 1099-MISC may be downloaded from the IRS:" -> Instructions for Form 1099-MISC may be downloaded from the IRS:
C10: https://www.irs.gov/pub/irs-pdf/f1099msc.pdf
C12: ="Form 1099-MISC may be downloaded from the IRS:" -> Form 1099-MISC may be downloaded from the IRS:
C13: https://www.irs.gov/pub/irs-pdf/f1099msc_21.pdf
C72: Table of Contents

Sheet 1099-R
B1: Information from Form 1099-R, Distributions From Pensions, Annuities, Retirement or Profit-Sharing Plans, IRAs, Insurance Contracts, etc. | AT1: Notes
C2: =IF(Name_1st_Yours="","Enter your name on the"&CHAR(10)&"sheet labeled '1040'",NameYours) -> Enter your name on the sheet labeled '1040' | D2: Enter payer's name here. | E2: Payer #2 | F2: Payer #3 | G2: Payer #4 | H2: Payer #5 | I2: Payer #6 | J2: Payer #7 | K2: Payer #8 | L2: Payer #9 | M2: Total IRAs | N2: Total Pension / Annuities | O2: Qualified CONVersion to ROTH IRA | U2: IRA | AE2: P/A | AO2: CONV
C3: Enter "IRA" or "P/A" or "CONV" >>> | M3: IRA | N3: P/A | O3: CONV | Q3: =NOT(AND(ISERROR(FIND("IRA",D3,1)),ISERROR(FIND("ira",D3,1)))) -> FALSE | R3: =NOT(AND(ISERROR(FIND("IRA",E3,1)),ISERROR(FIND("ira",E3,1)))) -> FALSE | S3: =NOT(AND(ISERROR(FIND("IRA",F3,1)),ISERROR(FIND("ira",F3,1)))) -> FALSE | T3: =NOT(AND(ISERROR(FIND("IRA",G3,1)),ISERROR(FIND("ira",G3,1)))) -> FALSE | U3: =NOT(AND(ISERROR(FIND("IRA",H3,1)),ISERROR(FIND("ira",H3,1)))) -> FALSE | V3: =NOT(AND(ISERROR(FIND("IRA",I3,1)),ISERROR(FIND("ira",I3,1)))) -> FALSE | W3: =NOT(AND(ISERROR(FIND("IRA",J3,1)),ISERROR(FIND("ira",J3,1)))) -> FALSE | X3: =NOT(AND(ISERROR(FIND("IRA",K3,1)),ISERROR(FIND("ira",K3,1)))) -> FALSE | Y3: =NOT(AND(ISERROR(FIND("IRA",L3,1)),ISERROR(FIND("ira",L3,1)))) -> FALSE | AA3: =NOT(AND(ISERROR(FIND("P/A",D3,1)),ISERROR(FIND("p/a",D3,1)))) -> FALSE | AB3: =NOT(AND(ISERROR(FIND("P/A",E3,1)),ISERROR(FIND("p/a",E3,1)))) -> FALSE | AC3: =NOT(AND(ISERROR(FIND("P/A",F3,1)),ISERROR(FIND("p/a",F3,1)))) -> FALSE | AD3: =NOT(AND(ISERROR(FIND("P/A",G3,1)),ISERROR(FIND("p/a",G3,1)))) -> FALSE | AE3: =NOT(AND(ISERROR(FIND("P/A",H3,1)),ISERROR(FIND("p/a",H3,1)))) -> FALSE | AF3: =NOT(AND(ISERROR(FIND("P/A",I3,1)),ISERROR(FIND("p/a",I3,1)))) -> FALSE | AG3: =NOT(AND(ISERROR(FIND("P/A",J3,1)),ISERROR(FIND("p/a",J3,1)))) -> FALSE | AH3: =NOT(AND(ISERROR(FIND("P/A",K3,1)),ISERROR(FIND("p/a",K3,1)))) -> FALSE | AI3: =NOT(AND(ISERROR(FIND("P/A",L3,1)),ISERROR(FIND("p/a",L3,1)))) -> FALSE | AK3: =NOT(AND(ISERROR(FIND("CONV",D3,1)),ISERROR(FIND("conv",D3,1)))) -> FALSE | AL3: =NOT(AND(ISERROR(FIND("CONV",E3,1)),ISERROR(FIND("conv",E3,1)))) -> FALSE | AM3: =NOT(AND(ISERROR(FIND("CONV",F3,1)),ISERROR(FIND("conv",F3,1)))) -> FALSE | AN3: =NOT(AND(ISERROR(FIND("CONV",G3,1)),ISERROR(FIND("conv",G3,1)))) -> FALSE | AO3: =NOT(AND(ISERROR(FIND("CONV",H3,1)),ISERROR(FIND("conv",H3,1)))) -> FALSE | AP3: =NOT(AND(ISERROR(FIND("CONV",I3,1)),ISERROR(FIND("conv",I3,1)))) -> FALSE | AQ3: =NOT(AND(ISERROR(FIND("CONV",J3,1)),ISERROR(FIND("conv",J3,1)))) -> FALSE | AR3: =NOT(AND(ISERROR(FIND("CONV",K3,1)),ISERROR(FIND("conv",K3,1)))) -> FALSE | AS3: =NOT(AND(ISERROR(FIND("CONV",L3,1)),ISERROR(FIND("conv",L3,1)))) -> FALSE
B4: 1 | C4: Gross distribution | M4: =SUM(Q4:Y4) -> 0 | N4: =SUM(AA4:AI4) -> 0 | O4: =SUM(AK4:AS4) -> 0 | Q4: =IF(Q$3,ROUND(D4,0),0) -> 0 | R4: =IF(R$3,ROUND(E4,0),0) -> 0 | S4: =IF(S$3,ROUND(F4,0),0) -> 0 | T4: =IF(T$3,ROUND(G4,0),0) -> 0 | U4: =IF(U$3,ROUND(H4,0),0) -> 0 | V4: =IF(V$3,ROUND(I4,0),0) -> 0 | W4: =IF(W$3,ROUND(J4,0),0) -> 0 | X4: =IF(X$3,ROUND(K4,0),0) -> 0 | Y4: =IF(Y$3,ROUND(L4,0),0) -> 0 | AA4: =IF(AA$3,ROUND(D4,0),0) -> 0 | AB4: =IF(AB$3,ROUND(E4,0),0) -> 0 | AC4: =IF(AC$3,ROUND(F4,0),0) -> 0 | AD4: =IF(AD$3,ROUND(G4,0),0) -> 0 | AE4: =IF(AE$3,ROUND(H4,0),0) -> 0 | AF4: =IF(AF$3,ROUND(I4,0),0) -> 0 | AG4: =IF(AG$3,ROUND(J4,0),0) -> 0 | AH4: =IF(AH$3,ROUND(K4,0),0) -> 0 | AI4: =IF(AI$3,ROUND(L4,0),0) -> 0 | AK4: =IF(AK$3,ROUND(D4,0),0) -> 0 | AL4: =IF(AL$3,ROUND(E4,0),0) -> 0 | AM4: =IF(AM$3,ROUND(F4,0),0) -> 0 | AN4: =IF(AN$3,ROUND(G4,0),0) -> 0 | AO4: =IF(AO$3,ROUND(H4,0),0) -> 0 | AP4: =IF(AP$3,ROUND(I4,0),0) -> 0 | AQ4: =IF(AQ$3,ROUND(J4,0),0) -> 0 | AR4: =IF(AR$3,ROUND(K4,0),0) -> 0 | AS4: =IF(AS$3,ROUND(L4,0),0) -> 0
B5: 2a | C5: Taxable amount | M5: =SUM(Q5:Y5) -> 0 | N5: =SUM(AA5:AI5) -> 0 | O5: =SUM(AK5:AS5) -> 0 | Q5: =IF(Q$3,ROUND(D5,0),0) -> 0 | R5: =IF(R$3,ROUND(E5,0),0) -> 0 | S5: =IF(S$3,ROUND(F5,0),0) -> 0 | T5: =IF(T$3,ROUND(G5,0),0) -> 0 | U5: =IF(U$3,ROUND(H5,0),0) -> 0 | V5: =IF(V$3,ROUND(I5,0),0) -> 0 | W5: =IF(W$3,ROUND(J5,0),0) -> 0 | X5: =IF(X$3,ROUND(K5,0),0) -> 0 | Y5: =IF(Y$3,ROUND(L5,0),0) -> 0 | AA5: =IF(AA$3,ROUND(D5,0),0) -> 0 | AB5: =IF(AB$3,ROUND(E5,0),0) -> 0 | AC5: =IF(AC$3,ROUND(F5,0),0) -> 0 | AD5: =IF(AD$3,ROUND(G5,0),0) -> 0 | AE5: =IF(AE$3,ROUND(H5,0),0) -> 0 | AF5: =IF(AF$3,ROUND(I5,0),0) -> 0 | AG5: =IF(AG$3,ROUND(J5,0),0) -> 0 | AH5: =IF(AH$3,ROUND(K5,0),0) -> 0 | AI5: =IF(AI$3,ROUND(L5,0),0) -> 0 | AK5: =IF(AK$3,ROUND(D5,0),0) -> 0 | AL5: =IF(AL$3,ROUND(E5,0),0) -> 0 | AM5: =IF(AM$3,ROUND(F5,0),0) -> 0 | AN5: =IF(AN$3,ROUND(G5,0),0) -> 0 | AO5: =IF(AO$3,ROUND(H5,0),0) -> 0 | AP5: =IF(AP$3,ROUND(I5,0),0) -> 0 | AQ5: =IF(AQ$3,ROUND(J5,0),0) -> 0 | AR5: =IF(AR$3,ROUND(K5,0),0) -> 0 | AS5: =IF(AS$3,ROUND(L5,0),0) -> 0
B6: 2b | C6: Taxable amount not determined / total distr. | M6: =" - - - -" -> - - - - | N6: =" - - - -" -> - - - - | O6: =" - - - -" -> - - - -
B7: 3 | C7: Capital gain (included in box 2a) | M7: =SUM(Q7:Y7) -> 0 | N7: =SUM(AA7:AI7) -> 0 | O7: =SUM(AK7:AS7) -> 0 | Q7: =IF(Q$3,ROUND(D7,0),0) -> 0 | R7: =IF(R$3,ROUND(E7,0),0) -> 0 | S7: =IF(S$3,ROUND(F7,0),0) -> 0 | T7: =IF(T$3,ROUND(G7,0),0) -> 0 | U7: =IF(U$3,ROUND(H7,0),0) -> 0 | V7: =IF(V$3,ROUND(I7,0),0) -> 0 | W7: =IF(W$3,ROUND(J7,0),0) -> 0 | X7: =IF(X$3,ROUND(K7,0),0) -> 0 | Y7: =IF(Y$3,ROUND(L7,0),0) -> 0 | AA7: =IF(AA$3,ROUND(D7,0),0) -> 0 | AB7: =IF(AB$3,ROUND(E7,0),0) -> 0 | AC7: =IF(AC$3,ROUND(F7,0),0) -> 0 | AD7: =IF(AD$3,ROUND(G7,0),0) -> 0 | AE7: =IF(AE$3,ROUND(H7,0),0) -> 0 | AF7: =IF(AF$3,ROUND(I7,0),0) -> 0 | AG7: =IF(AG$3,ROUND(J7,0),0) -> 0 | AH7: =IF(AH$3,ROUND(K7,0),0) -> 0 | AI7: =IF(AI$3,ROUND(L7,0),0) -> 0 | AK7: =IF(AK$3,ROUND(D7,0),0) -> 0 | AL7: =IF(AL$3,ROUND(E7,0),0) -> 0 | AM7: =IF(AM$3,ROUND(F7,0),0) -> 0 | AN7: =IF(AN$3,ROUND(G7,0),0) -> 0 | AO7: =IF(AO$3,ROUND(H7,0),0) -> 0 | AP7: =IF(AP$3,ROUND(I7,0),0) -> 0 | AQ7: =IF(AQ$3,ROUND(J7,0),0) -> 0 | AR7: =IF(AR$3,ROUND(K7,0),0) -> 0 | AS7: =IF(AS$3,ROUND(L7,0),0) -> 0
B8: 4 | C8: Federal income tax withheld | M8: =SUM(Q8:Y8) -> 0 | N8: =SUM(AA8:AI8) -> 0 | O8: =SUM(AK8:AS8) -> 0 | Q8: =IF(Q$3,ROUND(D8,0),0) -> 0 | R8: =IF(R$3,ROUND(E8,0),0) -> 0 | S8: =IF(S$3,ROUND(F8,0),0) -> 0 | T8: =IF(T$3,ROUND(G8,0),0) -> 0 | U8: =IF(U$3,ROUND(H8,0),0) -> 0 | V8: =IF(V$3,ROUND(I8,0),0) -> 0 | W8: =IF(W$3,ROUND(J8,0),0) -> 0 | X8: =IF(X$3,ROUND(K8,0),0) -> 0 | Y8: =IF(Y$3,ROUND(L8,0),0) -> 0 | AA8: =IF(AA$3,ROUND(D8,0),0) -> 0 | AB8: =IF(AB$3,ROUND(E8,0),0) -> 0 | AC8: =IF(AC$3,ROUND(F8,0),0) -> 0 | AD8: =IF(AD$3,ROUND(G8,0),0) -> 0 | AE8: =IF(AE$3,ROUND(H8,0),0) -> 0 | AF8: =IF(AF$3,ROUND(I8,0),0) -> 0 | AG8: =IF(AG$3,ROUND(J8,0),0) -> 0 | AH8: =IF(AH$3,ROUND(K8,0),0) -> 0 | AI8: =IF(AI$3,ROUND(L8,0),0) -> 0 | AK8: =IF(AK$3,ROUND(D8,0),0) -> 0 | AL8: =IF(AL$3,ROUND(E8,0),0) -> 0 | AM8: =IF(AM$3,ROUND(F8,0),0) -> 0 | AN8: =IF(AN$3,ROUND(G8,0),0) -> 0 | AO8: =IF(AO$3,ROUND(H8,0),0) -> 0 | AP8: =IF(AP$3,ROUND(I8,0),0) -> 0 | AQ8: =IF(AQ$3,ROUND(J8,0),0) -> 0 | AR8: =IF(AR$3,ROUND(K8,0),0) -> 0 | AS8: =IF(AS$3,ROUND(L8,0),0) -> 0
B9: 5 | C9: Employee contributions / Insurance premiums / Designated Roth IRA contributions | M9: =SUM(Q9:Y9) -> 0 | N9: =SUM(AA9:AI9) -> 0 | O9: =SUM(AK9:AS9) -> 0 | Q9: =IF(Q$3,ROUND(D9,0),0) -> 0 | R9: =IF(R$3,ROUND(E9,0),0) -> 0 | S9: =IF(S$3,ROUND(F9,0),0) -> 0 | T9: =IF(T$3,ROUND(G9,0),0) -> 0 | U9: =IF(U$3,ROUND(H9,0),0) -> 0 | V9: =IF(V$3,ROUND(I9,0),0) -> 0 | W9: =IF(W$3,ROUND(J9,0),0) -> 0 | X9: =IF(X$3,ROUND(K9,0),0) -> 0 | Y9: =IF(Y$3,ROUND(L9,0),0) -> 0 | AA9: =IF(AA$3,ROUND(D9,0),0) -> 0 | AB9: =IF(AB$3,ROUND(E9,0),0) -> 0 | AC9: =IF(AC$3,ROUND(F9,0),0) -> 0 | AD9: =IF(AD$3,ROUND(G9,0),0) -> 0 | AE9: =IF(AE$3,ROUND(H9,0),0) -> 0 | AF9: =IF(AF$3,ROUND(I9,0),0) -> 0 | AG9: =IF(AG$3,ROUND(J9,0),0) -> 0 | AH9: =IF(AH$3,ROUND(K9,0),0) -> 0 | AI9: =IF(AI$3,ROUND(L9,0),0) -> 0 | AK9: =IF(AK$3,ROUND(D9,0),0) -> 0 | AL9: =IF(AL$3,ROUND(E9,0),0) -> 0 | AM9: =IF(AM$3,ROUND(F9,0),0) -> 0 | AN9: =IF(AN$3,ROUND(G9,0),0) -> 0 | AO9: =IF(AO$3,ROUND(H9,0),0) -> 0 | AP9: =IF(AP$3,ROUND(I9,0),0) -> 0 | AQ9: =IF(AQ$3,ROUND(J9,0),0) -> 0 | AR9: =IF(AR$3,ROUND(K9,0),0) -> 0 | AS9: =IF(AS$3,ROUND(L9,0),0) -> 0
B10: 6 | C10: Net unrealized appreciation in employer's securities | M10: =SUM(Q10:Y10) -> 0 | N10: =SUM(AA10:AI10) -> 0 | O10: =SUM(AK10:AS10) -> 0 | Q10: =IF(Q$3,ROUND(D10,0),0) -> 0 | R10: =IF(R$3,ROUND(E10,0),0) -> 0 | S10: =IF(S$3,ROUND(F10,0),0) -> 0 | T10: =IF(T$3,ROUND(G10,0),0) -> 0 | U10: =IF(U$3,ROUND(H10,0),0) -> 0 | V10: =IF(V$3,ROUND(I10,0),0) -> 0 | W10: =IF(W$3,ROUND(J10,0),0) -> 0 | X10: =IF(X$3,ROUND(K10,0),0) -> 0 | Y10: =IF(Y$3,ROUND(L10,0),0) -> 0 | AA10: =IF(AA$3,ROUND(D10,0),0) -> 0 | AB10: =IF(AB$3,ROUND(E10,0),0) -> 0 | AC10: =IF(AC$3,ROUND(F10,0),0) -> 0 | AD10: =IF(AD$3,ROUND(G10,0),0) -> 0 | AE10: =IF(AE$3,ROUND(H10,0),0) -> 0 | AF10: =IF(AF$3,ROUND(I10,0),0) -> 0 | AG10: =IF(AG$3,ROUND(J10,0),0) -> 0 | AH10: =IF(AH$3,ROUND(K10,0),0) -> 0 | AI10: =IF(AI$3,ROUND(L10,0),0) -> 0 | AK10: =IF(AK$3,ROUND(D10,0),0) -> 0 | AL10: =IF(AL$3,ROUND(E10,0),0) -> 0 | AM10: =IF(AM$3,ROUND(F10,0),0) -> 0 | AN10: =IF(AN$3,ROUND(G10,0),0) -> 0 | AO10: =IF(AO$3,ROUND(H10,0),0) -> 0 | AP10: =IF(AP$3,ROUND(I10,0),0) -> 0 | AQ10: =IF(AQ$3,ROUND(J10,0),0) -> 0 | AR10: =IF(AR$3,ROUND(K10,0),0) -> 0 | AS10: =IF(AS$3,ROUND(L10,0),0) -> 0
B11: 7 | C11: Distribution code(s) (Code D only) | M11: =" - - - -" -> - - - - | N11: =" - - - -" -> - - - - | O11: =" - - - -" -> - - - - | AK11: =IF(AK$3,ROUND(D11,0),0) -> 0 | AL11: =IF(AL$3,ROUND(E11,0),0) -> 0 | AM11: =IF(AM$3,ROUND(F11,0),0) -> 0 | AN11: =IF(AN$3,ROUND(G11,0),0) -> 0 | AO11: =IF(AO$3,ROUND(H11,0),0) -> 0 | AP11: =IF(AP$3,ROUND(I11,0),0) -> 0 | AQ11: =IF(AQ$3,ROUND(J11,0),0) -> 0 | AR11: =IF(AR$3,ROUND(K11,0),0) -> 0 | AS11: =IF(AS$3,ROUND(L11,0),0) -> 0
B12: 8 | C12: Other | M12: =SUM(Q12:Y12) -> 0 | N12: =SUM(AA12:AI12) -> 0 | O12: =SUM(AK12:AS12) -> 0 | Q12: =IF(Q$3,ROUND(D12,0),0) -> 0 | R12: =IF(R$3,ROUND(E12,0),0) -> 0 | S12: =IF(S$3,ROUND(F12,0),0) -> 0 | T12: =IF(T$3,ROUND(G12,0),0) -> 0 | U12: =IF(U$3,ROUND(H12,0),0) -> 0 | V12: =IF(V$3,ROUND(I12,0),0) -> 0 | W12: =IF(W$3,ROUND(J12,0),0) -> 0 | X12: =IF(X$3,ROUND(K12,0),0) -> 0 | Y12: =IF(Y$3,ROUND(L12,0),0) -> 0 | AA12: =IF(AA$3,ROUND(D12,0),0) -> 0 | AB12: =IF(AB$3,ROUND(E12,0),0) -> 0 | AC12: =IF(AC$3,ROUND(F12,0),0) -> 0 | AD12: =IF(AD$3,ROUND(G12,0),0) -> 0 | AE12: =IF(AE$3,ROUND(H12,0),0) -> 0 | AF12: =IF(AF$3,ROUND(I12,0),0) -> 0 | AG12: =IF(AG$3,ROUND(J12,0),0) -> 0 | AH12: =IF(AH$3,ROUND(K12,0),0) -> 0 | AI12: =IF(AI$3,ROUND(L12,0),0) -> 0 | AK12: =IF(AK$3,ROUND(D12,0),0) -> 0 | AL12: =IF(AL$3,ROUND(E12,0),0) -> 0 | AM12: =IF(AM$3,ROUND(F12,0),0) -> 0 | AN12: =IF(AN$3,ROUND(G12,0),0) -> 0 | AO12: =IF(AO$3,ROUND(H12,0),0) -> 0 | AP12: =IF(AP$3,ROUND(I12,0),0) -> 0 | AQ12: =IF(AQ$3,ROUND(J12,0),0) -> 0 | AR12: =IF(AR$3,ROUND(K12,0),0) -> 0 | AS12: =IF(AS$3,ROUND(L12,0),0) -> 0
B13: 9a | C13: Your percentage of total distribution | M13: =SUM(Q13:Y13) -> 0 | N13: =SUM(AA13:AI13) -> 0 | O13: =SUM(AK13:AS13) -> 0 | Q13: =IF(Q3,D13,0) -> 0 | R13: =IF(R3,E13,0) -> 0 | S13: =IF(S3,F13,0) -> 0 | T13: =IF(T3,G13,0) -> 0 | U13: =IF(U3,H13,0) -> 0 | V13: =IF(V3,I13,0) -> 0 | W13: =IF(W3,J13,0) -> 0 | X13: =IF(X3,K13,0) -> 0 | Y13: =IF(Y3,L13,0) -> 0 | AA13: =IF(AA3,D13,0) -> 0 | AB13: =IF(AB3,E13,0) -> 0 | AC13: =IF(AC3,F13,0) -> 0 | AD13: =IF(AD3,G13,0) -> 0 | AE13: =IF(AE3,H13,0) -> 0 | AF13: =IF(AF3,I13,0) -> 0 | AG13: =IF(AG3,J13,0) -> 0 | AH13: =IF(AH3,K13,0) -> 0 | AI13: =IF(AI3,L13,0) -> 0 | AK13: =IF(AK3,D13,0) -> 0 | AL13: =IF(AL3,E13,0) -> 0 | AM13: =IF(AM3,F13,0) -> 0 | AN13: =IF(AN3,G13,0) -> 0 | AO13: =IF(AO3,H13,0) -> 0 | AP13: =IF(AP3,I13,0) -> 0 | AQ13: =IF(AQ3,J13,0) -> 0 | AR13: =IF(AR3,K13,0) -> 0 | AS13: =IF(AS3,L13,0) -> 0
B14: 9b | C14: Total employee contributions | M14: =SUM(Q14:Y14) -> 0 | N14: =SUM(AA14:AI14) -> 0 | O14: =SUM(AK14:AS14) -> 0 | Q14: =IF(Q$3,ROUND(D14,0),0) -> 0 | R14: =IF(R$3,ROUND(E14,0),0) -> 0 | S14: =IF(S$3,ROUND(F14,0),0) -> 0 | T14: =IF(T$3,ROUND(G14,0),0) -> 0 | U14: =IF(U$3,ROUND(H14,0),0) -> 0 | V14: =IF(V$3,ROUND(I14,0),0) -> 0 | W14: =IF(W$3,ROUND(J14,0),0) -> 0 | X14: =IF(X$3,ROUND(K14,0),0) -> 0 | Y14: =IF(Y$3,ROUND(L14,0),0) -> 0 | AA14: =IF(AA$3,ROUND(D14,0),0) -> 0 | AB14: =IF(AB$3,ROUND(E14,0),0) -> 0 | AC14: =IF(AC$3,ROUND(F14,0),0) -> 0 | AD14: =IF(AD$3,ROUND(G14,0),0) -> 0 | AE14: =IF(AE$3,ROUND(H14,0),0) -> 0 | AF14: =IF(AF$3,ROUND(I14,0),0) -> 0 | AG14: =IF(AG$3,ROUND(J14,0),0) -> 0 | AH14: =IF(AH$3,ROUND(K14,0),0) -> 0 | AI14: =IF(AI$3,ROUND(L14,0),0) -> 0 | AK14: =IF(AK$3,ROUND(D14,0),0) -> 0 | AL14: =IF(AL$3,ROUND(E14,0),0) -> 0 | AM14: =IF(AM$3,ROUND(F14,0),0) -> 0 | AN14: =IF(AN$3,ROUND(G14,0),0) -> 0 | AO14: =IF(AO$3,ROUND(H14,0),0) -> 0 | AP14: =IF(AP$3,ROUND(I14,0),0) -> 0 | AQ14: =IF(AQ$3,ROUND(J14,0),0) -> 0 | AR14: =IF(AR$3,ROUND(K14,0),0) -> 0 | AS14: =IF(AS$3,ROUND(L14,0),0) -> 0
B15: 10 | C15: Amount allocable to IRR within 5 years | M15: =SUM(Q15:Y15) -> 0 | N15: =SUM(AA15:AI15) -> 0 | O15: =SUM(AK15:AS15) -> 0 | Q15: =IF(Q$3,ROUND(D15,0),0) -> 0 | R15: =IF(R$3,ROUND(E15,0),0) -> 0 | S15: =IF(S$3,ROUND(F15,0),0) -> 0 | T15: =IF(T$3,ROUND(G15,0),0) -> 0 | U15: =IF(U$3,ROUND(H15,0),0) -> 0 | V15: =IF(V$3,ROUND(I15,0),0) -> 0 | W15: =IF(W$3,ROUND(J15,0),0) -> 0 | X15: =IF(X$3,ROUND(K15,0),0) -> 0 | Y15: =IF(Y$3,ROUND(L15,0),0) -> 0 | AA15: =IF(AA$3,ROUND(D15,0),0) -> 0 | AB15: =IF(AB$3,ROUND(E15,0),0) -> 0 | AC15: =IF(AC$3,ROUND(F15,0),0) -> 0 | AD15: =IF(AD$3,ROUND(G15,0),0) -> 0 | AE15: =IF(AE$3,ROUND(H15,0),0) -> 0 | AF15: =IF(AF$3,ROUND(I15,0),0) -> 0 | AG15: =IF(AG$3,ROUND(J15,0),0) -> 0 | AH15: =IF(AH$3,ROUND(K15,0),0) -> 0 | AI15: =IF(AI$3,ROUND(L15,0),0) -> 0 | AK15: =IF(AK$3,ROUND(D15,0),0) -> 0 | AL15: =IF(AL$3,ROUND(E15,0),0) -> 0 | AM15: =IF(AM$3,ROUND(F15,0),0) -> 0 | AN15: =IF(AN$3,ROUND(G15,0),0) -> 0 | AO15: =IF(AO$3,ROUND(H15,0),0) -> 0 | AP15: =IF(AP$3,ROUND(I15,0),0) -> 0 | AQ15: =IF(AQ$3,ROUND(J15,0),0) -> 0 | AR15: =IF(AR$3,ROUND(K15,0),0) -> 0 | AS15: =IF(AS$3,ROUND(L15,0),0) -> 0
B16: 11 | C16: 1st year of desig. Roth contrib. | M16: =SUM(Q16:Y16) -> 0 | N16: =SUM(AA16:AI16) -> 0 | O16: =SUM(AK16:AS16) -> 0 | Q16: =IF(Q$3,ROUND(D16,0),0) -> 0 | R16: =IF(R$3,ROUND(E16,0),0) -> 0 | S16: =IF(S$3,ROUND(F16,0),0) -> 0 | T16: =IF(T$3,ROUND(G16,0),0) -> 0 | U16: =IF(U$3,ROUND(H16,0),0) -> 0 | V16: =IF(V$3,ROUND(I16,0),0) -> 0 | W16: =IF(W$3,ROUND(J16,0),0) -> 0 | X16: =IF(X$3,ROUND(K16,0),0) -> 0 | Y16: =IF(Y$3,ROUND(L16,0),0) -> 0 | AA16: =IF(AA$3,ROUND(D16,0),0) -> 0 | AB16: =IF(AB$3,ROUND(E16,0),0) -> 0 | AC16: =IF(AC$3,ROUND(F16,0),0) -> 0 | AD16: =IF(AD$3,ROUND(G16,0),0) -> 0 | AE16: =IF(AE$3,ROUND(H16,0),0) -> 0 | AF16: =IF(AF$3,ROUND(I16,0),0) -> 0 | AG16: =IF(AG$3,ROUND(J16,0),0) -> 0 | AH16: =IF(AH$3,ROUND(K16,0),0) -> 0 | AI16: =IF(AI$3,ROUND(L16,0),0) -> 0 | AK16: =IF(AK$3,ROUND(D16,0),0) -> 0 | AL16: =IF(AL$3,ROUND(E16,0),0) -> 0 | AM16: =IF(AM$3,ROUND(F16,0),0) -> 0 | AN16: =IF(AN$3,ROUND(G16,0),0) -> 0 | AO16: =IF(AO$3,ROUND(H16,0),0) -> 0 | AP16: =IF(AP$3,ROUND(I16,0),0) -> 0 | AQ16: =IF(AQ$3,ROUND(J16,0),0) -> 0 | AR16: =IF(AR$3,ROUND(K16,0),0) -> 0 | AS16: =IF(AS$3,ROUND(L16,0),0) -> 0
B17: 12 | C17: FATCA filing requirement | M17: =" - - - -" -> - - - - | N17: =" - - - -" -> - - - - | O17: =" - - - -" -> - - - - | Q17: =IF(Q$3,ROUND(D17,0),0) -> 0 | R17: =IF(R$3,ROUND(E17,0),0) -> 0 | S17: =IF(S$3,ROUND(F17,0),0) -> 0 | T17: =IF(T$3,ROUND(G17,0),0) -> 0 | U17: =IF(U$3,ROUND(H17,0),0) -> 0 | V17: =IF(V$3,ROUND(I17,0),0) -> 0 | W17: =IF(W$3,ROUND(J17,0),0) -> 0 | X17: =IF(X$3,ROUND(K17,0),0) -> 0 | Y17: =IF(Y$3,ROUND(L17,0),0) -> 0 | AA17: =IF(AA$3,ROUND(D17,0),0) -> 0 | AB17: =IF(AB$3,ROUND(E17,0),0) -> 0 | AC17: =IF(AC$3,ROUND(F17,0),0) -> 0 | AD17: =IF(AD$3,ROUND(G17,0),0) -> 0 | AE17: =IF(AE$3,ROUND(H17,0),0) -> 0 | AF17: =IF(AF$3,ROUND(I17,0),0) -> 0 | AG17: =IF(AG$3,ROUND(J17,0),0) -> 0 | AH17: =IF(AH$3,ROUND(K17,0),0) -> 0 | AI17: =IF(AI$3,ROUND(L17,0),0) -> 0 | AK17: =IF(AK$3,ROUND(D17,0),0) -> 0 | AL17: =IF(AL$3,ROUND(E17,0),0) -> 0 | AM17: =IF(AM$3,ROUND(F17,0),0) -> 0 | AN17: =IF(AN$3,ROUND(G17,0),0) -> 0 | AO17: =IF(AO$3,ROUND(H17,0),0) -> 0 | AP17: =IF(AP$3,ROUND(I17,0),0) -> 0 | AQ17: =IF(AQ$3,ROUND(J17,0),0) -> 0 | AR17: =IF(AR$3,ROUND(K17,0),0) -> 0 | AS17: =IF(AS$3,ROUND(L17,0),0) -> 0
B18: 13 | C18: Date of Payment | M18: =" - - - -" -> - - - - | N18: =" - - - -" -> - - - - | O18: =" - - - -" -> - - - - | Q18: =IF(Q$3,ROUND(D18,0),0) -> 0 | R18: =IF(R$3,ROUND(E18,0),0) -> 0 | S18: =IF(S$3,ROUND(F18,0),0) -> 0 | T18: =IF(T$3,ROUND(G18,0),0) -> 0 | U18: =IF(U$3,ROUND(H18,0),0) -> 0 | V18: =IF(V$3,ROUND(I18,0),0) -> 0 | W18: =IF(W$3,ROUND(J18,0),0) -> 0 | X18: =IF(X$3,ROUND(K18,0),0) -> 0 | Y18: =IF(Y$3,ROUND(L18,0),0) -> 0 | AA18: =IF(AA$3,ROUND(D18,0),0) -> 0 | AB18: =IF(AB$3,ROUND(E18,0),0) -> 0 | AC18: =IF(AC$3,ROUND(F18,0),0) -> 0 | AD18: =IF(AD$3,ROUND(G18,0),0) -> 0 | AE18: =IF(AE$3,ROUND(H18,0),0) -> 0 | AF18: =IF(AF$3,ROUND(I18,0),0) -> 0 | AG18: =IF(AG$3,ROUND(J18,0),0) -> 0 | AH18: =IF(AH$3,ROUND(K18,0),0) -> 0 | AI18: =IF(AI$3,ROUND(L18,0),0) -> 0 | AK18: =IF(AK$3,ROUND(D18,0),0) -> 0 | AL18: =IF(AL$3,ROUND(E18,0),0) -> 0 | AM18: =IF(AM$3,ROUND(F18,0),0) -> 0 | AN18: =IF(AN$3,ROUND(G18,0),0) -> 0 | AO18: =IF(AO$3,ROUND(H18,0),0) -> 0 | AP18: =IF(AP$3,ROUND(I18,0),0) -> 0 | AQ18: =IF(AQ$3,ROUND(J18,0),0) -> 0 | AR18: =IF(AR$3,ROUND(K18,0),0) -> 0 | AS18: =IF(AS$3,ROUND(L18,0),0) -> 0
B19: 14 | C19: State tax withheld | M19: =SUM(Q19:Y19) -> 0 | N19: =SUM(AA19:AI19) -> 0 | O19: =SUM(AK19:AS19) -> 0 | Q19: =IF(Q$3,ROUND(D19,0),0) -> 0 | R19: =IF(R$3,ROUND(E19,0),0) -> 0 | S19: =IF(S$3,ROUND(F19,0),0) -> 0 | T19: =IF(T$3,ROUND(G19,0),0) -> 0 | U19: =IF(U$3,ROUND(H19,0),0) -> 0 | V19: =IF(V$3,ROUND(I19,0),0) -> 0 | W19: =IF(W$3,ROUND(J19,0),0) -> 0 | X19: =IF(X$3,ROUND(K19,0),0) -> 0 | Y19: =IF(Y$3,ROUND(L19,0),0) -> 0 | AA19: =IF(AA$3,ROUND(D19,0),0) -> 0 | AB19: =IF(AB$3,ROUND(E19,0),0) -> 0 | AC19: =IF(AC$3,ROUND(F19,0),0) -> 0 | AD19: =IF(AD$3,ROUND(G19,0),0) -> 0 | AE19: =IF(AE$3,ROUND(H19,0),0) -> 0 | AF19: =IF(AF$3,ROUND(I19,0),0) -> 0 | AG19: =IF(AG$3,ROUND(J19,0),0) -> 0 | AH19: =IF(AH$3,ROUND(K19,0),0) -> 0 | AI19: =IF(AI$3,ROUND(L19,0),0) -> 0 | AK19: =IF(AK$3,ROUND(D19,0),0) -> 0 | AL19: =IF(AL$3,ROUND(E19,0),0) -> 0 | AM19: =IF(AM$3,ROUND(F19,0),0) -> 0 | AN19: =IF(AN$3,ROUND(G19,0),0) -> 0 | AO19: =IF(AO$3,ROUND(H19,0),0) -> 0 | AP19: =IF(AP$3,ROUND(I19,0),0) -> 0 | AQ19: =IF(AQ$3,ROUND(J19,0),0) -> 0 | AR19: =IF(AR$3,ROUND(K19,0),0) -> 0 | AS19: =IF(AS$3,ROUND(L19,0),0) -> 0
B20: 15 | C20: State/payer's state no. | M20: =" - - - -" -> - - - - | N20: =" - - - -" -> - - - - | O20: =" - - - -" -> - - - -
B21: 16 | C21: State distribution | M21: =SUM(Q21:Y21) -> 0 | N21: =SUM(AA21:AI21) -> 0 | O21: =SUM(AK21:AS21) -> 0 | Q21: =IF(Q$3,ROUND(D21,0),0) -> 0 | R21: =IF(R$3,ROUND(E21,0),0) -> 0 | S21: =IF(S$3,ROUND(F21,0),0) -> 0 | T21: =IF(T$3,ROUND(G21,0),0) -> 0 | U21: =IF(U$3,ROUND(H21,0),0) -> 0 | V21: =IF(V$3,ROUND(I21,0),0) -> 0 | W21: =IF(W$3,ROUND(J21,0),0) -> 0 | X21: =IF(X$3,ROUND(K21,0),0) -> 0 | Y21: =IF(Y$3,ROUND(L21,0),0) -> 0 | AA21: =IF(AA$3,ROUND(D21,0),0) -> 0 | AB21: =IF(AB$3,ROUND(E21,0),0) -> 0 | AC21: =IF(AC$3,ROUND(F21,0),0) -> 0 | AD21: =IF(AD$3,ROUND(G21,0),0) -> 0 | AE21: =IF(AE$3,ROUND(H21,0),0) -> 0 | AF21: =IF(AF$3,ROUND(I21,0),0) -> 0 | AG21: =IF(AG$3,ROUND(J21,0),0) -> 0 | AH21: =IF(AH$3,ROUND(K21,0),0) -> 0 | AI21: =IF(AI$3,ROUND(L21,0),0) -> 0 | AK21: =IF(AK$3,ROUND(D21,0),0) -> 0 | AL21: =IF(AL$3,ROUND(E21,0),0) -> 0 | AM21: =IF(AM$3,ROUND(F21,0),0) -> 0 | AN21: =IF(AN$3,ROUND(G21,0),0) -> 0 | AO21: =IF(AO$3,ROUND(H21,0),0) -> 0 | AP21: =IF(AP$3,ROUND(I21,0),0) -> 0 | AQ21: =IF(AQ$3,ROUND(J21,0),0) -> 0 | AR21: =IF(AR$3,ROUND(K21,0),0) -> 0 | AS21: =IF(AS$3,ROUND(L21,0),0) -> 0
B22: 17 | C22: Local tax withheld | M22: =SUM(Q22:Y22) -> 0 | N22: =SUM(AA22:AI22) -> 0 | O22: =SUM(AK22:AS22) -> 0 | Q22: =IF(Q$3,ROUND(D22,0),0) -> 0 | R22: =IF(R$3,ROUND(E22,0),0) -> 0 | S22: =IF(S$3,ROUND(F22,0),0) -> 0 | T22: =IF(T$3,ROUND(G22,0),0) -> 0 | U22: =IF(U$3,ROUND(H22,0),0) -> 0 | V22: =IF(V$3,ROUND(I22,0),0) -> 0 | W22: =IF(W$3,ROUND(J22,0),0) -> 0 | X22: =IF(X$3,ROUND(K22,0),0) -> 0 | Y22: =IF(Y$3,ROUND(L22,0),0) -> 0 | AA22: =IF(AA$3,ROUND(D22,0),0) -> 0 | AB22: =IF(AB$3,ROUND(E22,0),0) -> 0 | AC22: =IF(AC$3,ROUND(F22,0),0) -> 0 | AD22: =IF(AD$3,ROUND(G22,0),0) -> 0 | AE22: =IF(AE$3,ROUND(H22,0),0) -> 0 | AF22: =IF(AF$3,ROUND(I22,0),0) -> 0 | AG22: =IF(AG$3,ROUND(J22,0),0) -> 0 | AH22: =IF(AH$3,ROUND(K22,0),0) -> 0 | AI22: =IF(AI$3,ROUND(L22,0),0) -> 0 | AK22: =IF(AK$3,ROUND(D22,0),0) -> 0 | AL22: =IF(AL$3,ROUND(E22,0),0) -> 0 | AM22: =IF(AM$3,ROUND(F22,0),0) -> 0 | AN22: =IF(AN$3,ROUND(G22,0),0) -> 0 | AO22: =IF(AO$3,ROUND(H22,0),0) -> 0 | AP22: =IF(AP$3,ROUND(I22,0),0) -> 0 | AQ22: =IF(AQ$3,ROUND(J22,0),0) -> 0 | AR22: =IF(AR$3,ROUND(K22,0),0) -> 0 | AS22: =IF(AS$3,ROUND(L22,0),0) -> 0
B23: 18 | C23: Name of locality | D23: =OR(D3="CONV",D3="conv") -> FALSE | E23: =OR(E3="CONV",E3="conv") -> FALSE | F23: =OR(F3="CONV",F3="conv") -> FALSE | G23: =OR(G3="CONV",G3="conv") -> FALSE | H23: =OR(H3="CONV",H3="conv") -> FALSE | I23: =OR(I3="CONV",I3="conv") -> FALSE | J23: =OR(J3="CONV",J3="conv") -> FALSE | K23: =OR(K3="CONV",K3="conv") -> FALSE | L23: =OR(L3="CONV",L3="conv") -> FALSE | M23: =" - - - -" -> - - - - | N23: =" - - - -" -> - - - - | O23: =" - - - -" -> - - - -
B24: 19 | C24: Local distribution | M24: =SUM(Q24:Y24) -> 0 | N24: =SUM(AA24:AI24) -> 0 | O24: =SUM(AK24:AS24) -> 0 | Q24: =IF(Q$3,ROUND(D24,0),0) -> 0 | R24: =IF(R$3,ROUND(E24,0),0) -> 0 | S24: =IF(S$3,ROUND(F24,0),0) -> 0 | T24: =IF(T$3,ROUND(G24,0),0) -> 0 | U24: =IF(U$3,ROUND(H24,0),0) -> 0 | V24: =IF(V$3,ROUND(I24,0),0) -> 0 | W24: =IF(W$3,ROUND(J24,0),0) -> 0 | X24: =IF(X$3,ROUND(K24,0),0) -> 0 | Y24: =IF(Y$3,ROUND(L24,0),0) -> 0 | AA24: =IF(AA$3,ROUND(D24,0),0) -> 0 | AB24: =IF(AB$3,ROUND(E24,0),0) -> 0 | AC24: =IF(AC$3,ROUND(F24,0),0) -> 0 | AD24: =IF(AD$3,ROUND(G24,0),0) -> 0 | AE24: =IF(AE$3,ROUND(H24,0),0) -> 0 | AF24: =IF(AF$3,ROUND(I24,0),0) -> 0 | AG24: =IF(AG$3,ROUND(J24,0),0) -> 0 | AH24: =IF(AH$3,ROUND(K24,0),0) -> 0 | AI24: =IF(AI$3,ROUND(L24,0),0) -> 0 | AK24: =IF(AK$3,ROUND(D24,0),0) -> 0 | AL24: =IF(AL$3,ROUND(E24,0),0) -> 0 | AM24: =IF(AM$3,ROUND(F24,0),0) -> 0 | AN24: =IF(AN$3,ROUND(G24,0),0) -> 0 | AO24: =IF(AO$3,ROUND(H24,0),0) -> 0 | AP24: =IF(AP$3,ROUND(I24,0),0) -> 0 | AQ24: =IF(AQ$3,ROUND(J24,0),0) -> 0 | AR24: =IF(AR$3,ROUND(K24,0),0) -> 0 | AS24: =IF(AS$3,ROUND(L24,0),0) -> 0
B25: Only bolded amounts are used in this spreadsheet. | D25: =OR(D23:L23) -> FALSE
D26: =IF(OR(LEFT(D11,1)="D",LEFT(D11,1)="d"),D5,"") | E26: =IF(OR(LEFT(E11,1)="D",LEFT(E11,1)="d"),E5,"") | F26: =IF(OR(LEFT(F11,1)="D",LEFT(F11,1)="d"),F5,"") | G26: =IF(OR(LEFT(G11,1)="D",LEFT(G11,1)="d"),G5,"") | H26: =IF(OR(LEFT(H11,1)="D",LEFT(H11,1)="d"),H5,"") | I26: =IF(OR(LEFT(I11,1)="D",LEFT(I11,1)="d"),I5,"") | J26: =IF(OR(LEFT(J11,1)="D",LEFT(J11,1)="d"),J5,"") | K26: =IF(OR(LEFT(K11,1)="D",LEFT(K11,1)="d"),K5,"") | L26: =IF(OR(LEFT(L11,1)="D",LEFT(L11,1)="d"),L5,"") | N26: =SUM(D26:L26) -> 0 | O26: =SUM(E26:M26) -> 0
D27: =IF(OR(LEFT(D11,1)="D",LEFT(D11,1)="d"),SUM(D19,D22),"") | E27: =IF(OR(LEFT(E11,1)="D",LEFT(E11,1)="d"),SUM(E19,E22),"") | F27: =IF(OR(LEFT(F11,1)="D",LEFT(F11,1)="d"),SUM(F19,F22),"") | G27: =IF(OR(LEFT(G11,1)="D",LEFT(G11,1)="d"),SUM(G19,G22),"") | H27: =IF(OR(LEFT(H11,1)="D",LEFT(H11,1)="d"),SUM(H19,H22),"") | I27: =IF(OR(LEFT(I11,1)="D",LEFT(I11,1)="d"),SUM(I19,I22),"") | J27: =IF(OR(LEFT(J11,1)="D",LEFT(J11,1)="d"),SUM(J19,J22),"") | K27: =IF(OR(LEFT(K11,1)="D",LEFT(K11,1)="d"),SUM(K19,K22),"") | L27: =IF(OR(LEFT(L11,1)="D",LEFT(L11,1)="d"),SUM(L19,L22),"") | N27: =SUM(D27:L27) -> 0 | O27: =SUM(E27:M27) -> 0
B28: Information from Form 1099-R, Distributions From Pensions, Annuities, Retirement or Profit-Sharing Plans, IRAs, Insurance Contracts, etc.
C29: =IF(Name_1st_Sp="","Enter your spouse's name on the"&CHAR(10)&"sheet labeled '1040'",NameSpouse) -> Enter your spouse's name on the sheet labeled '1040' | D29: Payer #1 | E29: Payer #2 | F29: Payer #3 | G29: Payer #4 | H29: Payer #5 | I29: Payer #6 | J29: Payer #7 | K29: Payer #8 | L29: Payer #9 | M29: Total IRAs | N29: Total Pension / Annuities | O29: Qualified Conversion to ROTH IRA
C30: Enter "IRA" or "P/A" or "CONV" >>> | M30: IRA | N30: P/A | O30: CONV | Q30: =NOT(AND(ISERROR(FIND("IRA",D30,1)),ISERROR(FIND("ira",D30,1)))) -> FALSE | R30: =NOT(AND(ISERROR(FIND("IRA",E30,1)),ISERROR(FIND("ira",E30,1)))) -> FALSE | S30: =NOT(AND(ISERROR(FIND("IRA",F30,1)),ISERROR(FIND("ira",F30,1)))) -> FALSE | T30: =NOT(AND(ISERROR(FIND("IRA",G30,1)),ISERROR(FIND("ira",G30,1)))) -> FALSE | U30: =NOT(AND(ISERROR(FIND("IRA",H30,1)),ISERROR(FIND("ira",H30,1)))) -> FALSE | V30: =NOT(AND(ISERROR(FIND("IRA",I30,1)),ISERROR(FIND("ira",I30,1)))) -> FALSE | W30: =NOT(AND(ISERROR(FIND("IRA",J30,1)),ISERROR(FIND("ira",J30,1)))) -> FALSE | X30: =NOT(AND(ISERROR(FIND("IRA",K30,1)),ISERROR(FIND("ira",K30,1)))) -> FALSE | Y30: =NOT(AND(ISERROR(FIND("IRA",L30,1)),ISERROR(FIND("ira",L30,1)))) -> FALSE | AA30: =NOT(AND(ISERROR(FIND("P/A",D30,1)),ISERROR(FIND("p/a",D30,1)))) -> FALSE | AB30: =NOT(AND(ISERROR(FIND("P/A",E30,1)),ISERROR(FIND("p/a",E30,1)))) -> FALSE | AC30: =NOT(AND(ISERROR(FIND("P/A",F30,1)),ISERROR(FIND("p/a",F30,1)))) -> FALSE | AD30: =NOT(AND(ISERROR(FIND("P/A",G30,1)),ISERROR(FIND("p/a",G30,1)))) -> FALSE | AE30: =NOT(AND(ISERROR(FIND("P/A",H30,1)),ISERROR(FIND("p/a",H30,1)))) -> FALSE | AF30: =NOT(AND(ISERROR(FIND("P/A",I30,1)),ISERROR(FIND("p/a",I30,1)))) -> FALSE | AG30: =NOT(AND(ISERROR(FIND("P/A",J30,1)),ISERROR(FIND("p/a",J30,1)))) -> FALSE | AH30: =NOT(AND(ISERROR(FIND("P/A",K30,1)),ISERROR(FIND("p/a",K30,1)))) -> FALSE | AI30: =NOT(AND(ISERROR(FIND("P/A",L30,1)),ISERROR(FIND("p/a",L30,1)))) -> FALSE | AK30: =NOT(AND(ISERROR(FIND("CONV",D30,1)),ISERROR(FIND("conv",D30,1)))) -> FALSE | AL30: =NOT(AND(ISERROR(FIND("CONV",E30,1)),ISERROR(FIND("conv",E30,1)))) -> FALSE | AM30: =NOT(AND(ISERROR(FIND("CONV",F30,1)),ISERROR(FIND("conv",F30,1)))) -> FALSE | AN30: =NOT(AND(ISERROR(FIND("CONV",G30,1)),ISERROR(FIND("conv",G30,1)))) -> FALSE | AO30: =NOT(AND(ISERROR(FIND("CONV",H30,1)),ISERROR(FIND("conv",H30,1)))) -> FALSE | AP30: =NOT(AND(ISERROR(FIND("CONV",I30,1)),ISERROR(FIND("conv",I30,1)))) -> FALSE | AQ30: =NOT(AND(ISERROR(FIND("CONV",J30,1)),ISERROR(FIND("conv",J30,1)))) -> FALSE | AR30: =NOT(AND(ISERROR(FIND("CONV",K30,1)),ISERROR(FIND("conv",K30,1)))) -> FALSE | AS30: =NOT(AND(ISERROR(FIND("CONV",L30,1)),ISERROR(FIND("conv",L30,1)))) -> FALSE
B31: 1 | C31: Gross distribution | M31: =SUM(Q31:Y31) -> 0 | N31: =SUM(AA31:AI31) -> 0 | O31: =SUM(AK31:AS31) -> 0 | Q31: =IF(Q$30,ROUND(D31,0),0) -> 0 | R31: =IF(R$30,ROUND(E31,0),0) -> 0 | S31: =IF(S$30,ROUND(F31,0),0) -> 0 | T31: =IF(T$30,ROUND(G31,0),0) -> 0 | U31: =IF(U$30,ROUND(H31,0),0) -> 0 | V31: =IF(V$30,ROUND(I31,0),0) -> 0 | W31: =IF(W$30,ROUND(J31,0),0) -> 0 | X31: =IF(X$30,ROUND(K31,0),0) -> 0 | Y31: =IF(Y$30,ROUND(L31,0),0) -> 0 | AA31: =IF(AA$30,ROUND(D31,0),0) -> 0 | AB31: =IF(AB$30,ROUND(E31,0),0) -> 0 | AC31: =IF(AC$30,ROUND(F31,0),0) -> 0 | AD31: =IF(AD$30,ROUND(G31,0),0) -> 0 | AE31: =IF(AE$30,ROUND(H31,0),0) -> 0 | AF31: =IF(AF$30,ROUND(I31,0),0) -> 0 | AG31: =IF(AG$30,ROUND(J31,0),0) -> 0 | AH31: =IF(AH$30,ROUND(K31,0),0) -> 0 | AI31: =IF(AI$30,ROUND(L31,0),0) -> 0 | AK31: =IF(AK$30,ROUND(D31,0),0) -> 0 | AL31: =IF(AL$30,ROUND(E31,0),0) -> 0 | AM31: =IF(AM$30,ROUND(F31,0),0) -> 0 | AN31: =IF(AN$30,ROUND(G31,0),0) -> 0 | AO31: =IF(AO$30,ROUND(H31,0),0) -> 0 | AP31: =IF(AP$30,ROUND(I31,0),0) -> 0 | AQ31: =IF(AQ$30,ROUND(J31,0),0) -> 0 | AR31: =IF(AR$30,ROUND(K31,0),0) -> 0 | AS31: =IF(AS$30,ROUND(L31,0),0) -> 0
B32: 2a | C32: Taxable amount | M32: =SUM(Q32:Y32) -> 0 | N32: =SUM(AA32:AI32) -> 0 | O32: =SUM(AK32:AS32) -> 0 | Q32: =IF(Q$30,ROUND(D32,0),0) -> 0 | R32: =IF(R$30,ROUND(E32,0),0) -> 0 | S32: =IF(S$30,ROUND(F32,0),0) -> 0 | T32: =IF(T$30,ROUND(G32,0),0) -> 0 | U32: =IF(U$30,ROUND(H32,0),0) -> 0 | V32: =IF(V$30,ROUND(I32,0),0) -> 0 | W32: =IF(W$30,ROUND(J32,0),0) -> 0 | X32: =IF(X$30,ROUND(K32,0),0) -> 0 | Y32: =IF(Y$30,ROUND(L32,0),0) -> 0 | AA32: =IF(AA$30,ROUND(D32,0),0) -> 0 | AB32: =IF(AB$30,ROUND(E32,0),0) -> 0 | AC32: =IF(AC$30,ROUND(F32,0),0) -> 0 | AD32: =IF(AD$30,ROUND(G32,0),0) -> 0 | AE32: =IF(AE$30,ROUND(H32,0),0) -> 0 | AF32: =IF(AF$30,ROUND(I32,0),0) -> 0 | AG32: =IF(AG$30,ROUND(J32,0),0) -> 0 | AH32: =IF(AH$30,ROUND(K32,0),0) -> 0 | AI32: =IF(AI$30,ROUND(L32,0),0) -> 0 | AK32: =IF(AK$30,ROUND(D32,0),0) -> 0 | AL32: =IF(AL$30,ROUND(E32,0),0) -> 0 | AM32: =IF(AM$30,ROUND(F32,0),0) -> 0 | AN32: =IF(AN$30,ROUND(G32,0),0) -> 0 | AO32: =IF(AO$30,ROUND(H32,0),0) -> 0 | AP32: =IF(AP$30,ROUND(I32,0),0) -> 0 | AQ32: =IF(AQ$30,ROUND(J32,0),0) -> 0 | AR32: =IF(AR$30,ROUND(K32,0),0) -> 0 | AS32: =IF(AS$30,ROUND(L32,0),0) -> 0
B33: 2b | C33: Taxable amount not determined / total distr. | M33: =" - - - -" -> - - - - | N33: =" - - - -" -> - - - - | O33: =" - - - -" -> - - - -
B34: 3 | C34: Capital gain (not included in box 2a) | M34: =SUM(Q34:Y34) -> 0 | N34: =SUM(AA34:AI34) -> 0 | O34: =SUM(AK34:AS34) -> 0 | Q34: =IF(Q$30,ROUND(D34,0),0) -> 0 | R34: =IF(R$30,ROUND(E34,0),0) -> 0 | S34: =IF(S$30,ROUND(F34,0),0) -> 0 | T34: =IF(T$30,ROUND(G34,0),0) -> 0 | U34: =IF(U$30,ROUND(H34,0),0) -> 0 | V34: =IF(V$30,ROUND(I34,0),0) -> 0 | W34: =IF(W$30,ROUND(J34,0),0) -> 0 | X34: =IF(X$30,ROUND(K34,0),0) -> 0 | Y34: =IF(Y$30,ROUND(L34,0),0) -> 0 | AA34: =IF(AA$30,ROUND(D34,0),0) -> 0 | AB34: =IF(AB$30,ROUND(E34,0),0) -> 0 | AC34: =IF(AC$30,ROUND(F34,0),0) -> 0 | AD34: =IF(AD$30,ROUND(G34,0),0) -> 0 | AE34: =IF(AE$30,ROUND(H34,0),0) -> 0 | AF34: =IF(AF$30,ROUND(I34,0),0) -> 0 | AG34: =IF(AG$30,ROUND(J34,0),0) -> 0 | AH34: =IF(AH$30,ROUND(K34,0),0) -> 0 | AI34: =IF(AI$30,ROUND(L34,0),0) -> 0 | AK34: =IF(AK$30,ROUND(D34,0),0) -> 0 | AL34: =IF(AL$30,ROUND(E34,0),0) -> 0 | AM34: =IF(AM$30,ROUND(F34,0),0) -> 0 | AN34: =IF(AN$30,ROUND(G34,0),0) -> 0 | AO34: =IF(AO$30,ROUND(H34,0),0) -> 0 | AP34: =IF(AP$30,ROUND(I34,0),0) -> 0 | AQ34: =IF(AQ$30,ROUND(J34,0),0) -> 0 | AR34: =IF(AR$30,ROUND(K34,0),0) -> 0 | AS34: =IF(AS$30,ROUND(L34,0),0) -> 0
B35: 4 | C35: Federal income tax withheld | M35: =SUM(Q35:Y35) -> 0 | N35: =SUM(AA35:AI35) -> 0 | O35: =SUM(AK35:AS35) -> 0 | Q35: =IF(Q$30,ROUND(D35,0),0) -> 0 | R35: =IF(R$30,ROUND(E35,0),0) -> 0 | S35: =IF(S$30,ROUND(F35,0),0) -> 0 | T35: =IF(T$30,ROUND(G35,0),0) -> 0 | U35: =IF(U$30,ROUND(H35,0),0) -> 0 | V35: =IF(V$30,ROUND(I35,0),0) -> 0 | W35: =IF(W$30,ROUND(J35,0),0) -> 0 | X35: =IF(X$30,ROUND(K35,0),0) -> 0 | Y35: =IF(Y$30,ROUND(L35,0),0) -> 0 | AA35: =IF(AA$30,ROUND(D35,0),0) -> 0 | AB35: =IF(AB$30,ROUND(E35,0),0) -> 0 | AC35: =IF(AC$30,ROUND(F35,0),0) -> 0 | AD35: =IF(AD$30,ROUND(G35,0),0) -> 0 | AE35: =IF(AE$30,ROUND(H35,0),0) -> 0 | AF35: =IF(AF$30,ROUND(I35,0),0) -> 0 | AG35: =IF(AG$30,ROUND(J35,0),0) -> 0 | AH35: =IF(AH$30,ROUND(K35,0),0) -> 0 | AI35: =IF(AI$30,ROUND(L35,0),0) -> 0 | AK35: =IF(AK$30,ROUND(D35,0),0) -> 0 | AL35: =IF(AL$30,ROUND(E35,0),0) -> 0 | AM35: =IF(AM$30,ROUND(F35,0),0) -> 0 | AN35: =IF(AN$30,ROUND(G35,0),0) -> 0 | AO35: =IF(AO$30,ROUND(H35,0),0) -> 0 | AP35: =IF(AP$30,ROUND(I35,0),0) -> 0 | AQ35: =IF(AQ$30,ROUND(J35,0),0) -> 0 | AR35: =IF(AR$30,ROUND(K35,0),0) -> 0 | AS35: =IF(AS$30,ROUND(L35,0),0) -> 0
B36: 5 | C36: Employee contributions / Insurance premiums / Designated Roth IRA contributions | M36: =SUM(Q36:Y36) -> 0 | N36: =SUM(AA36:AI36) -> 0 | O36: =SUM(AK36:AS36) -> 0 | Q36: =IF(Q$30,ROUND(D36,0),0) -> 0 | R36: =IF(R$30,ROUND(E36,0),0) -> 0 | S36: =IF(S$30,ROUND(F36,0),0) -> 0 | T36: =IF(T$30,ROUND(G36,0),0) -> 0 | U36: =IF(U$30,ROUND(H36,0),0) -> 0 | V36: =IF(V$30,ROUND(I36,0),0) -> 0 | W36: =IF(W$30,ROUND(J36,0),0) -> 0 | X36: =IF(X$30,ROUND(K36,0),0) -> 0 | Y36: =IF(Y$30,ROUND(L36,0),0) -> 0 | AA36: =IF(AA$30,ROUND(D36,0),0) -> 0 | AB36: =IF(AB$30,ROUND(E36,0),0) -> 0 | AC36: =IF(AC$30,ROUND(F36,0),0) -> 0 | AD36: =IF(AD$30,ROUND(G36,0),0) -> 0 | AE36: =IF(AE$30,ROUND(H36,0),0) -> 0 | AF36: =IF(AF$30,ROUND(I36,0),0) -> 0 | AG36: =IF(AG$30,ROUND(J36,0),0) -> 0 | AH36: =IF(AH$30,ROUND(K36,0),0) -> 0 | AI36: =IF(AI$30,ROUND(L36,0),0) -> 0 | AK36: =IF(AK$30,ROUND(D36,0),0) -> 0 | AL36: =IF(AL$30,ROUND(E36,0),0) -> 0 | AM36: =IF(AM$30,ROUND(F36,0),0) -> 0 | AN36: =IF(AN$30,ROUND(G36,0),0) -> 0 | AO36: =IF(AO$30,ROUND(H36,0),0) -> 0 | AP36: =IF(AP$30,ROUND(I36,0),0) -> 0 | AQ36: =IF(AQ$30,ROUND(J36,0),0) -> 0 | AR36: =IF(AR$30,ROUND(K36,0),0) -> 0 | AS36: =IF(AS$30,ROUND(L36,0),0) -> 0
B37: 6 | C37: Net unrealized appreciation in employer's securities | M37: =SUM(Q37:Y37) -> 0 | N37: =SUM(AA37:AI37) -> 0 | O37: =SUM(AK37:AS37) -> 0 | Q37: =IF(Q$30,ROUND(D37,0),0) -> 0 | R37: =IF(R$30,ROUND(E37,0),0) -> 0 | S37: =IF(S$30,ROUND(F37,0),0) -> 0 | T37: =IF(T$30,ROUND(G37,0),0) -> 0 | U37: =IF(U$30,ROUND(H37,0),0) -> 0 | V37: =IF(V$30,ROUND(I37,0),0) -> 0 | W37: =IF(W$30,ROUND(J37,0),0) -> 0 | X37: =IF(X$30,ROUND(K37,0),0) -> 0 | Y37: =IF(Y$30,ROUND(L37,0),0) -> 0 | AA37: =IF(AA$30,ROUND(D37,0),0) -> 0 | AB37: =IF(AB$30,ROUND(E37,0),0) -> 0 | AC37: =IF(AC$30,ROUND(F37,0),0) -> 0 | AD37: =IF(AD$30,ROUND(G37,0),0) -> 0 | AE37: =IF(AE$30,ROUND(H37,0),0) -> 0 | AF37: =IF(AF$30,ROUND(I37,0),0) -> 0 | AG37: =IF(AG$30,ROUND(J37,0),0) -> 0 | AH37: =IF(AH$30,ROUND(K37,0),0) -> 0 | AI37: =IF(AI$30,ROUND(L37,0),0) -> 0 | AK37: =IF(AK$30,ROUND(D37,0),0) -> 0 | AL37: =IF(AL$30,ROUND(E37,0),0) -> 0 | AM37: =IF(AM$30,ROUND(F37,0),0) -> 0 | AN37: =IF(AN$30,ROUND(G37,0),0) -> 0 | AO37: =IF(AO$30,ROUND(H37,0),0) -> 0 | AP37: =IF(AP$30,ROUND(I37,0),0) -> 0 | AQ37: =IF(AQ$30,ROUND(J37,0),0) -> 0 | AR37: =IF(AR$30,ROUND(K37,0),0) -> 0 | AS37: =IF(AS$30,ROUND(L37,0),0) -> 0
B38: 7 | C38: Distribution code(s) (Code D only) | M38: =" - - - -" -> - - - - | N38: =" - - - -" -> - - - - | O38: =" - - - -" -> - - - -
B39: 8 | C39: Other | M39: =SUM(Q39:Y39) -> 0 | N39: =SUM(AA39:AI39) -> 0 | O39: =SUM(AK39:AS39) -> 0 | Q39: =IF(Q$30,ROUND(D39,0),0) -> 0 | R39: =IF(R$30,ROUND(E39,0),0) -> 0 | S39: =IF(S$30,ROUND(F39,0),0) -> 0 | T39: =IF(T$30,ROUND(G39,0),0) -> 0 | U39: =IF(U$30,ROUND(H39,0),0) -> 0 | V39: =IF(V$30,ROUND(I39,0),0) -> 0 | W39: =IF(W$30,ROUND(J39,0),0) -> 0 | X39: =IF(X$30,ROUND(K39,0),0) -> 0 | Y39: =IF(Y$30,ROUND(L39,0),0) -> 0 | AA39: =IF(AA$30,ROUND(D39,0),0) -> 0 | AB39: =IF(AB$30,ROUND(E39,0),0) -> 0 | AC39: =IF(AC$30,ROUND(F39,0),0) -> 0 | AD39: =IF(AD$30,ROUND(G39,0),0) -> 0 | AE39: =IF(AE$30,ROUND(H39,0),0) -> 0 | AF39: =IF(AF$30,ROUND(I39,0),0) -> 0 | AG39: =IF(AG$30,ROUND(J39,0),0) -> 0 | AH39: =IF(AH$30,ROUND(K39,0),0) -> 0 | AI39: =IF(AI$30,ROUND(L39,0),0) -> 0 | AK39: =IF(AK$30,ROUND(D39,0),0) -> 0 | AL39: =IF(AL$30,ROUND(E39,0),0) -> 0 | AM39: =IF(AM$30,ROUND(F39,0),0) -> 0 | AN39: =IF(AN$30,ROUND(G39,0),0) -> 0 | AO39: =IF(AO$30,ROUND(H39,0),0) -> 0 | AP39: =IF(AP$30,ROUND(I39,0),0) -> 0 | AQ39: =IF(AQ$30,ROUND(J39,0),0) -> 0 | AR39: =IF(AR$30,ROUND(K39,0),0) -> 0 | AS39: =IF(AS$30,ROUND(L39,0),0) -> 0
B40: 9a | C40: Your percentage of total distribution | M40: =SUM(Q40:Y40) -> 0 | N40: =SUM(AA40:AI40) -> 0 | O40: =SUM(AK40:AS40) -> 0 | Q40: =IF(Q30,D40,0) -> 0 | R40: =IF(R30,E40,0) -> 0 | S40: =IF(S30,F40,0) -> 0 | T40: =IF(T30,G40,0) -> 0 | U40: =IF(U30,H40,0) -> 0 | V40: =IF(V30,I40,0) -> 0 | W40: =IF(W30,J40,0) -> 0 | X40: =IF(X30,K40,0) -> 0 | Y40: =IF(Y30,L40,0) -> 0 | AA40: =IF(AA30,D40,0) -> 0 | AB40: =IF(AB30,E40,0) -> 0 | AC40: =IF(AC30,F40,0) -> 0 | AD40: =IF(AD30,G40,0) -> 0 | AE40: =IF(AE30,H40,0) -> 0 | AF40: =IF(AF30,I40,0) -> 0 | AG40: =IF(AG30,J40,0) -> 0 | AH40: =IF(AH30,K40,0) -> 0 | AI40: =IF(AI30,L40,0) -> 0 | AK40: =IF(AK30,D40,0) -> 0 | AL40: =IF(AL30,E40,0) -> 0 | AM40: =IF(AM30,F40,0) -> 0 | AN40: =IF(AN30,G40,0) -> 0 | AO40: =IF(AO30,H40,0) -> 0 | AP40: =IF(AP30,I40,0) -> 0 | AQ40: =IF(AQ30,J40,0) -> 0 | AR40: =IF(AR30,K40,0) -> 0 | AS40: =IF(AS30,L40,0) -> 0
B41: 9b | C41: Total employee contributions | M41: =SUM(Q41:Y41) -> 0 | N41: =SUM(AA41:AI41) -> 0 | O41: =SUM(AK41:AS41) -> 0 | Q41: =IF(Q$30,ROUND(D41,0),0) -> 0 | R41: =IF(R$30,ROUND(E41,0),0) -> 0 | S41: =IF(S$30,ROUND(F41,0),0) -> 0 | T41: =IF(T$30,ROUND(G41,0),0) -> 0 | U41: =IF(U$30,ROUND(H41,0),0) -> 0 | V41: =IF(V$30,ROUND(I41,0),0) -> 0 | W41: =IF(W$30,ROUND(J41,0),0) -> 0 | X41: =IF(X$30,ROUND(K41,0),0) -> 0 | Y41: =IF(Y$30,ROUND(L41,0),0) -> 0 | AA41: =IF(AA$30,ROUND(D41,0),0) -> 0 | AB41: =IF(AB$30,ROUND(E41,0),0) -> 0 | AC41: =IF(AC$30,ROUND(F41,0),0) -> 0 | AD41: =IF(AD$30,ROUND(G41,0),0) -> 0 | AE41: =IF(AE$30,ROUND(H41,0),0) -> 0 | AF41: =IF(AF$30,ROUND(I41,0),0) -> 0 | AG41: =IF(AG$30,ROUND(J41,0),0) -> 0 | AH41: =IF(AH$30,ROUND(K41,0),0) -> 0 | AI41: =IF(AI$30,ROUND(L41,0),0) -> 0 | AK41: =IF(AK$30,ROUND(D41,0),0) -> 0 | AL41: =IF(AL$30,ROUND(E41,0),0) -> 0 | AM41: =IF(AM$30,ROUND(F41,0),0) -> 0 | AN41: =IF(AN$30,ROUND(G41,0),0) -> 0 | AO41: =IF(AO$30,ROUND(H41,0),0) -> 0 | AP41: =IF(AP$30,ROUND(I41,0),0) -> 0 | AQ41: =IF(AQ$30,ROUND(J41,0),0) -> 0 | AR41: =IF(AR$30,ROUND(K41,0),0) -> 0 | AS41: =IF(AS$30,ROUND(L41,0),0) -> 0
B42: 10 | C42: Amount allocable to IRR within 5 years | M42: =SUM(Q42:Y42) -> 0 | N42: =SUM(AA42:AI42) -> 0 | O42: =SUM(AK42:AS42) -> 0 | Q42: =IF(Q$30,ROUND(D42,0),0) -> 0 | R42: =IF(R$30,ROUND(E42,0),0) -> 0 | S42: =IF(S$30,ROUND(F42,0),0) -> 0 | T42: =IF(T$30,ROUND(G42,0),0) -> 0 | U42: =IF(U$30,ROUND(H42,0),0) -> 0 | V42: =IF(V$30,ROUND(I42,0),0) -> 0 | W42: =IF(W$30,ROUND(J42,0),0) -> 0 | X42: =IF(X$30,ROUND(K42,0),0) -> 0 | Y42: =IF(Y$30,ROUND(L42,0),0) -> 0 | AA42: =IF(AA$30,ROUND(D42,0),0) -> 0 | AB42: =IF(AB$30,ROUND(E42,0),0) -> 0 | AC42: =IF(AC$30,ROUND(F42,0),0) -> 0 | AD42: =IF(AD$30,ROUND(G42,0),0) -> 0 | AE42: =IF(AE$30,ROUND(H42,0),0) -> 0 | AF42: =IF(AF$30,ROUND(I42,0),0) -> 0 | AG42: =IF(AG$30,ROUND(J42,0),0) -> 0 | AH42: =IF(AH$30,ROUND(K42,0),0) -> 0 | AI42: =IF(AI$30,ROUND(L42,0),0) -> 0 | AK42: =IF(AK$30,ROUND(D42,0),0) -> 0 | AL42: =IF(AL$30,ROUND(E42,0),0) -> 0 | AM42: =IF(AM$30,ROUND(F42,0),0) -> 0 | AN42: =IF(AN$30,ROUND(G42,0),0) -> 0 | AO42: =IF(AO$30,ROUND(H42,0),0) -> 0 | AP42: =IF(AP$30,ROUND(I42,0),0) -> 0 | AQ42: =IF(AQ$30,ROUND(J42,0),0) -> 0 | AR42: =IF(AR$30,ROUND(K42,0),0) -> 0 | AS42: =IF(AS$30,ROUND(L42,0),0) -> 0
B43: 11 | C43: 1st year of desig. Roth contrib. | M43: =SUM(Q43:Y43) -> 0 | N43: =SUM(AA43:AI43) -> 0 | O43: =SUM(AK43:AS43) -> 0 | Q43: =IF(Q$30,ROUND(D43,0),0) -> 0 | R43: =IF(R$30,ROUND(E43,0),0) -> 0 | S43: =IF(S$30,ROUND(F43,0),0) -> 0 | T43: =IF(T$30,ROUND(G43,0),0) -> 0 | U43: =IF(U$30,ROUND(H43,0),0) -> 0 | V43: =IF(V$30,ROUND(I43,0),0) -> 0 | W43: =IF(W$30,ROUND(J43,0),0) -> 0 | X43: =IF(X$30,ROUND(K43,0),0) -> 0 | Y43: =IF(Y$30,ROUND(L43,0),0) -> 0 | AA43: =IF(AA$30,ROUND(D43,0),0) -> 0 | AB43: =IF(AB$30,ROUND(E43,0),0) -> 0 | AC43: =IF(AC$30,ROUND(F43,0),0) -> 0 | AD43: =IF(AD$30,ROUND(G43,0),0) -> 0 | AE43: =IF(AE$30,ROUND(H43,0),0) -> 0 | AF43: =IF(AF$30,ROUND(I43,0),0) -> 0 | AG43: =IF(AG$30,ROUND(J43,0),0) -> 0 | AH43: =IF(AH$30,ROUND(K43,0),0) -> 0 | AI43: =IF(AI$30,ROUND(L43,0),0) -> 0 | AK43: =IF(AK$30,ROUND(D43,0),0) -> 0 | AL43: =IF(AL$30,ROUND(E43,0),0) -> 0 | AM43: =IF(AM$30,ROUND(F43,0),0) -> 0 | AN43: =IF(AN$30,ROUND(G43,0),0) -> 0 | AO43: =IF(AO$30,ROUND(H43,0),0) -> 0 | AP43: =IF(AP$30,ROUND(I43,0),0) -> 0 | AQ43: =IF(AQ$30,ROUND(J43,0),0) -> 0 | AR43: =IF(AR$30,ROUND(K43,0),0) -> 0 | AS43: =IF(AS$30,ROUND(L43,0),0) -> 0
B44: 12 | C44: FATCA filing requirement | M44: =" - - - -" -> - - - - | N44: =" - - - -" -> - - - - | O44: =" - - - -" -> - - - - | Q44: =IF(Q$30,ROUND(D44,0),0) -> 0 | R44: =IF(R$30,ROUND(E44,0),0) -> 0 | S44: =IF(S$30,ROUND(F44,0),0) -> 0 | T44: =IF(T$30,ROUND(G44,0),0) -> 0 | U44: =IF(U$30,ROUND(H44,0),0) -> 0 | V44: =IF(V$30,ROUND(I44,0),0) -> 0 | W44: =IF(W$30,ROUND(J44,0),0) -> 0 | X44: =IF(X$30,ROUND(K44,0),0) -> 0 | Y44: =IF(Y$30,ROUND(L44,0),0) -> 0 | AA44: =IF(AA$30,ROUND(D44,0),0) -> 0 | AB44: =IF(AB$30,ROUND(E44,0),0) -> 0 | AC44: =IF(AC$30,ROUND(F44,0),0) -> 0 | AD44: =IF(AD$30,ROUND(G44,0),0) -> 0 | AE44: =IF(AE$30,ROUND(H44,0),0) -> 0 | AF44: =IF(AF$30,ROUND(I44,0),0) -> 0 | AG44: =IF(AG$30,ROUND(J44,0),0) -> 0 | AH44: =IF(AH$30,ROUND(K44,0),0) -> 0 | AI44: =IF(AI$30,ROUND(L44,0),0) -> 0 | AK44: =IF(AK$30,ROUND(D44,0),0) -> 0 | AL44: =IF(AL$30,ROUND(E44,0),0) -> 0 | AM44: =IF(AM$30,ROUND(F44,0),0) -> 0 | AN44: =IF(AN$30,ROUND(G44,0),0) -> 0 | AO44: =IF(AO$30,ROUND(H44,0),0) -> 0 | AP44: =IF(AP$30,ROUND(I44,0),0) -> 0 | AQ44: =IF(AQ$30,ROUND(J44,0),0) -> 0 | AR44: =IF(AR$30,ROUND(K44,0),0) -> 0 | AS44: =IF(AS$30,ROUND(L44,0),0) -> 0
B45: 13 | C45: Date of Payment | M45: =" - - - -" -> - - - - | N45: =" - - - -" -> - - - - | O45: =" - - - -" -> - - - - | Q45: =IF(Q$30,ROUND(D45,0),0) -> 0 | R45: =IF(R$30,ROUND(E45,0),0) -> 0 | S45: =IF(S$30,ROUND(F45,0),0) -> 0 | T45: =IF(T$30,ROUND(G45,0),0) -> 0 | U45: =IF(U$30,ROUND(H45,0),0) -> 0 | V45: =IF(V$30,ROUND(I45,0),0) -> 0 | W45: =IF(W$30,ROUND(J45,0),0) -> 0 | X45: =IF(X$30,ROUND(K45,0),0) -> 0 | Y45: =IF(Y$30,ROUND(L45,0),0) -> 0 | AA45: =IF(AA$30,ROUND(D45,0),0) -> 0 | AB45: =IF(AB$30,ROUND(E45,0),0) -> 0 | AC45: =IF(AC$30,ROUND(F45,0),0) -> 0 | AD45: =IF(AD$30,ROUND(G45,0),0) -> 0 | AE45: =IF(AE$30,ROUND(H45,0),0) -> 0 | AF45: =IF(AF$30,ROUND(I45,0),0) -> 0 | AG45: =IF(AG$30,ROUND(J45,0),0) -> 0 | AH45: =IF(AH$30,ROUND(K45,0),0) -> 0 | AI45: =IF(AI$30,ROUND(L45,0),0) -> 0 | AK45: =IF(AK$30,ROUND(D45,0),0) -> 0 | AL45: =IF(AL$30,ROUND(E45,0),0) -> 0 | AM45: =IF(AM$30,ROUND(F45,0),0) -> 0 | AN45: =IF(AN$30,ROUND(G45,0),0) -> 0 | AO45: =IF(AO$30,ROUND(H45,0),0) -> 0 | AP45: =IF(AP$30,ROUND(I45,0),0) -> 0 | AQ45: =IF(AQ$30,ROUND(J45,0),0) -> 0 | AR45: =IF(AR$30,ROUND(K45,0),0) -> 0 | AS45: =IF(AS$30,ROUND(L45,0),0) -> 0
B46: 14 | C46: State tax withheld | M46: =SUM(Q46:Y46) -> 0 | N46: =SUM(AA46:AI46) -> 0 | O46: =SUM(AK46:AS46) -> 0 | Q46: =IF(Q$30,ROUND(D46,0),0) -> 0 | R46: =IF(R$30,ROUND(E46,0),0) -> 0 | S46: =IF(S$30,ROUND(F46,0),0) -> 0 | T46: =IF(T$30,ROUND(G46,0),0) -> 0 | U46: =IF(U$30,ROUND(H46,0),0) -> 0 | V46: =IF(V$30,ROUND(I46,0),0) -> 0 | W46: =IF(W$30,ROUND(J46,0),0) -> 0 | X46: =IF(X$30,ROUND(K46,0),0) -> 0 | Y46: =IF(Y$30,ROUND(L46,0),0) -> 0 | AA46: =IF(AA$30,ROUND(D46,0),0) -> 0 | AB46: =IF(AB$30,ROUND(E46,0),0) -> 0 | AC46: =IF(AC$30,ROUND(F46,0),0) -> 0 | AD46: =IF(AD$30,ROUND(G46,0),0) -> 0 | AE46: =IF(AE$30,ROUND(H46,0),0) -> 0 | AF46: =IF(AF$30,ROUND(I46,0),0) -> 0 | AG46: =IF(AG$30,ROUND(J46,0),0) -> 0 | AH46: =IF(AH$30,ROUND(K46,0),0) -> 0 | AI46: =IF(AI$30,ROUND(L46,0),0) -> 0 | AK46: =IF(AK$30,ROUND(D46,0),0) -> 0 | AL46: =IF(AL$30,ROUND(E46,0),0) -> 0 | AM46: =IF(AM$30,ROUND(F46,0),0) -> 0 | AN46: =IF(AN$30,ROUND(G46,0),0) -> 0 | AO46: =IF(AO$30,ROUND(H46,0),0) -> 0 | AP46: =IF(AP$30,ROUND(I46,0),0) -> 0 | AQ46: =IF(AQ$30,ROUND(J46,0),0) -> 0 | AR46: =IF(AR$30,ROUND(K46,0),0) -> 0 | AS46: =IF(AS$30,ROUND(L46,0),0) -> 0
B47: 15 | C47: State/payer's state no. | M47: =" - - - -" -> - - - - | N47: =" - - - -" -> - - - - | O47: =" - - - -" -> - - - -
B48: 16 | C48: State distribution | M48: =SUM(Q48:Y48) -> 0 | N48: =SUM(AA48:AI48) -> 0 | O48: =SUM(AK48:AS48) -> 0 | Q48: =IF(Q$30,ROUND(D48,0),0) -> 0 | R48: =IF(R$30,ROUND(E48,0),0) -> 0 | S48: =IF(S$30,ROUND(F48,0),0) -> 0 | T48: =IF(T$30,ROUND(G48,0),0) -> 0 | U48: =IF(U$30,ROUND(H48,0),0) -> 0 | V48: =IF(V$30,ROUND(I48,0),0) -> 0 | W48: =IF(W$30,ROUND(J48,0),0) -> 0 | X48: =IF(X$30,ROUND(K48,0),0) -> 0 | Y48: =IF(Y$30,ROUND(L48,0),0) -> 0 | AA48: =IF(AA$30,ROUND(D48,0),0) -> 0 | AB48: =IF(AB$30,ROUND(E48,0),0) -> 0 | AC48: =IF(AC$30,ROUND(F48,0),0) -> 0 | AD48: =IF(AD$30,ROUND(G48,0),0) -> 0 | AE48: =IF(AE$30,ROUND(H48,0),0) -> 0 | AF48: =IF(AF$30,ROUND(I48,0),0) -> 0 | AG48: =IF(AG$30,ROUND(J48,0),0) -> 0 | AH48: =IF(AH$30,ROUND(K48,0),0) -> 0 | AI48: =IF(AI$30,ROUND(L48,0),0) -> 0 | AK48: =IF(AK$30,ROUND(D48,0),0) -> 0 | AL48: =IF(AL$30,ROUND(E48,0),0) -> 0 | AM48: =IF(AM$30,ROUND(F48,0),0) -> 0 | AN48: =IF(AN$30,ROUND(G48,0),0) -> 0 | AO48: =IF(AO$30,ROUND(H48,0),0) -> 0 | AP48: =IF(AP$30,ROUND(I48,0),0) -> 0 | AQ48: =IF(AQ$30,ROUND(J48,0),0) -> 0 | AR48: =IF(AR$30,ROUND(K48,0),0) -> 0 | AS48: =IF(AS$30,ROUND(L48,0),0) -> 0
B49: 17 | C49: Local tax withheld | M49: =SUM(Q49:Y49) -> 0 | N49: =SUM(AA49:AI49) -> 0 | O49: =SUM(AK49:AS49) -> 0 | Q49: =IF(Q$30,ROUND(D49,0),0) -> 0 | R49: =IF(R$30,ROUND(E49,0),0) -> 0 | S49: =IF(S$30,ROUND(F49,0),0) -> 0 | T49: =IF(T$30,ROUND(G49,0),0) -> 0 | U49: =IF(U$30,ROUND(H49,0),0) -> 0 | V49: =IF(V$30,ROUND(I49,0),0) -> 0 | W49: =IF(W$30,ROUND(J49,0),0) -> 0 | X49: =IF(X$30,ROUND(K49,0),0) -> 0 | Y49: =IF(Y$30,ROUND(L49,0),0) -> 0 | AA49: =IF(AA$30,ROUND(D49,0),0) -> 0 | AB49: =IF(AB$30,ROUND(E49,0),0) -> 0 | AC49: =IF(AC$30,ROUND(F49,0),0) -> 0 | AD49: =IF(AD$30,ROUND(G49,0),0) -> 0 | AE49: =IF(AE$30,ROUND(H49,0),0) -> 0 | AF49: =IF(AF$30,ROUND(I49,0),0) -> 0 | AG49: =IF(AG$30,ROUND(J49,0),0) -> 0 | AH49: =IF(AH$30,ROUND(K49,0),0) -> 0 | AI49: =IF(AI$30,ROUND(L49,0),0) -> 0 | AK49: =IF(AK$30,ROUND(D49,0),0) -> 0 | AL49: =IF(AL$30,ROUND(E49,0),0) -> 0 | AM49: =IF(AM$30,ROUND(F49,0),0) -> 0 | AN49: =IF(AN$30,ROUND(G49,0),0) -> 0 | AO49: =IF(AO$30,ROUND(H49,0),0) -> 0 | AP49: =IF(AP$30,ROUND(I49,0),0) -> 0 | AQ49: =IF(AQ$30,ROUND(J49,0),0) -> 0 | AR49: =IF(AR$30,ROUND(K49,0),0) -> 0 | AS49: =IF(AS$30,ROUND(L49,0),0) -> 0
B50: 18 | C50: Name of locality | D50: =OR(D30="CONV",D30="conv") -> FALSE | E50: =OR(E30="CONV",E30="conv") -> FALSE | F50: =OR(F30="CONV",F30="conv") -> FALSE | G50: =OR(G30="CONV",G30="conv") -> FALSE | H50: =OR(H30="CONV",H30="conv") -> FALSE | I50: =OR(I30="CONV",I30="conv") -> FALSE | J50: =OR(J30="CONV",J30="conv") -> FALSE | K50: =OR(K30="CONV",K30="conv") -> FALSE | L50: =OR(L30="CONV",L30="conv") -> FALSE | M50: =" - - - -" -> - - - - | N50: =" - - - -" -> - - - - | O50: =" - - - -" -> - - - - | Q50: =IF(Q$30,ROUND(D50,0),0) -> 0 | R50: =IF(R$30,ROUND(E50,0),0) -> 0 | S50: =IF(S$30,ROUND(F50,0),0) -> 0 | T50: =IF(T$30,ROUND(G50,0),0) -> 0 | U50: =IF(U$30,ROUND(H50,0),0) -> 0 | V50: =IF(V$30,ROUND(I50,0),0) -> 0 | W50: =IF(W$30,ROUND(J50,0),0) -> 0 | X50: =IF(X$30,ROUND(K50,0),0) -> 0 | Y50: =IF(Y$30,ROUND(L50,0),0) -> 0
B51: 19 | C51: Local distribution | M51: =SUM(Q51:Y51) -> 0 | N51: =SUM(AA51:AI51) -> 0 | O51: =SUM(AK51:AS51) -> 0 | Q51: =IF(Q$30,ROUND(D51,0),0) -> 0 | R51: =IF(R$30,ROUND(E51,0),0) -> 0 | S51: =IF(S$30,ROUND(F51,0),0) -> 0 | T51: =IF(T$30,ROUND(G51,0),0) -> 0 | U51: =IF(U$30,ROUND(H51,0),0) -> 0 | V51: =IF(V$30,ROUND(I51,0),0) -> 0 | W51: =IF(W$30,ROUND(J51,0),0) -> 0 | X51: =IF(X$30,ROUND(K51,0),0) -> 0 | Y51: =IF(Y$30,ROUND(L51,0),0) -> 0 | AA51: =IF(AA$30,ROUND(D51,0),0) -> 0 | AB51: =IF(AB$30,ROUND(E51,0),0) -> 0 | AC51: =IF(AC$30,ROUND(F51,0),0) -> 0 | AD51: =IF(AD$30,ROUND(G51,0),0) -> 0 | AE51: =IF(AE$30,ROUND(H51,0),0) -> 0 | AF51: =IF(AF$30,ROUND(I51,0),0) -> 0 | AG51: =IF(AG$30,ROUND(J51,0),0) -> 0 | AH51: =IF(AH$30,ROUND(K51,0),0) -> 0 | AI51: =IF(AI$30,ROUND(L51,0),0) -> 0 | AK51: =IF(AK$30,ROUND(D51,0),0) -> 0 | AL51: =IF(AL$30,ROUND(E51,0),0) -> 0 | AM51: =IF(AM$30,ROUND(F51,0),0) -> 0 | AN51: =IF(AN$30,ROUND(G51,0),0) -> 0 | AO51: =IF(AO$30,ROUND(H51,0),0) -> 0 | AP51: =IF(AP$30,ROUND(I51,0),0) -> 0 | AQ51: =IF(AQ$30,ROUND(J51,0),0) -> 0 | AR51: =IF(AR$30,ROUND(K51,0),0) -> 0 | AS51: =IF(AS$30,ROUND(L51,0),0) -> 0
B52: Only bolded amounts are used in this spreadsheet. | D52: =OR(D50:L50) -> FALSE
D53: =IF(OR(LEFT(D38,1)="D",LEFT(D38,1)="d"),D32,"") | E53: =IF(OR(LEFT(E38,1)="D",LEFT(E38,1)="d"),E32,"") | F53: =IF(OR(LEFT(F38,1)="D",LEFT(F38,1)="d"),F32,"") | G53: =IF(OR(LEFT(G38,1)="D",LEFT(G38,1)="d"),G32,"") | H53: =IF(OR(LEFT(H38,1)="D",LEFT(H38,1)="d"),H32,"") | I53: =IF(OR(LEFT(I38,1)="D",LEFT(I38,1)="d"),I32,"") | J53: =IF(OR(LEFT(J38,1)="D",LEFT(J38,1)="d"),J32,"") | K53: =IF(OR(LEFT(K38,1)="D",LEFT(K38,1)="d"),K32,"") | L53: =IF(OR(LEFT(L38,1)="D",LEFT(L38,1)="d"),L32,"") | N53: =SUM(D53:L53) -> 0 | O53: =SUM(E53:M53) -> 0
D54: =IF(OR(LEFT(D38,1)="D",LEFT(D38,1)="d"),SUM(D46,D49),"") | E54: =IF(OR(LEFT(E38,1)="D",LEFT(E38,1)="d"),SUM(E46,E49),"") | F54: =IF(OR(LEFT(F38,1)="D",LEFT(F38,1)="d"),SUM(F46,F49),"") | G54: =IF(OR(LEFT(G38,1)="D",LEFT(G38,1)="d"),SUM(G46,G49),"") | H54: =IF(OR(LEFT(H38,1)="D",LEFT(H38,1)="d"),SUM(H46,H49),"") | I54: =IF(OR(LEFT(I38,1)="D",LEFT(I38,1)="d"),SUM(I46,I49),"") | J54: =IF(OR(LEFT(J38,1)="D",LEFT(J38,1)="d"),SUM(J46,J49),"") | K54: =IF(OR(LEFT(K38,1)="D",LEFT(K38,1)="d"),SUM(K46,K49),"") | L54: =IF(OR(LEFT(L38,1)="D",LEFT(L38,1)="d"),SUM(L46,L49),"") | N54: =SUM(D54:L54) -> 0 | O54: =SUM(E54:M54) -> 0
B55: Information from Form 1099-R, Distributions From Pensions, Annuities, Retirement or Profit-Sharing Plans, IRAs, Insurance Contracts, etc.
C56: Total Distributions | D56: Total IRAs | E56: Total Pension / Annuities | F56: Qualified Conversion to ROTH IRA
D57: IRA | E57: P/A | F57: CONV | G57: Used at: | J57: If your IRA is fully taxable, this spreadsheet will automatically enter
B58: 1 | C58: Gross distribution | D58: =SUM(M4,M31) -> 0 | E58: =SUM(N4,N31) -> 0 | F58: =SUM(O4,O31) -> 0 | G58: Form 1040, Line 4a, 5a | I58: =IF(E58=0,0,ROUND(E58,0)) -> 0 | J58: the total IRA distributions (from Form(s) 1099-R, box 2a) on line 4b;
B59: 2a | C59: Taxable amount | D59: =SUM(IRA_Taxable_You,IRA_Taxable_Spouse) -> 0 | E59: =SUM(PA_Taxable_You,PA_Taxable_Spouse) -> 0 | F59: =" - - - -" -> - - - - | G59: Form 1040, Line 4b, 5b | J59: do not make an entry on line 4a.
B60: 2b | C60: Taxable amount not determined / total distr. | D60: =" - - - -" -> - - - - | E60: =" - - - -" -> - - - - | F60: =" - - - -" -> - - - - | J60: If your pension or annuity is fully taxable, this spreadsheet will automatically
B61: 3 | C61: Capital gain (not included in box 2a) | D61: =SUM(M7,M34) -> 0 | E61: =SUM(N7,N34) -> 0 | F61: =SUM(O7,O34) -> 0 | J61: enter the total pension or annuity distributions (from Form(s) 1099-R, box 2a)
B62: 4 | C62: Federal income tax withheld | D62: =SUM(M8,M35) -> 0 | E62: =SUM(N8,N35) -> 0 | F62: =SUM(O8,O35) -> 0 | G62: 1040, line 25b | J62: on line 5b; do not make an entry on line 5a.
B63: 5 | C63: Employee contributions / Insurance premiums / Designated Roth IRA contributions | D63: =SUM(M9,M36) -> 0 | E63: =SUM(N9,N36) -> 0 | F63: =SUM(O9,O36) -> 0
B64: 6 | C64: Net unrealized appreciation in employer's securities | D64: =SUM(M10,M37) -> 0 | E64: =SUM(N10,N37) -> 0 | F64: =SUM(O10,O37) -> 0 | J64: If your Form 1099-R doesn't show the taxable amount, you must use
B65: 7 | C65: Distribution code(s) (Portion of line 2a w/Code D) | D65: =" - - - -" -> - - - - | E65: =SUM(N26,N53) -> 0 | F65: =" - - - -" -> - - - - | G65: Form 8960, Line 3 (for Dist. Code 'D' only) | J65: the General Rule explained in Pub. 939 to figure the taxable part to enter on
B66: 8 | C66: Other | D66: =" - - - -" -> - - - - | E66: =" - - - -" -> - - - - | F66: =" - - - -" -> - - - - | J66: line 4b. But if your annuity starting date was after July 1, 1986,
B67: 9a | C67: Your percentage of total distribution | D67: =SUM(M13,M40) -> 0 | E67: =SUM(N13,N40) -> 0 | F67: =SUM(O13,O40) -> 0 | J67: see Simplified Method, sheet "Lines 5ab (Simplified Meth WS)", to find out if you
B68: 9b | C68: Total employee contributions | D68: =SUM(M14,M41) -> 0 | E68: =SUM(N14,N41) -> 0 | F68: =SUM(O14,O41) -> 0 | J68: must use that method to figure the taxable part. You can ask the IRS to figure the
B69: 10 | C69: Amount allocable to IRR within 5 years | D69: =SUM(M15,M42) -> 0 | E69: =SUM(N15,N42) -> 0 | F69: =SUM(O15,O42) -> 0 | J69: taxable part for you for a $1,000 fee. For details, see Pub. 939.
B70: 11 | C70: 1st year of desig. Roth contrib. | D70: =SUM(M16,M43) -> 0 | E70: =SUM(N16,N43) -> 0 | F70: =SUM(O16,O43) -> 0
B71: 12 | C71: FATCA filing requirement | D71: =" - - - -" -> - - - - | E71: =" - - - -" -> - - - - | F71: =" - - - -" -> - - - -
B72: 13 | C72: Date of Payment | D72: =" - - - -" -> - - - - | E72: =" - - - -" -> - - - - | F72: =" - - - -" -> - - - -
B73: 14 | C73: State tax withheld | D73: =SUM(M19,M46) -> 0 | E73: =SUM(N19,N46) -> 0 | F73: =SUM(O19,O46) -> 0 | G73: Sch. A, Line 5a | J73: The sheet labeled "Line 5ab (Simplified Meth WS)" is a stand-alone worksheet that
B74: 15 | C74: State/payer's state no. | D74: =" - - - -" -> - - - - | E74: =" - - - -" -> - - - - | F74: =" - - - -" -> - - - - | J74: is used to calculate the taxable amount of a pension or annuity that is not fully taxable.
B75: 16 | C75: State distribution | D75: =SUM(M21,M48) -> 0 | E75: =SUM(N21,N48) -> 0 | F75: =SUM(O21,O48) -> 0
B76: 17 | C76: Local tax withheld | D76: =SUM(M22,M49) -> 0 | E76: =SUM(N22,N49) -> 0 | F76: =SUM(O22,O49) -> 0 | G76: Sch. A, Line 5a
B77: 18 | C77: Portion of state and local taxes w/Code D | D77: =" - - - -" -> - - - - | E77: =ROUND(SUM(N27,N54),0) -> 0 | F77: =ROUND(SUM(O27,O54),0) -> 0
B78: 19 | C78: Local distribution | D78: =SUM(M24,M51) -> 0 | E78: =SUM(N24,N51) -> 0 | F78: =SUM(O24,O51) -> 0
B79: Only bolded amounts are used in this spreadsheet.
C86: Table of Contents

Sheet SSA-1099
B1: Information from Form SSA-1099, Social Security Benefit Statement | N1: Notes
B2: 1 | C2: =IF(Name_1st_Yours="","Enter your name on sheet labeled '1040'",NameYours) -> Enter your name on sheet labeled '1040'
B3: 3 | C3: ="Benefits Paid in "&TaxYear -> Benefits Paid in 2021
B4: 4 | C4: ="Benefits Repaid in "&TaxYear -> Benefits Repaid in 2021
B5: 5 | C5: ="Net Benefits for "&TaxYear&" (Box 3 minus Box 4)" -> Net Benefits for 2021 (Box 3 minus Box 4) | D5: =SUM(D3,-D4) -> 0 | E5: Used on Notice 703, Line A (below)
B6: 6 | C6: Voluntary Federal income Tax Withheld | E6: Used in 1040, line 25b | G6: =ROUND(D6,0) -> 0
B7: 1 | C7: =IF(Name_1st_Sp="","Enter your spouse's name on the sheet labeled '1040'",NameSpouse) -> Enter your spouse's name on the sheet labeled '1040'
B8: 3 | C8: ="Benefits Paid in "&TaxYear -> Benefits Paid in 2021
B9: 4 | C9: ="Benefits Repaid in "&TaxYear -> Benefits Repaid in 2021
B10: 5 | C10: ="Net Benefits for "&TaxYear&" (Box 3 minus Box 4)" -> Net Benefits for 2021 (Box 3 minus Box 4) | D10: =SUM(D8,-D9) -> 0 | E10: Used on Notice 703, Line A (below)
B11: 6 | C11: Voluntary Federal income Tax Withheld | E11: Used in 1040, line 25b | G11: =ROUND(D11,0) -> 0
C13: Notice 703 | I13: Department of the Treasury
C14: (Rev. October 2020) | I14: Internal Revenue Service
C15: Read This To See If Your Social Security Benefits May Be Taxable
C17: ="If your social security and/or SSI (supplemental security income) benefits were your only source of income for "&TaxYear&", you probably will not have to file a federal income tax return. See IRS Pub. 501, Exemptions, Standard Deduction, and Filing Information, or your tax return instructions to find out if you have to file a return." -> If your social security and/or SSI (supplemental security income) benefits were your only source of income for 2021, you probably will not have to file a federal income tax return. See IRS Pub. 501, Exemptions, Standard Deduction, and Filing Information, or your tax return instructions to find out if you have to file a return. | D17: ="We developed this worksheet for you to see if your benefits may be taxable for "&TaxYear&". Fill in lines A through E."&CHAR(10)&CHAR(10)&"Do not use the worksheet below if any of the following apply to you; instead, go directly to IRS Pub. 915, Social Security and Equivalent Railroad Retirement Benefits."&CHAR(10)&CHAR(10)&"o You received Form RRB-1099, Form SSA-1042S, or Form RRB-1042S." -> We developed this worksheet for you to see if your benefits may be taxable for 2021. Fill in lines A through E. Do not use the worksheet below if any of the following apply to you; instead, go directly to IRS Pub. 915, Social Security and Equivalent Railroad Retirement Benefits. o You received Form RRB-1099, Form SSA-1042S, or Form RRB-1042S. | G17: o You exclude income from sources outside the United States or foreign housing, income earned by bona fide residents of American Samoa or Puerto Rico, interest income from series EE or I U.S. savings bonds issued after 1989, or employer-provided adoption benefits. | L17: Manual Override ê
C18: Note. If you plan to file a joint income tax return, include your spouse's amounts, if any, on lines A, C, and D
B19: A | C19: Enter the total amount from box 5 of all your Forms SSA-1099. Include the
C20: ="full amount of any lump-sum benefit payments received in "&TaxYear&", for "&TaxYear&" and" -> full amount of any lump-sum benefit payments received in 2021, for 2021 and | M20: Line A is used in
C21: earlier years. . . . . . . . . . . . . . . . . . . . . . . . . . . . . . . . . . . . . . . . . . . . . . | D21: . . . . . . . . . . . . . . . . . . . . . . . . . . . . . . . . . . . . . . . . . . . . . | E21: . . . . . . . . . . . . . . . . . . . . . . . . . . . . . . . . . . . . . . . . . . . . . | F21: A | G21: =IF(L21<>"",ROUND(L21,0),ROUND(SUM(D5,D10),0)) -> 0 | I21: 0.5 | M21: Sheet "Line 6ab (SS Bene)", line 1.
B22: B | C22: ="Multiply line A by "&TEXT(I21,"0%")&" ("&TEXT(I21,"0.00")&")" -> Multiply line A by 50% (0.50) | G22: . . . . . . . . . . . . . . . . . . . . . . . . . . . . . . . . . . . . . . . . . . . . . . . . . . . | H22: B | I22: =ROUND(G21*I21,0) -> 0
B23: C | C23: Enter your total income that is taxable (excluding Line A), such as pensions, wages, interest, ordinary dividends, and capital gain distributions. Do not reduce your income by any items such as student loan interest deduction, the standard deduction (or itemized deductions), or
C24: exemptions . . . . . . . . . . . . . . . . . . . . . . . . . . . . . . . . . . . . . . . . . | H24: C | I24: =IF(L24<>"",ROUND(L24,0),M24) -> 0 | M24: =SUM(Wages,TaxableInterest,OrdinaryDividends,IRA_Taxable,PA_Taxable,CapitalGains,Additional_Income) -> 0
B25: D | C25: Enter any tax-exempt interest such as interest on municipal bonds | G25: . . . . . . . . . . . . . . . . . . . . . | H25: D | I25: =IF(L25<>"",ROUND(L25,0),TaxExemptInt) -> 0
B26: E | C26: Add lines B, C, and D, and enter the total here. Then, read the information below | G26: . . . . . . . . . . . . . . | H26: E | I26: =SUM(I22,I24,I25) -> 0 | M26: 32000
M27: 25000
C28: Part of your social security benefits may be taxable. | I28: =AND(M28<>0,I26>M28) -> FALSE | M28: =IF(OR(File_Single<>"",File_Head<>""),M27,IF(File_Marr_Joint<>"",M26,IF(AND(File_Marr_Sep<>"",LivedApart),M27,0))) -> 0
C29: ="Part of your social security benefits may be taxable if, for "&TaxYear&", item 1, 2, or 3 below applies to you:" -> Part of your social security benefits may be taxable if, for 2021, item 1, 2, or 3 below applies to you: | D29: If none of your benefits are taxable, but you must otherwise file a tax return, do the following | G29: Railroad Retirement Benefits, for rules on a lump-sum election you can make that may reduce the amount of your taxable benefits.
C30: ="1. You were single, a head of household, or a qualifying widow(er) and line E above is more than "&TEXT(M27,"$0,000")&"." -> 1. You were single, a head of household, or a qualifying widow(er) and line E above is more than $25,000. | D30: o Enter the total amount from line A above on Form 1040, line 6a, and enter -0- on Form 1040, line 6b. | G30: Get More Information From the IRS
C31: =CHAR(10)&"2. You were married, would file jointly, and line E above is more than "&TEXT(M26,"$0,000")&"."&CHAR(10)&CHAR(10)&"3. You were married, would file separately, and line E above is more than zero (more than "&TEXT(M27,"$0,000")&" if you lived apart from your spouse for all of "&TaxYear&")." -> 2. You were married, would file jointly, and line E above is more than $32,000. 3. You were married, would file separately, and line E above is more than zero (more than $25,000 if you lived apart from your spouse for all of 2021). | D31: =CHAR(10)&"o If you were married, file separately, and lived apart from your spouse for all of "&TaxYear&", enter “D” to the right of the word “benefits” on Form 1040, line 6a." -> o If you were married, file separately, and lived apart from your spouse for all of 2021, enter “D” to the right of the word “benefits” on Form 1040, line 6a. | G31: ="If you still have questions about whether your social security benefits are taxable, see IRS "&CHAR(10)&"Pub. 915 or your "&TaxYear&" federal income tax return instructions, or visit IRS.gov and enter 'social security income' in the search box. Go to www.irs.gov/Forms to view, download, or print all of the forms and publications you may need." -> If you still have questions about whether your social security benefits are taxable, see IRS Pub. 915 or your 2021 federal income tax return instructions, or visit IRS.gov and enter 'social security income' in the search box. Go to www.irs.gov/Forms to view, download, or print all of the forms and publications you may need.
C32: ="If your figures show that part of"&CHAR(10)&"your benefits may be taxable, see"&CHAR(10)&"IRS Pub. 915, and Social Security"&CHAR(10)&"Benefits in your "&TaxYear&" federal"&CHAR(10)&"income tax return instructions." -> If your figures show that part of your benefits may be taxable, see IRS Pub. 915, and Social Security Benefits in your 2021 federal income tax return instructions. | D32: ="Note. If your figures show that part of your benefits may be taxable and you received benefits in "&TaxYear&" that were for a prior year, see IRS Pub. 915, Social Security and Equivalent" -> Note. If your figures show that part of your benefits may be taxable and you received benefits in 2021 that were for a prior year, see IRS Pub. 915, Social Security and Equivalent
D33: Do not return this notice to the SSA or the IRS. Keep it with your records.
C34: IRS.gov | I34: Catalog No. 61879N
C39: Table of Contents

Sheet 1040
C1: =RevDateTime -> 46003.399 | G1: NOTE: Check every calculation carefully!!! | AJ1: =IF(File_Single<>"",1,0) -> 0 | BI1: Notes
C2: =RevDateTime -> 46003.399 | G2: www.excel1040.com | AH2: © Glenn Reeves, 2022 | AJ2: =IF(File_Marr_Joint<>"",1,0) -> 0 | AL2: Check here to remove blue & green colors from all sheets. | AP2: =(AK2<>"") -> FALSE | AX2: =DATEVALUE("1-JAN-"&TaxYear) -> 44197 | AY2: =IF(BA2>365,TRUE,FALSE) -> FALSE | AZ2: =DATEVALUE("1-JAN-"&TaxYear+1)-1 -> 44561 | BA2: =EndOfTaxYear+1-BeginningOfTaxYear -> 365 | BC2: Alaska | BD2: Hawaii | BE2: Maine | BF2: Mass. | BG2: D.C. | BI2: Date
B3: Form | C3: 1040 | F3: =IF(FilingStatusError,"Please check only ONE filing status box.","Department of the Treasury––Internal Revenue Service (99)") -> Department of the Treasury––Internal Revenue Service (99) | R3: 2021 | AJ3: =IF(File_Marr_Sep<>"",1,0) -> 0 | AL3: Check here to hide Social Security numbers from forms. | AP3: =(AK3<>"") -> FALSE | BC3: =IF(ISERROR(FIND("ALASKA",State)),FALSE,TRUE) -> FALSE | BD3: =IF(ISERROR(FIND("HAWAII",State)),FALSE,TRUE) -> FALSE | BE3: =IF(ISERROR(FIND("MAINE",State)),FALSE,TRUE) -> FALSE | BF3: =IF(ISERROR(FIND("MASSACHUSETTS",State)),FALSE,TRUE) -> FALSE | BG3: =IF(ISERROR(FIND("DISTRICT",State)),FALSE,TRUE) -> FALSE
F4: =IF(NumFileStatusBoxes=0,"Check one FILING STATUS box.","U.S. Individual Income Tax Return") -> Check one FILING STATUS box. | V4: OMB No. 1545-0074 | Z4: =IF(FilingStatusError,"Check only ONE filing status block","IRS Use Only—Do not write or staple in this space.") -> IRS Use Only—Do not write or staple in this space. | AJ4: =IF(File_Head<>"",1,0) -> 0 | AK4: Filing Status: | AM4: =IF(NumFileStatusBoxes=0,"Filing status not indicated.",IF(FilingStatusError,"Check only ONE filing status box.",IF(File_Single<>"","Single",IF(File_Marr_Joint<>"","Married - Filing Jointly",IF(File_Marr_Sep<>"","Married - Filing Separately",IF(File_Head<>"","Head of Household",IF(File_Qual_Widow<>"","Qualifying Widow(er)",""))))))) -> Filing status not indicated. | BC4: =IF(ISERROR(FIND("AK",State)),FALSE,TRUE) -> FALSE | BD4: =IF(ISERROR(FIND("HI",State)),FALSE,TRUE) -> FALSE | BE4: =IF(ISERROR(FIND("ME",State)),FALSE,TRUE) -> FALSE | BF4: =IF(ISERROR(FIND("MA",State)),FALSE,TRUE) -> FALSE | BG4: =IF(ISERROR(FIND("DC",State)),FALSE,TRUE) -> FALSE
C6: Filing Status | F6: Single | J6: Married filing jointly | P6: Married filing separately (MFS) | W6: Head of Household (HOH) | AC6: Qualifying Widow(er) (QW) | AJ6: =IF(File_Qual_Widow<>"",1,0) -> 0 | AL6: =IF(File_Marr_Sep<>"","Yes. Did you live apart from your spouse for all of "&TEXT(TaxYear,"0")&"?","") | AP6: =AND(File_Marr_Sep<>"",OR(AK6<>"",AK7<>""),NOT(AND(AK6<>"",AK7<>""))) -> FALSE | BC6: =IF(ISERROR(FIND("Alaska",State)),FALSE,TRUE) -> FALSE | BD6: =IF(ISERROR(FIND("Hawaii",State)),FALSE,TRUE) -> FALSE | BE6: =IF(ISERROR(FIND("Maine",State)),FALSE,TRUE) -> FALSE | BF6: =IF(ISERROR(FIND("Massachusetts",State)),FALSE,TRUE) -> FALSE | BG6: =IF(ISERROR(FIND("D.C.",State)),FALSE,TRUE) -> FALSE
C7: Check only | E7: If you checked the MFS box, enter the name of spouse. | AH7: If you checked the HOH or QW box, enter the child’s name if the qualifying | AJ7: =SUM(AJ1:AJ6) -> 0 | AL7: =IF(OR(AND(AK6<>"",AK7<>""),AND(File_Marr_Sep<>"",AK6="",AK7="")),"No. Please check ONE box.",IF(File_Marr_Sep<>"","No.","")) | AP7: =AND(File_Marr_Sep,AK6<>"",AK7="") -> FALSE | AQ7: =AND(DependentYOU="",OR(File_Single<>"",File_Marr_Joint<>"",File_Marr_Sep<>"",File_Head<>"",File_Qual_Widow<>"")) -> FALSE | BC7: =OR(BC3,BC4,BC6) -> FALSE | BD7: =OR(BD3,BD4,BD6) -> FALSE | BE7: =OR(BE3,BE4,BE6) -> FALSE | BF7: =OR(BF3,BF4,BF6) -> FALSE | BG7: =OR(BG3,BG4,BG6) -> FALSE
C8: one box. | E8: person is a child but not your dependent. | AJ8: =NumFileStatusBoxes>1 -> FALSE | AL8: =IF(File_Marr_Sep<>"","Check here if you spouse had no income and is NOT filing a tax return.","") | AQ8: =AND(DependentSPOUSE="",File_Marr_Joint<>"") -> FALSE | BF8: =OR(BE7,BF7,BG7) -> FALSE
C9: Your first name and middle initial | M9: =IF(AND(File_Marr_Sep<>"",OR(NOT(LivedApartAnswered),K8="")),"Please answer questions at right regarding your spouse."," Last name") -> Last name | Z9: Your social security number | AJ9: =(NumFileStatusBoxes>1) -> FALSE | AL9: =IF(AND(OR(File_Single<>"",File_Head<>""),OR(sp_over_64<>"",sp_blind<>"",DependentSPOUSE<>"",Dual_Status_Alien<>"")),TRUE,FALSE) -> FALSE | AM9: =IF(AND(Name_1st_Yours<>"",Name_1st_Sp<>""),Name_1st_Yours&" "&Name_Last_Yours&" & "&Name_1st_Sp&" "&Name_Last_Sp,IF(Name_Last_Yours<>"",Name_1st_Yours&" "&Name_Last_Yours,"")) | BF9: For 'Patriots' Day or
Z10: 1010001 | AJ10: =IF(AND(OR(File_Single<>"",File_Head<>""),OR(sp_over_64<>"",sp_blind<>"")),TRUE,FALSE) -> FALSE | AL10: =IF(OR(File_Marr_Joint<>"",File_Marr_Sep<>"",File_Qual_Widow<>""),TRUE,FALSE) -> FALSE | AM10: =Name_1st_Yours&" "&Name_Last_Yours | AN10: =Name_1st_Sp&" "&Name_Last_Sp | BF10: Emancipation Day (D.C.)
C11: If joint return, spouse's first name and middle initial | M11: Last name | Z11: =IF(AND(File_Marr_Sep<>"",SS_Spouse=""),"Enter spouse's Soc. Sec. number","Spouse's social security number") -> Spouse's social security number | AU11: =IF(you_over_64<>"",1,0) -> 0
Z12: 1010002 | AU12: =IF(you_blind<>"",1,0) -> 0 | AX12: =IF(OR(YourBirthMonth="",YourBirthDay="",YourBirthYear=""),FALSE,TRUE) -> FALSE | AY12: =IF(OR(YourBirthMonth="",YourBirthDay="",YourBirthYear=""),"Enter your birthdate",IF(BA102,"Your birthdate appears to be in error.",IF(AX13,"For IRS purposes, you were "&YourAge&" years old on December 31, "&TaxYear&".","You were "&YourAge&" years old on December 31, "&TaxYear&"."))) -> Enter your birthdate
C13: Home address (number and street). If you have a P.O. box, see instructions. | W13: Apt. no. | Z13: Presidential Election Campaign | AL13: =IF(AND($AL$10,AX12,AX14),"Birthdates",IF($AL$10,"Enter your birthdate and your spouse's birthdate.",IF(AX12,"Birthdate","Enter your birthdate."))) -> Enter your birthdate. | AU13: =IF(AND(OR(File_Marr_Joint<>"",MFS_Spouse_NotFiling<>""),sp_over_64<>""),1,0) -> 0 | AX13: =AND(YourBirthMonth=1,YourBirthDay=1) -> FALSE
Z14: Check here if you, or your spouse if filing jointly, want $3 to go to this fund. Checking a box below will not change your tax or refund. | AM14: Month (e.g. '11') | AN14: Day (e.g. '9') | AO14: Year (e.g. '1997') | AU14: =IF(sp_blind<>"",1,0) -> 0 | AX14: =AND(OR(File_Marr_Sep<>"",File_Marr_Joint<>""),SpouseBirthMonth<>"",SpouseBirthDay<>"",SpouseBirthYear<>"") -> FALSE | AY14: =IF(AND(File_Marr_Sep="",File_Marr_Joint=""),"",IF(AND(OR(File_Marr_Sep<>"",File_Marr_Joint<>""),OR(SpouseBirthMonth="",SpouseBirthDay="",SpouseBirthYear="")),"Enter spouse's birthdate.",IF(BA122,"Your birthdate appears to be in error.",IF(AX15,"For IRS purposes, you were "&SpouseAge&" years old on December 31, "&TaxYear&".","Your spouse was "&SpouseAge&" years old on December 31, "&TaxYear&"."))))
C15: City, town, or post office. If you have a foreign address, also complete spaces below. | R15: State | V15: ZIP Code | AL15: You | AU15: =IF(OR(AND(OR(File_Single<>"",File_Head<>""),OR(sp_over_64<>"",sp_blind<>"")),NumFileStatusBoxes=0),0,SUM(AU11:AU14)) -> 0 | AX15: =AND(SpouseBirthMonth=1,SpouseBirthDay=1) -> FALSE
AM16: =AY12 -> Enter your birthdate | AX16: =AND($AL$25,SpouseDeathYear<>"",SpouseDeathYear=TaxYear) -> FALSE | AY16: Spouse cannot be claimed.
C17: Foreign country name | N17: Foreign province/state/county | V17: Foreign postal code | AL17: =IF($AL$10,"Spouse ","") | AX17: =AND($AL$25,OR(SpouseDeathMonth<SpouseBirthMonth,AND(SpouseDeathMonth=SpouseBirthMonth,SpouseDeathDay<SpouseBirthDay))) -> FALSE
AD18: You | AG18: Spouse | AK18: =IF(File_Marr_Joint<>"","Check "&CHAR(10)&"if deceased","") | AM18: =AY14
B21: ="At any time during "&TaxYear&", did you receive, sell, send, exchange, or otherwise acquire any financial interest in any virtual currency?" -> At any time during 2021, did you receive, sell, send, exchange, or otherwise acquire any financial interest in any virtual currency? | AD21: Yes | AG21: No
B24: Standard Deduction | E24: Someone can claim: | J24: You as a dependent | P24: Your spouse as a dependent | AL24: =IF(AL25,"Date of death","") | AP24: =AND(SpouseDeceased<>"",SpouseDeathYear<>"",SpouseDeathYear<>TaxYear) -> FALSE
G25: Spouse itemizes on a separate return or you were a dual-status alien | AL25: =AND($AK$17<>"",$AL$10) -> FALSE | AM25: =IF(AND(SpouseDeceased<>"",OR(SpouseDeathMonth="",SpouseDeathDay="",SpouseDeathYear="")),"Enter date of spouse's death.",IF(AP24,"Error: Death of spouse was not during "&TaxYear&".",IF(BadDeathDate,"The date of death appears to be in error.","")))
B28: Age / Blindness | E28: You: | G28: =IF(BadBirthdate_Yours,"",IF(YourBirthDate<$AY$111,"X","")) | H28: =IF(AND(Name_1st_Yours<>"",NOT($AX$12))," Enter your birthdate in box at right."," Were born before January 2, "&TaxYear-64) -> Were born before January 2, 1957 | P28: Are blind | U28: Spouse: | V28: =IF(OR(File_Single<>"",File_Head<>"",AND(File_Marr_Sep<>"",MFS_Spouse_NotFiling=""),BadBirthdate_Spouse,AP24),"",IF(BG119,"X",IF(AND(SpouseDeceased<>"",NOT(BG119)),"",IF(AND(OR(File_Marr_Joint<>"",MFS_Spouse_NotFiling<>""),SpouseBirthDate<$AY$111),"X","")))) | W28: =IF(AND(File_Marr_Joint<>"",NOT($AX$14))," Enter spouse birthdate (in box at right)."," Was born before January 2, "&TaxYear-64) -> Was born before January 2, 1957 | AF28: Is blind
B30: Dependents | M30: (2) Social security number | S30: (3) Relationship to you
E31: (see instructions) : | Z31: (4) | AB31: if qualified for (see instructions): | AL31: Enter information on qualifying children and dependents on the 'Dependents' tab. | AQ31: =IF(Z33<>"",1,0) -> 0 | AR31: =(AND(E33<>"",Z33="",AF33="")) -> TRUE | AT31: =IF(Z33<>"",1,0) -> 0
B32: If more than four dependents, see instructions and check | E32: (1) First name | I32: Last name | Y32: Child tax credit | AC32: Credit for other dependents | AJ32: Enter information for dependents on the 'Dependents' sheet. | AQ32: =IF(Z34<>"",1,0) -> 0 | AR32: =(AND(E34<>"",Z34="",AF34="")) -> TRUE | AS32: =OR(AR31,AR32,AR33,AR34) -> TRUE | AT32: =IF(Z34<>"",1,0) -> 0
E33: =Dependents!E7&" "&Dependents!I7 | M33: =IF(OR(Dependents!M7="",Dependents!M7=0),"",Dependents!M7) | S33: =IF(Dependents!S7="","",Dependents!S7) | Z33: =IF(Dependents!Z7="","",Dependents!Z7) | AF33: =IF(Dependents!AF7="","",Dependents!AF7) | AK33: =IF(AF33<>"",1,0) -> 0 | AL33: =Dependents!AQ36 -> 0 | AM33: Number of qualifying children. | AQ33: =IF(Z35<>"",1,0) -> 0 | AR33: =(AND(E35<>"",Z35="",AF35="")) -> TRUE | AS33: =IF(DependentYOU="",1,0) -> 1 | AT33: =IF(Z35<>"",1,0) -> 0
E34: =Dependents!E8&" "&Dependents!I8 | M34: =IF(OR(Dependents!M8="",Dependents!M8=0),"",Dependents!M8) | S34: =IF(Dependents!S8="","",Dependents!S8) | Z34: =IF(Dependents!Z8="","",Dependents!Z8) | AF34: =IF(Dependents!AF8="","",Dependents!AF8) | AK34: =IF(AF34<>"",1,0) -> 0 | AL34: =Dependents!AQ37 -> 0 | AM34: Number of other dependents. | AQ34: =IF(Z36<>"",1,0) -> 0 | AR34: =(AND(E36<>"",Z36="",AF36="")) -> TRUE | AS34: =IF(AND(File_Marr_Joint<>"",DependentSPOUSE=""),1,0) -> 0 | AT34: =IF(Z36<>"",1,0) -> 0
E35: =Dependents!E9&" "&Dependents!I9 | M35: =IF(OR(Dependents!M9="",Dependents!M9=0),"",Dependents!M9) | S35: =IF(Dependents!S9="","",Dependents!S9) | Z35: =IF(Dependents!Z9="","",Dependents!Z9) | AF35: =IF(Dependents!AF9="","",Dependents!AF9) | AK35: =IF(AF35<>"",1,0) -> 0 | AN35: =OR(AM37<>"",AM38<>"",AN38<>"",AM39<>"",AN39<>"",AM40<>"",AN40<>"",AM41<>"",AN41<>"",AM42<>"",AN42<>"") -> FALSE | AO35: =IF(OR(NumFileStatusBoxes=0,NumFileStatusBoxes>1),0,SUM(AS33,AS34,AL33,AL34,SUM(AI33:AI36))) -> 0 | AP35: Tax Family Size (for Form 8962, Premium Tax Credit)
B36: here | D36: =IF(Dependents!D10="","",Dependents!D10) | E36: =Dependents!E10&" "&Dependents!I10 | M36: =IF(OR(Dependents!M10="",Dependents!M10=0),"",Dependents!M10) | S36: =IF(Dependents!S10="","",Dependents!S10) | Z36: =IF(Dependents!Z10="","",Dependents!Z10) | AF36: =IF(Dependents!AF10="","",Dependents!AF10) | AK36: =IF(AF36<>"",1,0) -> 0 | AM36: Manual Override | AN36: Manual Override | AO36: Determine the number of individuals in your tax family using your tax return. Your tax family generally includes you, your spouse if you are filing a joint return, and your dependents. If you checked the “Someone can claim you as a dependent” box, or if you’re filing jointly and you checked the “Someone can claim your spouse as a dependent” box on your tax return, you or your spouse are not included in the tax family size calculation for purposes of Form 8962, Premium Tax Credit, line 1.
E37: 1 | G37: Wages, salaries, tips, etc. Attach Form(s) W-2 | S37: =AJ37&" "&AJ38&" "&AJ39 | AB37: =E37 -> 1 | AC37: =IF(AM37<>"",ROUND(AM37,0),ROUND(SUM(W2_Wages,Dependent_Care),0)) -> 0 | AJ37: =IF(InmateIncome>0,"PRI "&TEXT(InmateIncome,"$0"),"") | AK37: 4a | AL37: =AND(CONV2ROTH=0,ROUND(IRA_Gross,0)=IRA_Taxable) -> TRUE
C38: Attach Sch. B if required. | E38: 2 | F38: a | G38: Tax-exempt interest | K38: . . . . | L38: =E38&"a" -> 2a | N38: =IF(AM38<>"",ROUND(AM38,0),SUM(TaxExemptInterest,Exempt_Interest_DIV)) -> 0 | S38: b | T38: Taxable interest | AA38: . . . . . . . . . | AB38: =E38&"b" -> 2b | AC38: =IF(AN38<>"",ROUND(AN38,0),Interest_Inc) -> 0 | AJ38: =IF(DeferredIncomeNQ>0,"DFC "&TEXT(DeferredIncomeNQ,"$0"),"") | AK38: 5a | AL38: =ROUND(PA_Gross,0)=PA_Taxable -> TRUE
E39: 3 | F39: a | G39: Qualified dividends | K39: . . . . | L39: =E39&"a" -> 3a | N39: =IF(AM39<>"",ROUND(AM39,0),ROUND(QualDiv_1099DIV,0)) -> 0 | S39: b | T39: Ordinary dividends | AA39: . . . . . . . . | AB39: =E39&"b" -> 3b | AC39: =IF(AN39<>"",ROUND(AN39,0),Dividend_Inc) -> 0 | AJ39: =IF(AND(Dependent_Care<>"",Dependent_Care<>0),"DCB","") | AL39: =AJ40<>"" -> FALSE | AT39: Override
B40: Standard | E40: 4 | F40: a | G40: IRA Distributions | K40: . . . . | L40: =E40&"a" -> 4a | N40: =IF(AM40<>"",ROUND(AM40,0),IF(AL37,"",SUM(ROUND(IRA_Gross,0),ROUND(CONV2ROTH,0)))) | S40: b | T40: Taxable amount | AA40: =IF(AT40<>"",". . . . "&AT40&" ",IF(AI40<>"",". . . . Rollover ",". . . . . . . . . . ")) -> . . . . . . . . . . | AB40: =E40&"b" -> 4b | AC40: =IF(AN40<>"",ROUND(AN40,0),ROUND(SUM(IRA_Taxable_1099R,IRAContrib_Taxable1,IRAContrib_Taxable2,IRAConvert_Taxable1,IRAConvert_Taxable2,RothIRADist_Taxable1,RothIRADist_Taxable2),0)) -> 0 | AJ40: =IF(OrdinaryDividends<Qualified_Dividends,"Error: Qualified dividends "&CHAR(10)&"(line 3a)"&CHAR(10)&"must be included in"&CHAR(10)&"ordinary dividends "&CHAR(10)&"(line 3b).",IF(AND(OrdinaryDividends<>0,Qualified_Dividends<>"",OrdinaryDividends<>Qualified_Dividends),"Caution: Be sure to include all of line 3a, Qualified Dividends, in line 3b, Ordinary Dividend, amount.",IF(AND(IRA_Taxable<>0,AL37,PA_Taxable<>0,AL38),"Lines 4a and 5a"&CHAR(10)&"are blank per"&CHAR(10)&"IRS instructions.",IF(AND(IRA_Taxable<>0,AL37),"Line 4a is blank per"&CHAR(10)&"IRS instructions.",IF(AND(PA_Taxable<>0,AL38),"Line 5a is blank per"&CHAR(10)&"IRS instructions.",IF(AN35,"Use Sheets W-2, "&CHAR(10)&"1099-INT, 1099-DIV, 1099-R, and "&CHAR(10)&"SSA-1099 for accurate results.",""))))))
B41: Deduction for -- | E41: 5 | F41: a | G41: Pensions and annuities | K41: . . . | L41: 5a | N41: =IF(AM41<>"",ROUND(AM41,0),IF(AL38,"",ROUND(PA_Gross,0))) | S41: b | T41: Taxable amount | AA41: =IF(AI41<>"",". . . .Rollover",". . . . . . . . . . ") -> . . . . . . . . . . | AB41: =E41&"b" -> 5b | AC41: =IF(AN41<>"",ROUND(AN41,0),ROUND(PA_Taxable_1099R,0)) -> 0 | AT41: Line 4b
B42: • | C42: Single or married | E42: 6 | F42: a | G42: Social security benefits | K42: =IF(LivedApart,"D ",". . . ") -> . . . | L42: =E42&"a" -> 6a | N42: =IF(AM42<>"",ROUND(AM42,0),ROUND('Line 6ab (SS Bene)'!G14,0)) -> 0 | S42: b | T42: Taxable amount | AA42: . . . . . . . . . . | AB42: =E42&"b" -> 6b | AC42: =IF(AN42<>"",ROUND(AN42,0),IF(ISERROR(ROUND(Tax_SS_Benefits,0)),"See 'Line 5' sheet.",ROUND(Tax_SS_Benefits,0))) -> 0 | AI42: Rollover | AT42: Dotted | AX42: Standard versus Itemized Deduction
C43: filing separately | E43: 7 | G43: Capital gain or (loss). Attach Schedule D if required. If not required, check here | Y43: . . . . . . . . | AB43: =E43 -> 7 | AC43: =IF(AM43<>"",ROUND(AM43,0),IF(Z43<>"",'1099-DIV'!H92,IF('Sch. D'!A61,SchDLine16,'Sch. D'!O89))) | AT43: Line
C44: 12550 | E44: 8 | G44: Other income from Schedule 1, line 10 | AA44: . . . . . . . . . . . . . . . . . . . . . . . | AB44: 8 | AC44: =IF(AM44<>"",ROUND(AM44,0),Additional_Income) -> 0 | AN44: =Z43<>"" -> FALSE | AX44: =IF(File_Single<>"",LOOKUP(Over_65_or_Blind,AO49:AO53,AP49:AP53),IF(OR(File_Marr_Joint<>"",File_Qual_Widow<>""),LOOKUP(Over_65_or_Blind,AO49:AO53,AQ49:AQ53),IF(File_Marr_Sep<>"",LOOKUP(Over_65_or_Blind,AO49:AO53,AR49:AR53),IF(File_Head<>"",LOOKUP(Over_65_or_Blind,AO49:AO53,AS49:AS53),0)))) -> 0 | AY44: =SchA_Filed -> FALSE | AZ44: =NOT(ItemizedDeduct) -> TRUE
B45: • | C45: Married filing | E45: 9 | G45: Add lines 1, 2b, 3b, 4b, 5b, 6b, 7, and 8. This is your total income | AA45: . . . . . . . . . . . . . . | AB45: 9 | AC45: =IF(AM45<>"",ROUND(AM45,0),SUM(Wages,TaxableInterest,OrdinaryDividends,IRA_Taxable,PA_Taxable,SocSecBenefits_Taxable,CapitalGains,AC44)) -> 0 | AO45: =IF(OR($AM$46<>"",$AL$9,NumFileStatusBoxes=0,Dual_Status_Alien<>"",DependentYOU<>"",DependentSPOUSE<>"",ItemizedDeduct),FALSE,TRUE) -> FALSE | AP45: =Over_65_or_Blind -> 0 | AX45: Standard | AY45: Itemized
C46: jointly or Qualifying | E46: 10 | G46: Adjustments to income from Schedule 1, line 26 | AA46: . . . . . . . . . . . . . . . . . . . . . . . . | AB46: 10 | AC46: =IF(AM46<>"",ROUND(AM46,0),SUM(AdjustToIncome)) -> 0 | AO46: Over 65 or Blind | AP46: Standard Deduction Chart | AX46: =IF(OR(Dual_Status_Alien<>"",ISERROR(Over_65_or_Blind)),0, IF('Line 12a (SD Depnts)'!L4,Std_Ded_Wrks_For_Dep, IF(Over_65_or_Blind>0,AX44,AX48))) -> 0 | AY46: =Tot_Item_Deduct -> 0
C47: widow(er) | E47: 11 | G47: Subtract line 10 from line 9. This is your adjusted gross income | AA47: . . . . . . . . . . . . . . . | AB47: 11 | AC47: =IF(AM47<>"",ROUND(AM47,0),SUM(Total_Income,-AC46)) -> 0 | AJ47: =IF(NumFileStatusBoxes=0,"Filing status not indicated.",IF(AND(AM49<>"",AM49>0,SchA_Filed),"Line 12b must be zero"&CHAR(10)&"if Schedule A"&CHAR(10)&" is filed. >>>",IF(AND(OR(AM49="",AM49=0),SchA_Filed),"Line 12b is -0- "&CHAR(10)&"if Schedule A is filed.",IF(AND(AM49<>"",AM49>AN48),"On Form 1040, the charity deduction is limited to "&TEXT(AN48,"$0")&" for your filing status.",IF(AND(AM49<>"",AM49<=AN48),"Charitable deduction claimed on Line 12b.","Enter Line 12b charitable contributions here >>>"))))) -> Filing status not indicated. | AO47: number of
C48: 25100 | E48: 12 | F48: a | G48: Standard deduction or itemized deductions (from Schedule A) | W48: . . . . . . | X48: 12a | Y48: =IF(AM48<>"",ROUND(AM48,0), IF(OR(AND(Total_Income=0,Adj_Gross_Inc=0),NumFileStatusBoxes=0,NumFileStatusBoxes>1,Birthday_Needed,$AL$9),0, IF(AND(NQDisasterLoss>0,StdDeduct),SD_AND_NQDL,IF(ItemizedDeduct,Tot_Item_Deduct,Standard )))) -> 0 | AN48: =IF(File_Marr_Joint<>"",600,IF(OR(File_Single<>"",File_Qual_Widow<>"",File_Head<>"",File_Marr_Sep<>""),300,300)) -> 300 | AO48: boxes checked | AP48: Single | AQ48: MFJ or QW | AR48: MFS | AS48: Head-of-H | AX48: =IF(File_Single<>"",SD_Single,IF(OR(File_Marr_Joint<>"",File_Qual_Widow<>""),SD_MFJW,IF(File_Head<>"",SD_Head,IF(File_Marr_Sep<>"",SD_Single,0)))) -> 0
B49: • | C49: Head of house | F49: b | G49: Charitable contributions if you take the standard deduction (see instructions) | W49: . . | X49: 12b | Y49: =IF(SchA_Filed,0,IF(AM49="","",MIN(ROUND(AM49,0),AN48))) | AO49: 0 | AP49: =SD_Single -> 12550 | AQ49: =SD_MFJW -> 25100 | AR49: =SD_Single -> 12550 | AS49: =SD_Head -> 18800 | AX49: NQDL
C50: 18800 | F50: c | G50: Add lines 12a and 12b | AA50: . . . . . . . . . . . . . . . . . . . . . . . . . . . . | AB50: 12c | AC50: =SUM(Deductions,Charitable) -> 0 | AJ50: Line 12a was calculated using: | AO50: 1 | AP50: =SUM(AP$49,$AO50*AP$55) -> 14250 | AQ50: =SUM(AQ$49,$AO50*AQ$55) -> 26450 | AR50: =SUM(AR$49,$AO50*AR$55) -> 13900 | AS50: =SUM(AS$49,$AO50*AS$55) -> 20500 | AX50: =IF(AND(StdDeduct,NQDisasterLoss<>"",NQDisasterLoss>0),SUM(Standard,NQDisasterLoss),Standard) -> 0
B51: • | C51: If you checked any | E51: 13 | G51: Qualified business income deduction from Form 8995 or Form 8995-A | AA51: =IF(AND(AI51="",QBID_1040<>"",QBID_1040<>0,QBID_Income2High),"Error: See Form 8995.",". . . . . . . . . . . . . . ") -> . . . . . . . . . . . . . . | AB51: 13 | AC51: =IF(AM51<>"",ROUND(AM51,0),IF(QBID="",0,QBID)) -> 0 | AJ51: =IF(AM46<>"","Manual Override",IF(FilingStatusError,"Filing status error.",IF(Birthday_Needed,"Birthdate(s) needed.",IF($AL$9,"Filing status error or invalid spouse input.",IF(NumFileStatusBoxes=0,"Filing status not indicated.", IF(Dual_Status_Alien<>"","Deduction is $0 due to spouse itemizing or dual-status alien.", IF(OR(DependentYOU<>"",DependentSPOUSE<>""),"Line 12a - Standard Deduction for Dependents",IF(AND(NQDisasterLoss>0,StdDeduct),"Standard deduction plus net qualified disaster losses"&CHAR(10)&"on Sch. A, Line 16.",IF(ItemizedDeduct,"Schedule A",IF(Over_65_or_Blind>0,"See Standard "&CHAR(10)&" Deduction Chart"&CHAR(10)&" at right →","Standard Deduction")))))))))) -> Filing status not indicated. | AO51: 2 | AP51: =SUM(AP$49,$AO51*AP$55) -> 15950 | AQ51: =SUM(AQ$49,$AO51*AQ$55) -> 27800 | AR51: =SUM(AR$49,$AO51*AR$55) -> 15250 | AS51: =SUM(AS$49,$AO51*AS$55) -> 22200 | AX51: Taxable_Inc | AY51: Single | AZ51: MFJ/QW | BA51: MFS | BB51: HOH
B52: Standard Deduction | E52: 14 | G52: Add lines 12c and 13 | AA52: . . . . . . . . . . . . . . . . . . . . . . . . . . . . | AB52: 14 | AC52: =IF(AM52<>"",ROUND(AM52,0),SUM(AC50,QBID_1040)) -> 0 | AN52: =OR(Q57<>"",T57<>"",W57<>"") -> FALSE | AO52: 3 | AQ52: =SUM(AQ$49,$AO52*AQ$55) -> 29150 | AR52: =SUM(AR$49,$AO52*AR$55) -> 16600 | AX52: =Taxable_Inc -> 0 | AY52: =LOOKUP(AX52,'Tax Table'!$B$2:$B$2063,'Tax Table'!$D$2:$D$2063) -> 0 | AZ52: =LOOKUP(AX52,'Tax Table'!$B$2:$B$2063,'Tax Table'!$E$2:$E$2063) -> 0 | BA52: =LOOKUP(AX52,'Tax Table'!$B$2:$B$2063,'Tax Table'!$F$2:$F$2063) -> 0 | BB52: =LOOKUP(AX52,'Tax Table'!$B$2:$B$2063,'Tax Table'!$G$2:$G$2063) -> 0
B53: box, see instructions. | E53: 15 | G53: Taxable income. | J53: Subtract line 14 from line 11. | R53: If zero or less, enter -0- | AA53: . . . . . . . . . . | AB53: 15 | AC53: =IF(AM53<>"",ROUND(AM53,0),MAX(0,SUM(Adj_Gross_Inc,-TotalDeductions))) -> 0 | AN53: =IF(AN52,"Total taxes from "&CHAR(10)&"line 16 (1), (2), & (3) ↓ ↓ ↓","") | AO53: 4 | AQ53: =SUM(AQ$49,$AO53*AQ$55) -> 30500 | AR53: =SUM(AR$49,$AO53*AR$55) -> 17950 | AY53: =IF(AX52<SectA_a3,"---",IF(AX52<=SectA_a4,ROUND((AX52*(SectA_b4/100)-SectA_d4),0),IF(AX52<=SectA_a5,ROUND((AX52*(SectA_b5/100)-SectA_d5),0),IF(AX52<=SectA_a6,ROUND((AX52*(SectA_b6/100)-SectA_d6),0),ROUND((AX52*(SectA_b7/100)-SectA_d7),0))))) -> --- | AZ53: =IF(AX52<SectB_a2,"---",IF(AX52<=SectB_a3,ROUND((AX52*(SectB_b3/100)-SectB_d3),0),IF(AX52<=SectB_a4,ROUND((AX52*(SectB_b4/100)-SectB_d4),0),IF(AX52<=SectB_a5,ROUND((AX52*(SectB_b5/100)-SectB_d5),0),IF(AX52<=SectB_a6,ROUND((AX52*(SectB_b6/100)-SectB_d6),0),ROUND((AX52*(SectB_b7/100)-SectB_d7),0)))))) -> --- | BA53: =IF(AX52<SectC_a2,"---",IF(AX52<=SectC_a3,ROUND((AX52*(SectC_b3/100)-SectC_d3),0),IF(AX52<=SectC_a4,ROUND((AX52*(SectC_b4/100)-SectC_d4),0),IF(AX52<=SectC_a5,ROUND((AX52*(SectC_b5/100)-SectC_d5),0),ROUND((AX52*(SectC_b6/100)-SectC_d6),0))))) -> --- | BB53: =IF(AX52<SectD_a2,"---",IF(AX52<=SectD_a3,ROUND((AX52*(SectD_b3/100)-SectD_d3),0),IF(AX52<=SectD_a4,ROUND((AX52*(SectD_b4/100)-SectD_d4),0),IF(AX52<=SectD_a5,ROUND((AX52*(SectD_b5/100)-SectD_d5),0),IF(AX52<=SectD_a6,ROUND((AX52*(SectD_b6/100)-SectD_d6),0),ROUND((AX52*(SectD_b7/100)-SectD_d7),0)))))) -> ---
B54: For Disclosure, Privacy Act, and Paperwork Reduction Act Notice, see separate instructions. | Y54: Cat. No. 11320B | AF54: Form 1040 | AH54: ="("&TaxYear&")" -> (2021) | AX54: =IF(File_Single<>"",AY52,IF(File_Marr_Joint<>"",AZ52,IF(File_Marr_Sep<>"", BA52,IF(File_Head<>"",BB52,IF(File_Qual_Widow<>"",AZ52,"Filing status?"))))) -> Filing status? | AY54: ="<100k" -> <100k
B55: ="Form 1040 ("&TaxYear&")" -> Form 1040 (2021) | AF55: =IF(AND(Birthday_Needed,OR(AX101,AX121)),"Enter your birthdate and your spouse's birthdates above.",IF(AND(Birthday_Needed,AX101),"Enter your birthdate above.","")) | AH55: Page 2 | AP55: 1700 | AQ55: 1350 | AR55: 1350 | AS55: 1700 | AX55: =IF(File_Single<>"",AY53,IF(OR(File_Marr_Joint<>"",File_Qual_Widow<>""),AZ53,IF(File_Marr_Sep<>"", BA53,IF(File_Head<>"",BB53,"Filing status?")))) -> Filing status? | AY55: =">=100k" -> >=100k | BA55: Tax >> | BB55: =IF(AX52>100000,AX55,AX54) -> Filing status?
AC56: =IF(AM57<>"",ROUND(AM57,0),IF(OR(Birthday_Needed,FilingStatusError),"", IF(FEI_Tax_Worksheet,SUM(Tax_FEI_TW,AO57),IF(CGTW,SUM(CGTW_Tax,AO57),IF(SchDTW_Used,SUM(SchDTW_Tax,AO57),SUM(BB55,AO57)))))) -> 0
E57: 16 | G57: Tax (see instructions). | O57: Check if any from Form(s): | P57: 1 | S57: 8814 2 | V57: 4972 3 | AA57: . . . | AB57: 16 | AJ57: The tax in Line 16 is | AO57: =ROUND(AN57,0) -> 0
E58: 17 | G58: Amount from Schedule 2, line 3 | AA58: . . . . . . . . . . . . . . . . . . . . . . . . | AB58: 17 | AC58: =IF(AM58<>"",ROUND(AM58,0),Schedule2) -> 0 | AJ58: calculated using: | AO58: =Q57<>"" -> FALSE | AQ58: =T57<>"" -> FALSE | AR58: =W57<>"" -> FALSE
E59: 18 | G59: Add lines 16 and 17 | AA59: . . . . . . . . . . . . . . . . . . . . . . . . . . . . . | AB59: 18 | AC59: =IF(AM59<>"",ROUND(AM59,0),SUM(Tax_SubTotal,AC58)) -> 0 | AJ59: =IF(AM57<>"","Manual override",IF(FilingStatusError,"Filing status information needed or needs corrected.",IF(Birthday_Needed,"Birthdate information needed.",IF(OR(Total_Income=0,Taxable_Inc=""),"",IF(FEI_Tax_Worksheet,"FEI Tax Worksheet on "&CHAR(10)&"'Line 16 (QDCG Tax)'"&CHAR(10)&AN59,IF(CGTW,"QD & CG Tax WS"&CHAR(10)&"'Line 16 (QDCG Tax)'"&CHAR(10)&AN59,IF(SchDTW_Used,"Sch. D Tax Worksheet"&CHAR(10)&AN59,IF(Taxable_Inc<100000,"Tax Table"&CHAR(10)&AN59,"Tax Formula"&CHAR(10)&AN59)))))))) | AN59: =AO59&AQ59&AR59 | AO59: =IF(AO58,"& Form 8814 "&"","") | AQ59: =IF(AQ58,"& Form 4972 "&"","") | AR59: =IF(AR58,"& Form "&X57&" ","")
E60: 19 | G60: Nonrefundable child tax credit or credit for other dependents from Schedule 8812 | AA60: . . . . . . . | AB60: 19 | AC60: =IF(AM60<>"",ROUND(AM60,0),SUM(CreditForOtherDepend_IB,CreditForOtherDepend_IC)) -> 0
E61: 20 | G61: Amount from Schedule 3, line 8 | AA61: . . . . . . . . . . . . . . . . . . . . . . . . . | AB61: 20 | AC61: =IF(AM61<>"",ROUND(AM61,0),Sch3_NonRefundCredits) -> 0
E62: 21 | G62: Add lines 19 and 20 | AA62: . . . . . . . . . . . . . . . . . . . . . . . . . . . . . | AB62: 21 | AC62: =IF(AM62<>"",ROUND(AM62,0),SUM(AC60,AC61)) -> 0 | AJ62: =IF(AND(AI62="",F8960_Applicable)," Check Form 8960.",IF(F8960_Applicable,"Form 8960 checked.",""))
E63: 22 | G63: Subtract line 21 from line 18. If zero or less, enter -0- | AA63: . . . . . . . . . . . . . . . . . . | AB63: =E63 -> 22 | AC63: =IF(AM63<>"",ROUND(AM63,0),MAX(0,SUM(Tax,-AC62))) -> 0
E64: 23 | G64: Other taxes, including self-employment tax, from Schedule 2, line 21 | AA64: . . . . . . . . . . . . . | AB64: =E64 -> 23 | AC64: =IF(AM64<>"",ROUND(AM64,0),TotalOtherTaxes) -> 0
E65: 24 | G65: Add lines 22 and 23. This is your total tax | AA65: . . . . . . . . . . . . . . . . . . . . . . . . . . | AB65: =E65 -> 24 | AC65: =SUM(AC63,AC64) -> 0
E66: 25 | G66: Federal income tax withheld from:
F67: a | G67: Form(s) W-2 | W67: . . . . . . . . . . . . . . . . . . . . . . . . | X67: 25a | Y67: =IF(AM67<>"",ROUND(AM67,0),W2_Tax_Withheld) -> 0
F68: b | G68: Form(s) 1099 | W68: . . . . . . . . . . . . . . . . . . . . . . . . | X68: 25b | Y68: =IF(AM68<>"",ROUND(AM68,0),SUM(F1099INT_FedTaxWH,F1099DIV_FedTaxWH,F1099G_FedTaxWH,IRA_FedTaxWH,PA_FedTaxWH,CONV_FedTaxWH,SS_FedTaxWH_You,SS_FedTaxWH_Spouse,ROUND(AJ68,0))) -> 0 | AL68: 25b (add)
F69: c | G69: Other forms (see instructions) | W69: . . . . . . . . . . . . . . . . . . | X69: 25c | Y69: =IF(AM69<>"",ROUND(AM69,0),SUM(F8959_WH,ROUND(AJ69,0))) -> 0 | AL69: 25c (add)
F70: d | G70: Add lines 25a through 25c | AA70: . . . . . . . . . . . . . . . . . . . . . . . . . . . | AB70: 25d | AC70: =SUM(W2_FedTaxWH,F1099_FedTaxWH,ROUND(Y69,0)) -> 0 | AJ70: =IF($AJ$72>0,"Form 8959, Line 24,","")
B71: If you have a qualifying child, attach Sch EIC. | E71: 26 | G71: =TaxYear&" estimated tax payments and amount applied from "&TaxYear-1&" return" -> 2021 estimated tax payments and amount applied from 2020 return | AA71: . . . . . . . . . . . . . | AB71: 26 | AJ71: =IF($AJ$72>0,"<<< added "&TEXT($AJ$72,"$000")&" to Line 25c.","")
E72: 27 | F72: a | G72: Earned income credit (EIC) | W72: =IF(EIC_No,". . . . . . . . . . . . . . . . . No. ",". . . . . . . . . . . . . . . . . .") -> . . . . . . . . . . . . . . . . . . | X72: 27a | Y72: =IF(AM72<>"",ROUND(AM72,0),EarnedIncomeCredit) -> 0 | AC72: =IF(AND($AI$72="",$AL$80),"Review sheet","") | AJ72: =IF(ISERROR(F8959_WH),0,F8959_WH) -> 0
G73: ="Check here if you were born after January 1, "&TaxYear-23&", and before" -> Check here if you were born after January 1, 1998, and before | AC73: =IF(AND($AI$72="",$AL$80),"'Line 27 (EIC)'","")
G74: ="January 2, "&TaxYear-17&", and you satisfy all the other requirements for" -> January 2, 2004, and you satisfy all the other requirements for | AC74: =IF(AND($AI$72="",$AL$80),"for possible earned","") | AJ74: =IF($AL$80,"Hide note.","")
G75: taxpayers who are at least age 18, to claim the EIC. See instructions | AC75: =IF(AND($AI$72="",$AL$80),"income tax credit.","")
F76: b | G76: Nontaxable combat pay election | R76: . . . . . . . . . . . | S76: 27b
F77: c | G77: ="Prior year ("&TaxYear-2&") earned income" -> Prior year (2019) earned income | R77: . . . . . . . . . . . | S77: 27c
E78: 28 | G78: Refundable child tax credit or additional child tax credit from Schedule 8812 | W78: . . . . . | X78: 28 | Y78: =IF(AM78<>"",ROUND(AM78,0),AdditionalCTC) -> 0
E79: 29 | G79: American opportunity credit from Form 8863, line 8 | W79: . . . . . . . . . . . . . . | X79: 29 | Y79: =IF(AM79<>"",ROUND(AM79,0),AO_Credit)
E80: 30 | G80: Recovery rebate credit. See instructions | W80: . . . . . . . . . . . . . . . . . . | X80: 30 | Y80: =IF(AM80<>"",ROUND(AM80,0),RebateCredit) -> 0 | AL80: =AND(EIC_trigger,NOT(EIC_Started),NumFileStatusBoxes=1) -> FALSE
E81: 31 | G81: Amount from Schedule 3, line 15 | W81: . . . . . . . . . . . . . . . . . . . . . | X81: 31 | Y81: =IF(AM81<>"",ROUND(AM81,0),OPRC) -> 0
E82: 32 | G82: Add lines 27a and 28 through 31. These are your total other payments and refundable credits | AA82: . . . . . . | AB82: 32 | AC82: =SUM(EIC,Y78,Y79,RecoveryRebateCredit,Y81) -> 0
E83: 33 | G83: Add lines 25d, 26, and 32. These are your total payments | AA83: . . . . . . . . . . . . . . . . . | AB83: 33 | AC83: =IF(AM83<>"",ROUND(AM83,0),SUM(AC70,AC71,AC82)) -> 0
E84: 34 | G84: If line 33 is more than line 24, subtract line 24 from line 33. This is the amount you overpaid | AA84: . . . . . . | AB84: =E84 -> 34 | AC84: =IF(AM84<>"",ROUND(AM84,0),IF(AC83>Tot_Tax,SUM(AC83,-Tot_Tax),0)) -> 0
B85: Refund | E85: 35 | F85: a | G85: Amount of line 34 you want refunded to you. If Form 8888 is attached, check here | Y85: . . . . . | AB85: =E85&"a" -> 35a | AC85: =Overpaid -> 0 | AJ85: =AND(You_Owe>1000,You_Owe>0.1*Tot_Tax) -> FALSE | AL85: =AND(AJ85,AI89="") -> FALSE
B86: Direct deposit? | F86: b | G86: Routing number | T86: c Type: | V86: Checking | Z86: Savings | AC86: =IF(AND($AI$89="",$AJ$94),"Sum of amounts on","") | AJ86: =IF($AL$85,"Check sheet 2210 to","")
B87: See instructions | F87: d | G87: Account number | AA87: . . . . . . . . . . . | AC87: =IF(AND($AI$89="",$AJ$94),"Lines 35a & 36","") | AJ87: =IF($AL$85,"figure any tax penalty","")
E88: 36 | G88: ="Amount of line 34 you want" -> Amount of line 34 you want | L88: ="applied to your "&TaxYear+1&" estimated tax" -> applied to your 2022 estimated tax | U88: =E88 -> 36 | W88: =IF(AM88<>"",ROUND(AM88,0),SUM(Overpaid,-AC85)) -> 0 | AC88: =IF(AND($AI$89="",$AJ$94),"must equal Line 34.","") | AJ88: =IF($AL$85,"that may apply.","")
B89: Amount You Owe | E89: 37 | G89: Amount you owe. Subtract line 33 from line 24. For details on how to pay, see instructions | AA89: . . . . . . | AB89: =E89 -> 37 | AC89: =IF(AM89<>"",AM89,IF(ISERROR(Tot_Tax-Tot_Payments+TaxPenalty),0,IF(Tot_Tax-Tot_Payments+TaxPenalty<0,0,Tot_Tax-Tot_Payments+TaxPenalty))) -> 0 | AJ89: =IF(OR(AJ85,AJ94),"Hide note.","")
E90: 38 | G90: =IF(AND(You_Owe<>"",You_Owe>1000,You_Owe>0.1*Tot_Tax,TaxPenalty=""),"Enter Estimated Tax Penalty (or 0 if none applies)","Estimated tax penalty (see instructions)") -> Estimated tax penalty (see instructions) | T90: . . . . . . . . . . | U90: =E90 -> 38 | W90: =IF(AM90<>"",ROUND(AM90,0),SUM('2210'!U107)) -> 0
B91: Third Party Designee | E91: Do you want to allow another person to discuss this return with the IRS?
E92: See instructions | U92: . . . . . . . . . . . . . . . . . . . . . . . . . . | W92: Yes. Complete below. | AC92: =IF(V92="","X","") -> X | AD92: No
E94: Designee's name | Q94: Phone no. | X94: Personal identification number (PIN) | AJ94: =(SUM(AC85,W88)<>Overpaid) -> FALSE
C95: Sign | E95: Under penalties of perjury, I declare that I have examined this return and accompanying schedules and statements, and to the best of my knowledge and belief, they are true,
C96: Here | E96: correct, and complete. Declaration of preparer (other than taxpayer) is based on all information of which preparer has any knowledge.
C97: Joint return? | E97: Your signature | P97: Date | T97: Your occupation | AA97: If the IRS sent you an Identity Prot. PIN, | BA97: Birthdate and age calculator | BF97: 1 | BG97: Jan
C98: See instructions. | AA98: enter here | BF98: 2 | BG98: Feb
C99: Keep a copy | E99: Spouse’s signature. If a joint return, both must sign. | P99: Date | T99: Spouse's occupation | AA99: If the IRS sent you an Identity Prot. PIN, | BF99: 3 | BG99: Mar
C100: for your records. | AA100: enter here | AY100: =DATEVALUE(AY102) -> #N/A | BF100: 4 | BG100: Apr
E101: Phone no. | P101: Email address | AX101: =IF(OR(YourBirthMonth="",YourBirthDay="",YourBirthYear=""),TRUE,FALSE) -> TRUE | AY101: =DATEVALUE(AY102) -> #N/A | AZ101: BadBirthday_Yours | BC101: 70th Birthday --> | BD101: =IF(AND(YourBirthMonth=2,YourBirthDay=29),YourBirthDay-1&"-"&LOOKUP(YourBirthMonth,$BF$97:$BF$109,$BG$97:$BG$109)&"-"&(YourBirthYear+70),YourBirthDay&"-"&LOOKUP(YourBirthMonth,$BF$97:$BF$109,$BG$97:$BG$109)&"-"&(YourBirthYear+70)) -> #N/A | BF101: 5 | BG101: May
C102: Paid Preparers Use Only | E102: Preparer’s name | L102: Preparer’s signature | V102: Date | Z102: PTIN | AE102: Check if: | AX102: =LOOKUP(YourBirthMonth,$BF$97:$BF$109,$BG$97:$BG$109) -> #N/A | AY102: =YourBirthDay&"-"&AX102&"-"&YourBirthYear -> #N/A | AZ102: =IF(OR(YourBirthMonth="",YourBirthDay="",YourBirthYear=""),TRUE,IF(ISERROR(AY101),TRUE,FALSE)) -> TRUE | BA102: =IF(AND(YourBirthMonth="",YourBirthDay="",YourBirthYear=""),FALSE,IF(OR(BadBirthdate_Yours,AND(YourAge>120,AND(YourBirthMonth<>"",YourBirthDay<>"",YourBirthYear<>""))),TRUE,FALSE)) -> FALSE | BE102: =YourBirthMonth+6 -> 6 | BF102: 6 | BG102: Jun
AF103: Self-employed | AY103: =IF(BA102,"",DATEVALUE(AY102)) -> #N/A | BB103: ="YOU are 70.5 on "&TEXT(EndOfTaxYear,"dd-mmm-yyyy")&" ->" -> YOU are 70.5 on 31-Dec-2021 -> | BC103: =IF(BadBirthdate_Yours,FALSE,IF(DATEVALUE(BD101)<=DATEVALUE(BC106),TRUE,FALSE)) -> FALSE | BE103: =IF(BE102<=12,YourBirthYear+70,YourBirthYear+71) -> 70 | BF103: 7 | BG103: Jul
E104: Firm’s name | AA104: Phone no. | AY104: =ROUNDDOWN((EndOfTaxYear-AY103)/365.25,1) -> #N/A | BB104: ="YOU are 65 on "&TEXT(EndOfTaxYear,"dd-mmm-yyyy")&" ->" -> YOU are 65 on 31-Dec-2021 -> | BC104: =IF(BadBirthdate_Yours,FALSE,YourAge>=65) -> FALSE | BF104: 8 | BG104: Aug
E105: Firm’s address | AA105: Firm's EIN | AY105: =IF(YourBirthYear="","?",IF(AND(YourBirthMonth=1,YourBirthDay=1),TaxYear-YourBirthYear+1,TaxYear-YourBirthYear)) -> ? | BB105: ="YOU are born before "&TEXT(BE105,"dd-mmm-yyyy")&" ->" -> YOU are born before 02-Jan-1956 -> | BC105: =AY101<$BE$105 -> #N/A | BD105: =(YEAR($BE$105)-YEAR(AY102)) -> #N/A | BE105: =DATEVALUE("2-JAN-"&TaxYear-65) -> 20456 | BF105: 9 | BG105: Sep
B106: Go to www.irs.gov/Form1040 for instructions and the latest information. | AC106: Form 1040 | AH106: ="("&TaxYear&")" -> (2021) | BB106: End of tax year minus 6 months --> | BC106: ="30-Jun-"&TaxYear -> 30-Jun-2021 | BF106: 10 | BG106: Oct
AX107: YOU >=24 Test | AZ107: =DATEVALUE("2-JAN-"&(TaxYear-23)) -> 35797 | BA107: =$AY$101<AZ107 -> #N/A | BF107: 11 | BG107: Nov
AX108: YOU >=25 Test | AZ108: =DATEVALUE("2-JAN-"&(TaxYear-24)) -> 35432 | BA108: =$AY$101<AZ108 -> #N/A | BF108: 12 | BG108: Dec
E109: Download Form 1040 General Instructions from IRS | AX109: YOU <65 Test | AZ109: =DATEVALUE("31-DEC-"&(TaxYear-65)) -> 20820 | BA109: =$AY$101>AZ109 -> #N/A | BF109: 13 | BG109: Bad
...

Sheet Dependents
M1: =IF(BO3,"One or more 'default' SSNs has been generated.","To be a valid SSN,"&CHAR(10)&"- Can't begin w/ '000',"&CHAR(10)&"- Can't begin w/ '666',"&CHAR(10)&"- Can't begin w/ '9'"&CHAR(10)&"- Issued before due date"&CHAR(10)&"(See instructions.)") -> To be a valid SSN, - Can't begin w/ '000', - Can't begin w/ '666', - Can't begin w/ '9' - Issued before due date (See instructions.) | AI1: =IF(BR3,"Enter child/dependent's birthdate to ensure accurate tax credit determination.","")
C2: To be counted for Child Tax Credit, the following must be included: - a valid Social Security Number - Child Tax Credit box checked - Birthdate | BH2: Dependents | BI2: Both (Error) | BJ2: Child Tax Credit | BK2: Other Dependent
BO3: =OR(BO7:BO10,BO15:BO30) -> FALSE | BR3: =OR(BR7:BR10,BR15:BR30) -> FALSE
B4: Dependents | M4: ="(2) Social security "&CHAR(10)&"number" -> (2) Social security number | S4: (3) Relationship to you | Y4: =IF(BI11>0,"Error: You cannot take both credits.","") | AI4: Birthdate | AO4: ="Age "&CHAR(10)&"(in "&TaxYear&")" -> Age (in 2021)
E5: (see instructions) : | Z5: (4) | AB5: if qualified for (see instructions): | BN5: Valid SSN? | BO5: Default SSN? | BR5: B/D Missing? | BS5: Under 18 w/SSN | BT5: Under 6 w/SSN | BU5: Other Depend | BW5: Depend w/SSN
B6: If more than four dependents, see instructions and check | E6: (1) First name | I6: Last name | Y6: Child tax credit | AC6: Credit for other dependents | BP6: QC
M7: =IF(OR(Z7<>"",AF7<>""),"001-01-0003","") | AO7: =IF(AI7="","",TaxYear-YEAR(AI7)) | AQ7: =IF(AND(BS7<>0,BT7<>0),BT$5,IF(BS7<>0,BS$5,IF(BT7<>0,BT$5,IF(BU7<>0,BU$5,IF(BW7<>0,$BW$5,""))))) | BH7: =IF(OR(E7<>"",I7<>"",M7<>"",S7<>"",Z7<>"",AF7<>""),1,0) -> 0 | BI7: =IF(AND(Z7<>"",AF7<>""),1,0) -> 0 | BJ7: =IF(AND(Z7<>"",$BI7=0),1,0) -> 0 | BK7: =IF(AND(AF7<>"",$BI7=0),1,0) -> 0 | BL7: =TEXT(M7,"000-00-0000") | BM7: =LEFT(BL7,3) | BN7: =AND(M7<>"",LEFT(BM7,3)<>"000",LEFT(BM7,3)<>"666",LEFT(BM7,1)<>"9") -> FALSE | BO7: =LEFT(M7,6)="001-01" -> FALSE | BP7: =IF(AND(M7<>"",NOT(BN7)),1,0) -> 0 | BR7: =AND(AI7="",OR(Z7<>"",AF7<>"")) -> FALSE | BS7: =IF(AND(AO7<18,Z7<>"",AF7="",BN7),1,0) -> 0 | BT7: =IF(OR(BS7=0,AO7>=6),0,IF(AO7<6,BS7,0)) -> 0 | BU7: =IF(OR(AND(Z7="",AF7<>""),AND(Z7<>"",AF7="",NOT(BN7))),1,0) -> 0 | BW7: =IF(AND(BH7=1,BP7<>1),1,0) -> 0
M8: =IF(OR(Z8<>"",AF8<>""),"001-01-0004","") | AO8: =IF(AI8="","",TaxYear-YEAR(AI8)) | AQ8: =IF(AND(BS8<>0,BT8<>0),BT$5,IF(BS8<>0,BS$5,IF(BT8<>0,BT$5,IF(BU8<>0,BU$5,IF(BW8<>0,$BW$5,""))))) | BH8: =IF(OR(E8<>"",I8<>"",M8<>"",S8<>"",Z8<>"",AF8<>""),1,0) -> 0 | BI8: =IF(AND(Z8<>"",AF8<>""),1,0) -> 0 | BJ8: =IF(AND(Z8<>"",$BI8=0),1,0) -> 0 | BK8: =IF(AND(AF8<>"",$BI8=0),1,0) -> 0 | BL8: =TEXT(M8,"000-00-0000") | BM8: =LEFT(BL8,3) | BN8: =AND(M8<>"",LEFT(BM8,3)<>"000",LEFT(BM8,3)<>"666",LEFT(BM8,1)<>"9") -> FALSE | BO8: =LEFT(M8,6)="001-01" -> FALSE | BP8: =IF(AND(M8<>"",NOT(BN8)),1,0) -> 0 | BR8: =AND(AI8="",OR(Z8<>"",AF8<>"")) -> FALSE | BS8: =IF(AND(AO8<18,Z8<>"",AF8="",BN8),1,0) -> 0 | BT8: =IF(OR(BS8=0,AO8>=6),0,IF(AO8<6,BS8,0)) -> 0 | BU8: =IF(OR(AND(Z8="",AF8<>""),AND(Z8<>"",AF8="",NOT(BN8))),1,0) -> 0 | BW8: =IF(AND(BH8=1,BP8<>1),1,0) -> 0
M9: =IF(OR(Z9<>"",AF9<>""),"001-01-0005","") | AO9: =IF(AI9="","",TaxYear-YEAR(AI9)) | AQ9: =IF(AND(BS9<>0,BT9<>0),BT$5,IF(BS9<>0,BS$5,IF(BT9<>0,BT$5,IF(BU9<>0,BU$5,IF(BW9<>0,$BW$5,""))))) | BH9: =IF(OR(E9<>"",I9<>"",M9<>"",S9<>"",Z9<>"",AF9<>""),1,0) -> 0 | BI9: =IF(AND(Z9<>"",AF9<>""),1,0) -> 0 | BJ9: =IF(AND(Z9<>"",$BI9=0),1,0) -> 0 | BK9: =IF(AND(AF9<>"",$BI9=0),1,0) -> 0 | BL9: =TEXT(M9,"000-00-0000") | BM9: =LEFT(BL9,3) | BN9: =AND(M9<>"",LEFT(BM9,3)<>"000",LEFT(BM9,3)<>"666",LEFT(BM9,1)<>"9") -> FALSE | BO9: =LEFT(M9,6)="001-01" -> FALSE | BP9: =IF(AND(M9<>"",NOT(BN9)),1,0) -> 0 | BR9: =AND(AI9="",OR(Z9<>"",AF9<>"")) -> FALSE | BS9: =IF(AND(AO9<18,Z9<>"",AF9="",BN9),1,0) -> 0 | BT9: =IF(OR(BS9=0,AO9>=6),0,IF(AO9<6,BS9,0)) -> 0 | BU9: =IF(OR(AND(Z9="",AF9<>""),AND(Z9<>"",AF9="",NOT(BN9))),1,0) -> 0 | BW9: =IF(AND(BH9=1,BP9<>1),1,0) -> 0
B10: here | D10: =IF(AR33>4,"X","") | M10: =IF(OR(Z10<>"",AF10<>""),"001-01-0006","") | AO10: =IF(AI10="","",TaxYear-YEAR(AI10)) | AQ10: =IF(AND(BS10<>0,BT10<>0),BT$5,IF(BS10<>0,BS$5,IF(BT10<>0,BT$5,IF(BU10<>0,BU$5,IF(BW10<>0,$BW$5,""))))) | BH10: =IF(OR(E10<>"",I10<>"",M10<>"",S10<>"",Z10<>"",AF10<>""),1,0) -> 0 | BI10: =IF(AND(Z10<>"",AF10<>""),1,0) -> 0 | BJ10: =IF(AND(Z10<>"",$BI10=0),1,0) -> 0 | BK10: =IF(AND(AF10<>"",$BI10=0),1,0) -> 0 | BL10: =TEXT(M10,"000-00-0000") | BM10: =LEFT(BL10,3) | BN10: =AND(M10<>"",LEFT(BM10,3)<>"000",LEFT(BM10,3)<>"666",LEFT(BM10,1)<>"9") -> FALSE | BO10: =LEFT(M10,6)="001-01" -> FALSE | BP10: =IF(AND(M10<>"",NOT(BN10)),1,0) -> 0 | BR10: =AND(AI10="",OR(Z10<>"",AF10<>"")) -> FALSE | BS10: =IF(AND(AO10<18,Z10<>"",AF10="",BN10),1,0) -> 0 | BT10: =IF(OR(BS10=0,AO10>=6),0,IF(AO10<6,BS10,0)) -> 0 | BU10: =IF(OR(AND(Z10="",AF10<>""),AND(Z10<>"",AF10="",NOT(BN10))),1,0) -> 0 | BW10: =IF(AND(BH10=1,BP10<>1),1,0) -> 0
BH11: =SUM(BH7:BH10) -> 0 | BI11: =SUM(BI7:BI10) -> 0 | BJ11: =SUM(BJ7:BJ10) -> 0 | BK11: =SUM(BK7:BK10) -> 0 | BP11: =SUM(BP7:BP10) -> 0
B12: More Dependents | M12: (2) Social security number | S12: (3) Relationship to you | Y12: =IF(AS32>0,"Error: You cannot take both credits.","") | AI12: Birthdate | AO12: ="Age "&CHAR(10)&"(in "&TaxYear&")" -> Age (in 2021)
E13: (see instructions) : | Z13: (4) | AB13: if qualified for (see instructions): | BN13: Valid SSN? | BO13: Default SSN? | BS13: Under 18 w/SSN | BT13: Under 6 w/SSN | BU13: Other Depend | BW13: Other Depend
E14: (1) First name | I14: Last name | Y14: Child tax credit | AC14: Credit for other dependents
M15: =IF(OR(Z15<>"",AF15<>""),"001-01-0007","") | AO15: =IF(AI15="","",TaxYear-YEAR(AI15)) | AQ15: =IF(AND(BS15<>0,BT15<>0),BT$5,IF(BS15<>0,BS$5,IF(BT15<>0,BT$5,IF(BU15<>0,BU$5,IF(BW15<>0,$BW$5,""))))) | BH15: =IF(OR(E15<>"",I15<>"",M15<>"",S15<>"",Z15<>"",AF15<>""),1,0) -> 0 | BI15: =IF(AND(Z15<>"",AF15<>""),1,0) -> 0 | BJ15: =IF(AND(Z15<>"",$BI15=0),1,0) -> 0 | BK15: =IF(AND(AF15<>"",$BI15=0),1,0) -> 0 | BL15: =TEXT(M15,"000-00-0000") | BM15: =LEFT(BL15,3) | BN15: =AND(M15<>"",LEFT(BM15,3)<>"000",LEFT(BM15,3)<>"666",LEFT(BM15,1)<>"9") -> FALSE | BO15: =LEFT(M15,6)="001-01" -> FALSE | BP15: =IF(AND(M15<>"",NOT(BN15)),1,0) -> 0 | BR15: =AND(AI15="",OR(Z15<>"",AF15<>"")) -> FALSE | BS15: =IF(AND(AO15<18,Z15<>"",AF15="",BN15),1,0) -> 0 | BT15: =IF(OR(BS15=0,AO15>=6),0,IF(AO15<6,BS15,0)) -> 0 | BU15: =IF(OR(AND(Z15="",AF15<>""),AND(Z15<>"",AF15="",NOT(BN15))),1,0) -> 0 | BW15: =IF(AND(BH15=1,BP15<>1),1,0) -> 0
M16: =IF(OR(Z16<>"",AF16<>""),"001-01-0008","") | AO16: =IF(AI16="","",TaxYear-YEAR(AI16)) | AQ16: =IF(AND(BS16<>0,BT16<>0),BT$5,IF(BS16<>0,BS$5,IF(BT16<>0,BT$5,IF(BU16<>0,BU$5,IF(BW16<>0,$BW$5,""))))) | BH16: =IF(OR(E16<>"",I16<>"",M16<>"",S16<>"",Z16<>"",AF16<>""),1,0) -> 0 | BI16: =IF(AND(Z16<>"",AF16<>""),1,0) -> 0 | BJ16: =IF(AND(Z16<>"",$BI16=0),1,0) -> 0 | BK16: =IF(AND(AF16<>"",$BI16=0),1,0) -> 0 | BL16: =TEXT(M16,"000-00-0000") | BM16: =LEFT(BL16,3) | BN16: =AND(M16<>"",LEFT(BM16,3)<>"000",LEFT(BM16,3)<>"666",LEFT(BM16,1)<>"9") -> FALSE | BO16: =LEFT(M16,6)="001-01" -> FALSE | BP16: =IF(AND(M16<>"",NOT(BN16)),1,0) -> 0 | BR16: =AND(AI16="",OR(Z16<>"",AF16<>"")) -> FALSE | BS16: =IF(AND(AO16<18,Z16<>"",AF16="",BN16),1,0) -> 0 | BT16: =IF(OR(BS16=0,AO16>=6),0,IF(AO16<6,BS16,0)) -> 0 | BU16: =IF(OR(AND(Z16="",AF16<>""),AND(Z16<>"",AF16="",NOT(BN16))),1,0) -> 0 | BW16: =IF(AND(BH16=1,BP16<>1),1,0) -> 0
M17: =IF(OR(Z17<>"",AF17<>""),"001-01-0009","") | AO17: =IF(AI17="","",TaxYear-YEAR(AI17)) | AQ17: =IF(AND(BS17<>0,BT17<>0),BT$5,IF(BS17<>0,BS$5,IF(BT17<>0,BT$5,IF(BU17<>0,BU$5,IF(BW17<>0,$BW$5,""))))) | BH17: =IF(OR(E17<>"",I17<>"",M17<>"",S17<>"",Z17<>"",AF17<>""),1,0) -> 0 | BI17: =IF(AND(Z17<>"",AF17<>""),1,0) -> 0 | BJ17: =IF(AND(Z17<>"",$BI17=0),1,0) -> 0 | BK17: =IF(AND(AF17<>"",$BI17=0),1,0) -> 0 | BL17: =TEXT(M17,"000-00-0000") | BM17: =LEFT(BL17,3) | BN17: =AND(M17<>"",LEFT(BM17,3)<>"000",LEFT(BM17,3)<>"666",LEFT(BM17,1)<>"9") -> FALSE | BO17: =LEFT(M17,6)="001-01" -> FALSE | BP17: =IF(AND(M17<>"",NOT(BN17)),1,0) -> 0 | BR17: =AND(AI17="",OR(Z17<>"",AF17<>"")) -> FALSE | BS17: =IF(AND(AO17<18,Z17<>"",AF17="",BN17),1,0) -> 0 | BT17: =IF(OR(BS17=0,AO17>=6),0,IF(AO17<6,BS17,0)) -> 0 | BU17: =IF(OR(AND(Z17="",AF17<>""),AND(Z17<>"",AF17="",NOT(BN17))),1,0) -> 0 | BW17: =IF(AND(BH17=1,BP17<>1),1,0) -> 0
M18: =IF(OR(Z18<>"",AF18<>""),"001-01-0010","") | AO18: =IF(AI18="","",TaxYear-YEAR(AI18)) | AQ18: =IF(AND(BS18<>0,BT18<>0),BT$5,IF(BS18<>0,BS$5,IF(BT18<>0,BT$5,IF(BU18<>0,BU$5,IF(BW18<>0,$BW$5,""))))) | BH18: =IF(OR(E18<>"",I18<>"",M18<>"",S18<>"",Z18<>"",AF18<>""),1,0) -> 0 | BI18: =IF(AND(Z18<>"",AF18<>""),1,0) -> 0 | BJ18: =IF(AND(Z18<>"",$BI18=0),1,0) -> 0 | BK18: =IF(AND(AF18<>"",$BI18=0),1,0) -> 0 | BL18: =TEXT(M18,"000-00-0000") | BM18: =LEFT(BL18,3) | BN18: =AND(M18<>"",LEFT(BM18,3)<>"000",LEFT(BM18,3)<>"666",LEFT(BM18,1)<>"9") -> FALSE | BO18: =LEFT(M18,6)="001-01" -> FALSE | BP18: =IF(AND(M18<>"",NOT(BN18)),1,0) -> 0 | BR18: =AND(AI18="",OR(Z18<>"",AF18<>"")) -> FALSE | BS18: =IF(AND(AO18<18,Z18<>"",AF18="",BN18),1,0) -> 0 | BT18: =IF(OR(BS18=0,AO18>=6),0,IF(AO18<6,BS18,0)) -> 0 | BU18: =IF(OR(AND(Z18="",AF18<>""),AND(Z18<>"",AF18="",NOT(BN18))),1,0) -> 0 | BW18: =IF(AND(BH18=1,BP18<>1),1,0) -> 0
M19: =IF(OR(Z19<>"",AF19<>""),"001-01-0011","") | AO19: =IF(AI19="","",TaxYear-YEAR(AI19)) | AQ19: =IF(AND(BS19<>0,BT19<>0),BT$5,IF(BS19<>0,BS$5,IF(BT19<>0,BT$5,IF(BU19<>0,BU$5,IF(BW19<>0,$BW$5,""))))) | BH19: =IF(OR(E19<>"",I19<>"",M19<>"",S19<>"",Z19<>"",AF19<>""),1,0) -> 0 | BI19: =IF(AND(Z19<>"",AF19<>""),1,0) -> 0 | BJ19: =IF(AND(Z19<>"",$BI19=0),1,0) -> 0 | BK19: =IF(AND(AF19<>"",$BI19=0),1,0) -> 0 | BL19: =TEXT(M19,"000-00-0000") | BM19: =LEFT(BL19,3) | BN19: =AND(M19<>"",LEFT(BM19,3)<>"000",LEFT(BM19,3)<>"666",LEFT(BM19,1)<>"9") -> FALSE | BO19: =LEFT(M19,6)="001-01" -> FALSE | BP19: =IF(AND(M19<>"",NOT(BN19)),1,0) -> 0 | BR19: =AND(AI19="",OR(Z19<>"",AF19<>"")) -> FALSE | BS19: =IF(AND(AO19<18,Z19<>"",AF19="",BN19),1,0) -> 0 | BT19: =IF(OR(BS19=0,AO19>=6),0,IF(AO19<6,BS19,0)) -> 0 | BU19: =IF(OR(AND(Z19="",AF19<>""),AND(Z19<>"",AF19="",NOT(BN19))),1,0) -> 0 | BW19: =IF(AND(BH19=1,BP19<>1),1,0) -> 0
M20: =IF(OR(Z20<>"",AF20<>""),"001-01-0012","") | AO20: =IF(AI20="","",TaxYear-YEAR(AI20)) | AQ20: =IF(AND(BS20<>0,BT20<>0),BT$5,IF(BS20<>0,BS$5,IF(BT20<>0,BT$5,IF(BU20<>0,BU$5,IF(BW20<>0,$BW$5,""))))) | BH20: =IF(OR(E20<>"",I20<>"",M20<>"",S20<>"",Z20<>"",AF20<>""),1,0) -> 0 | BI20: =IF(AND(Z20<>"",AF20<>""),1,0) -> 0 | BJ20: =IF(AND(Z20<>"",$BI20=0),1,0) -> 0 | BK20: =IF(AND(AF20<>"",$BI20=0),1,0) -> 0 | BL20: =TEXT(M20,"000-00-0000") | BM20: =LEFT(BL20,3) | BN20: =AND(M20<>"",LEFT(BM20,3)<>"000",LEFT(BM20,3)<>"666",LEFT(BM20,1)<>"9") -> FALSE | BO20: =LEFT(M20,6)="001-01" -> FALSE | BP20: =IF(AND(M20<>"",NOT(BN20)),1,0) -> 0 | BR20: =AND(AI20="",OR(Z20<>"",AF20<>"")) -> FALSE | BS20: =IF(AND(AO20<18,Z20<>"",AF20="",BN20),1,0) -> 0 | BT20: =IF(OR(BS20=0,AO20>=6),0,IF(AO20<6,BS20,0)) -> 0 | BU20: =IF(OR(AND(Z20="",AF20<>""),AND(Z20<>"",AF20="",NOT(BN20))),1,0) -> 0 | BW20: =IF(AND(BH20=1,BP20<>1),1,0) -> 0
M21: =IF(OR(Z21<>"",AF21<>""),"001-01-0013","") | AO21: =IF(AI21="","",TaxYear-YEAR(AI21)) | AQ21: =IF(AND(BS21<>0,BT21<>0),BT$5,IF(BS21<>0,BS$5,IF(BT21<>0,BT$5,IF(BU21<>0,BU$5,IF(BW21<>0,$BW$5,""))))) | BH21: =IF(OR(E21<>"",I21<>"",M21<>"",S21<>"",Z21<>"",AF21<>""),1,0) -> 0 | BI21: =IF(AND(Z21<>"",AF21<>""),1,0) -> 0 | BJ21: =IF(AND(Z21<>"",$BI21=0),1,0) -> 0 | BK21: =IF(AND(AF21<>"",$BI21=0),1,0) -> 0 | BL21: =TEXT(M21,"000-00-0000") | BM21: =LEFT(BL21,3) | BN21: =AND(M21<>"",LEFT(BM21,3)<>"000",LEFT(BM21,3)<>"666",LEFT(BM21,1)<>"9") -> FALSE | BO21: =LEFT(M21,6)="001-01" -> FALSE | BP21: =IF(AND(M21<>"",NOT(BN21)),1,0) -> 0 | BR21: =AND(AI21="",OR(Z21<>"",AF21<>"")) -> FALSE | BS21: =IF(AND(AO21<18,Z21<>"",AF21="",BN21),1,0) -> 0 | BT21: =IF(OR(BS21=0,AO21>=6),0,IF(AO21<6,BS21,0)) -> 0 | BU21: =IF(OR(AND(Z21="",AF21<>""),AND(Z21<>"",AF21="",NOT(BN21))),1,0) -> 0 | BW21: =IF(AND(BH21=1,BP21<>1),1,0) -> 0
M22: =IF(OR(Z22<>"",AF22<>""),"001-01-0014","") | AO22: =IF(AI22="","",TaxYear-YEAR(AI22)) | AQ22: =IF(AND(BS22<>0,BT22<>0),BT$5,IF(BS22<>0,BS$5,IF(BT22<>0,BT$5,IF(BU22<>0,BU$5,IF(BW22<>0,$BW$5,""))))) | BH22: =IF(OR(E22<>"",I22<>"",M22<>"",S22<>"",Z22<>"",AF22<>""),1,0) -> 0 | BI22: =IF(AND(Z22<>"",AF22<>""),1,0) -> 0 | BJ22: =IF(AND(Z22<>"",$BI22=0),1,0) -> 0 | BK22: =IF(AND(AF22<>"",$BI22=0),1,0) -> 0 | BL22: =TEXT(M22,"000-00-0000") | BM22: =LEFT(BL22,3) | BN22: =AND(M22<>"",LEFT(BM22,3)<>"000",LEFT(BM22,3)<>"666",LEFT(BM22,1)<>"9") -> FALSE | BO22: =LEFT(M22,6)="001-01" -> FALSE | BP22: =IF(AND(M22<>"",NOT(BN22)),1,0) -> 0 | BR22: =AND(AI22="",OR(Z22<>"",AF22<>"")) -> FALSE | BS22: =IF(AND(AO22<18,Z22<>"",AF22="",BN22),1,0) -> 0 | BT22: =IF(OR(BS22=0,AO22>=6),0,IF(AO22<6,BS22,0)) -> 0 | BU22: =IF(OR(AND(Z22="",AF22<>""),AND(Z22<>"",AF22="",NOT(BN22))),1,0) -> 0 | BW22: =IF(AND(BH22=1,BP22<>1),1,0) -> 0
M23: =IF(OR(Z23<>"",AF23<>""),"001-01-0015","") | AO23: =IF(AI23="","",TaxYear-YEAR(AI23)) | AQ23: =IF(AND(BS23<>0,BT23<>0),BT$5,IF(BS23<>0,BS$5,IF(BT23<>0,BT$5,IF(BU23<>0,BU$5,IF(BW23<>0,$BW$5,""))))) | BH23: =IF(OR(E23<>"",I23<>"",M23<>"",S23<>"",Z23<>"",AF23<>""),1,0) -> 0 | BI23: =IF(AND(Z23<>"",AF23<>""),1,0) -> 0 | BJ23: =IF(AND(Z23<>"",$BI23=0),1,0) -> 0 | BK23: =IF(AND(AF23<>"",$BI23=0),1,0) -> 0 | BL23: =TEXT(M23,"000-00-0000") | BM23: =LEFT(BL23,3) | BN23: =AND(M23<>"",LEFT(BM23,3)<>"000",LEFT(BM23,3)<>"666",LEFT(BM23,1)<>"9") -> FALSE | BO23: =LEFT(M23,6)="001-01" -> FALSE | BP23: =IF(AND(M23<>"",NOT(BN23)),1,0) -> 0 | BR23: =AND(AI23="",OR(Z23<>"",AF23<>"")) -> FALSE | BS23: =IF(AND(AO23<18,Z23<>"",AF23="",BN23),1,0) -> 0 | BT23: =IF(OR(BS23=0,AO23>=6),0,IF(AO23<6,BS23,0)) -> 0 | BU23: =IF(OR(AND(Z23="",AF23<>""),AND(Z23<>"",AF23="",NOT(BN23))),1,0) -> 0 | BW23: =IF(AND(BH23=1,BP23<>1),1,0) -> 0
M24: =IF(OR(Z24<>"",AF24<>""),"001-01-0016","") | AO24: =IF(AI24="","",TaxYear-YEAR(AI24)) | AQ24: =IF(AND(BS24<>0,BT24<>0),BT$5,IF(BS24<>0,BS$5,IF(BT24<>0,BT$5,IF(BU24<>0,BU$5,IF(BW24<>0,$BW$5,""))))) | BH24: =IF(OR(E24<>"",I24<>"",M24<>"",S24<>"",Z24<>"",AF24<>""),1,0) -> 0 | BI24: =IF(AND(Z24<>"",AF24<>""),1,0) -> 0 | BJ24: =IF(AND(Z24<>"",$BI24=0),1,0) -> 0 | BK24: =IF(AND(AF24<>"",$BI24=0),1,0) -> 0 | BL24: =TEXT(M24,"000-00-0000") | BM24: =LEFT(BL24,3) | BN24: =AND(M24<>"",LEFT(BM24,3)<>"000",LEFT(BM24,3)<>"666",LEFT(BM24,1)<>"9") -> FALSE | BO24: =LEFT(M24,6)="001-01" -> FALSE | BP24: =IF(AND(M24<>"",NOT(BN24)),1,0) -> 0 | BR24: =AND(AI24="",OR(Z24<>"",AF24<>"")) -> FALSE | BS24: =IF(AND(AO24<18,Z24<>"",AF24="",BN24),1,0) -> 0 | BT24: =IF(OR(BS24=0,AO24>=6),0,IF(AO24<6,BS24,0)) -> 0 | BU24: =IF(OR(AND(Z24="",AF24<>""),AND(Z24<>"",AF24="",NOT(BN24))),1,0) -> 0 | BW24: =IF(AND(BH24=1,BP24<>1),1,0) -> 0
M25: =IF(OR(Z25<>"",AF25<>""),"001-01-0017","") | AO25: =IF(AI25="","",TaxYear-YEAR(AI25)) | AQ25: =IF(AND(BS25<>0,BT25<>0),BT$5,IF(BS25<>0,BS$5,IF(BT25<>0,BT$5,IF(BU25<>0,BU$5,IF(BW25<>0,$BW$5,""))))) | BH25: =IF(OR(E25<>"",I25<>"",M25<>"",S25<>"",Z25<>"",AF25<>""),1,0) -> 0 | BI25: =IF(AND(Z25<>"",AF25<>""),1,0) -> 0 | BJ25: =IF(AND(Z25<>"",$BI25=0),1,0) -> 0 | BK25: =IF(AND(AF25<>"",$BI25=0),1,0) -> 0 | BL25: =TEXT(M25,"000-00-0000") | BM25: =LEFT(BL25,3) | BN25: =AND(M25<>"",LEFT(BM25,3)<>"000",LEFT(BM25,3)<>"666",LEFT(BM25,1)<>"9") -> FALSE | BO25: =LEFT(M25,6)="001-01" -> FALSE | BP25: =IF(AND(M25<>"",NOT(BN25)),1,0) -> 0 | BR25: =AND(AI25="",OR(Z25<>"",AF25<>"")) -> FALSE | BS25: =IF(AND(AO25<18,Z25<>"",AF25="",BN25),1,0) -> 0 | BT25: =IF(OR(BS25=0,AO25>=6),0,IF(AO25<6,BS25,0)) -> 0 | BU25: =IF(OR(AND(Z25="",AF25<>""),AND(Z25<>"",AF25="",NOT(BN25))),1,0) -> 0 | BW25: =IF(AND(BH25=1,BP25<>1),1,0) -> 0
M26: =IF(OR(Z26<>"",AF26<>""),"001-01-0018","") | AO26: =IF(AI26="","",TaxYear-YEAR(AI26)) | AQ26: =IF(AND(BS26<>0,BT26<>0),BT$5,IF(BS26<>0,BS$5,IF(BT26<>0,BT$5,IF(BU26<>0,BU$5,IF(BW26<>0,$BW$5,""))))) | BH26: =IF(OR(E26<>"",I26<>"",M26<>"",S26<>"",Z26<>"",AF26<>""),1,0) -> 0 | BI26: =IF(AND(Z26<>"",AF26<>""),1,0) -> 0 | BJ26: =IF(AND(Z26<>"",$BI26=0),1,0) -> 0 | BK26: =IF(AND(AF26<>"",$BI26=0),1,0) -> 0 | BL26: =TEXT(M26,"000-00-0000") | BM26: =LEFT(BL26,3) | BN26: =AND(M26<>"",LEFT(BM26,3)<>"000",LEFT(BM26,3)<>"666",LEFT(BM26,1)<>"9") -> FALSE | BO26: =LEFT(M26,6)="001-01" -> FALSE | BP26: =IF(AND(M26<>"",NOT(BN26)),1,0) -> 0 | BR26: =AND(AI26="",OR(Z26<>"",AF26<>"")) -> FALSE | BS26: =IF(AND(AO26<18,Z26<>"",AF26="",BN26),1,0) -> 0 | BT26: =IF(OR(BS26=0,AO26>=6),0,IF(AO26<6,BS26,0)) -> 0 | BU26: =IF(OR(AND(Z26="",AF26<>""),AND(Z26<>"",AF26="",NOT(BN26))),1,0) -> 0 | BW26: =IF(AND(BH26=1,BP26<>1),1,0) -> 0
M27: =IF(OR(Z27<>"",AF27<>""),"001-01-0019","") | AO27: =IF(AI27="","",TaxYear-YEAR(AI27)) | AQ27: =IF(AND(BS27<>0,BT27<>0),BT$5,IF(BS27<>0,BS$5,IF(BT27<>0,BT$5,IF(BU27<>0,BU$5,IF(BW27<>0,$BW$5,""))))) | BH27: =IF(OR(E27<>"",I27<>"",M27<>"",S27<>"",Z27<>"",AF27<>""),1,0) -> 0 | BI27: =IF(AND(Z27<>"",AF27<>""),1,0) -> 0 | BJ27: =IF(AND(Z27<>"",$BI27=0),1,0) -> 0 | BK27: =IF(AND(AF27<>"",$BI27=0),1,0) -> 0 | BL27: =TEXT(M27,"000-00-0000") | BM27: =LEFT(BL27,3) | BN27: =AND(M27<>"",LEFT(BM27,3)<>"000",LEFT(BM27,3)<>"666",LEFT(BM27,1)<>"9") -> FALSE | BO27: =LEFT(M27,6)="001-01" -> FALSE | BP27: =IF(AND(M27<>"",NOT(BN27)),1,0) -> 0 | BR27: =AND(AI27="",OR(Z27<>"",AF27<>"")) -> FALSE | BS27: =IF(AND(AO27<18,Z27<>"",AF27="",BN27),1,0) -> 0 | BT27: =IF(OR(BS27=0,AO27>=6),0,IF(AO27<6,BS27,0)) -> 0 | BU27: =IF(OR(AND(Z27="",AF27<>""),AND(Z27<>"",AF27="",NOT(BN27))),1,0) -> 0 | BW27: =IF(AND(BH27=1,BP27<>1),1,0) -> 0
M28: =IF(OR(Z28<>"",AF28<>""),"001-01-0020","") | AO28: =IF(AI28="","",TaxYear-YEAR(AI28)) | AQ28: =IF(AND(BS28<>0,BT28<>0),BT$5,IF(BS28<>0,BS$5,IF(BT28<>0,BT$5,IF(BU28<>0,BU$5,IF(BW28<>0,$BW$5,""))))) | BH28: =IF(OR(E28<>"",I28<>"",M28<>"",S28<>"",Z28<>"",AF28<>""),1,0) -> 0 | BI28: =IF(AND(Z28<>"",AF28<>""),1,0) -> 0 | BJ28: =IF(AND(Z28<>"",$BI28=0),1,0) -> 0 | BK28: =IF(AND(AF28<>"",$BI28=0),1,0) -> 0 | BL28: =TEXT(M28,"000-00-0000") | BM28: =LEFT(BL28,3) | BN28: =AND(M28<>"",LEFT(BM28,3)<>"000",LEFT(BM28,3)<>"666",LEFT(BM28,1)<>"9") -> FALSE | BO28: =LEFT(M28,6)="001-01" -> FALSE | BP28: =IF(AND(M28<>"",NOT(BN28)),1,0) -> 0 | BR28: =AND(AI28="",OR(Z28<>"",AF28<>"")) -> FALSE | BS28: =IF(AND(AO28<18,Z28<>"",AF28="",BN28),1,0) -> 0 | BT28: =IF(OR(BS28=0,AO28>=6),0,IF(AO28<6,BS28,0)) -> 0 | BU28: =IF(OR(AND(Z28="",AF28<>""),AND(Z28<>"",AF28="",NOT(BN28))),1,0) -> 0 | BW28: =IF(AND(BH28=1,BP28<>1),1,0) -> 0
M29: =IF(OR(Z29<>"",AF29<>""),"001-01-0021","") | AO29: =IF(AI29="","",TaxYear-YEAR(AI29)) | AQ29: =IF(AND(BS29<>0,BT29<>0),BT$5,IF(BS29<>0,BS$5,IF(BT29<>0,BT$5,IF(BU29<>0,BU$5,IF(BW29<>0,$BW$5,""))))) | BH29: =IF(OR(E29<>"",I29<>"",M29<>"",S29<>"",Z29<>"",AF29<>""),1,0) -> 0 | BI29: =IF(AND(Z29<>"",AF29<>""),1,0) -> 0 | BJ29: =IF(AND(Z29<>"",$BI29=0),1,0) -> 0 | BK29: =IF(AND(AF29<>"",$BI29=0),1,0) -> 0 | BL29: =TEXT(M29,"000-00-0000") | BM29: =LEFT(BL29,3) | BN29: =AND(M29<>"",LEFT(BM29,3)<>"000",LEFT(BM29,3)<>"666",LEFT(BM29,1)<>"9") -> FALSE | BO29: =LEFT(M29,6)="001-01" -> FALSE | BP29: =IF(AND(M29<>"",NOT(BN29)),1,0) -> 0 | BR29: =AND(AI29="",OR(Z29<>"",AF29<>"")) -> FALSE | BS29: =IF(AND(AO29<18,Z29<>"",AF29="",BN29),1,0) -> 0 | BT29: =IF(OR(BS29=0,AO29>=6),0,IF(AO29<6,BS29,0)) -> 0 | BU29: =IF(OR(AND(Z29="",AF29<>""),AND(Z29<>"",AF29="",NOT(BN29))),1,0) -> 0 | BW29: =IF(AND(BH29=1,BP29<>1),1,0) -> 0
M30: =IF(OR(Z30<>"",AF30<>""),"001-01-0022","") | AO30: =IF(AI30="","",TaxYear-YEAR(AI30)) | AQ30: =IF(AND(BS30<>0,BT30<>0),BT$5,IF(BS30<>0,BS$5,IF(BT30<>0,BT$5,IF(BU30<>0,BU$5,IF(BW30<>0,$BW$5,""))))) | BH30: =IF(OR(E30<>"",I30<>"",M30<>"",S30<>"",Z30<>"",AF30<>""),1,0) -> 0 | BI30: =IF(AND(Z30<>"",AF30<>""),1,0) -> 0 | BJ30: =IF(AND(Z30<>"",$BI30=0),1,0) -> 0 | BK30: =IF(AND(AF30<>"",$BI30=0),1,0) -> 0 | BL30: =TEXT(M30,"000-00-0000") | BM30: =LEFT(BL30,3) | BN30: =AND(M30<>"",LEFT(BM30,3)<>"000",LEFT(BM30,3)<>"666",LEFT(BM30,1)<>"9") -> FALSE | BO30: =LEFT(M30,6)="001-01" -> FALSE | BP30: =IF(AND(M30<>"",NOT(BN30)),1,0) -> 0 | BR30: =AND(AI30="",OR(Z30<>"",AF30<>"")) -> FALSE | BS30: =IF(AND(AO30<18,Z30<>"",AF30="",BN30),1,0) -> 0 | BT30: =IF(OR(BS30=0,AO30>=6),0,IF(AO30<6,BS30,0)) -> 0 | BU30: =IF(OR(AND(Z30="",AF30<>""),AND(Z30<>"",AF30="",NOT(BN30))),1,0) -> 0 | BW30: =IF(AND(BH30=1,BP30<>1),1,0) -> 0
AR32: =SUM(BH15:BH30) -> 0 | AS32: =SUM(BI15:BI30) -> 0 | AT32: =SUM(BJ15:BJ30) -> 0 | AU32: =SUM(BK15:BK30) -> 0 | AY32: =SUM(BP15:BP30) -> 0
AR33: =SUM(BH11,AR32) -> 0 | AS33: =SUM(BI11,AS32) -> 0 | AT33: =SUM(BJ11,AT32) -> 0 | AU33: =SUM(BK11,AU32) -> 0 | AY33: =SUM(BP11,AY32) -> 0
AZ34: Override | BD34: Children | BE34: Children
AP35: Total number of dependents: | AQ35: =IF(AZ35<>"",ROUND(AZ35,0),AR33) -> 0 | BD35: Under 18 w/SSNs | BE35: Under 6 w/SSNs | BF35: Other Dependents
AP36: Total number of Child Tax Credits: [Line 19 (CTC), Line 27a (EIC), Line 30 (Rebate Credit)] | AQ36: =IF(AZ36<>"",ROUND(AZ36,0),AT33) -> 0 | BD36: =SUM(BS7:BS10,BS15:BS30) -> 0 | BE36: =SUM(BT7:BT10,BT15:BT30) -> 0 | BF36: =SUM(BU7:BU10,BU15:BU30) -> 0
AP37: Total number of Other Dependents: [Line 19 (CTC)] | AQ37: =IF(AZ37<>"",ROUND(AZ37,0),AU33) -> 0 | BC37: Form 8812 > | BD37: Line 4a | BE37: Line 4b | BF37: Line 6
BD40: Dependents w/SSNs
BD41: =SUM(BW7:BW10,BW15:BW30) -> 0
BC42: Line 30 WS > | BD42: Line 5

Sheet Sch. 1
AP1: Notes
B2: SCHEDULE 1 (Form 1040) | AB2: OMB No. 1545-0074
G3: Additional Income and Adjustments to Income | AB3: =TaxYear -> 2021 | AP3: Date:
B5: Department of the Treasury | M5: Attach to Form 1040, 1040-SR, or 1040-NR. | AC5: Attachment Sequence 01
B6: Internal Revenue Service | G6: Go to www.irs.gov/Form1040 for instructions and the latest information.
B7: Name(s) shown on Form 1040, 1040-SR, or 1040-NR | AB7: Your social security number | AJ7: Manual Override
B8: =Names | AB8: =IF(NoSSN,"",SS_Yours) -> 1010001
AN9: 43465
B10: Part I | F10: Additional Income | AL10: Source: | AN10: =AND(AlimonyRcvd>0,OR(V13="",V13>=$AN$9)) -> FALSE
C11: 1 | D11: Taxable refunds, credits, or offsets of state and local income taxes | AA11: . . . . . . . . . . | AB11: 1 | AC11: =IF(AJ11<>"",ROUND(AJ11,0),State_Local_Tax_Refund) -> 0 | AL11: Sch. 1, Line 1 (SALT) | AN11: TIP
C12: 2a | D12: Alimony received | AA12: . . . . . . . . . . . . . . . . . . . . . . . . . . . . . . | AB12: 2a | AC12: =ROUND(AJ12,0) -> 0 | AI12: =IF(AN10,"See TIP. >>","") | AK12: <<< Enter Alimony Received here.
C13: b | D13: Date of original divorce or separation agreement (see instructions) | AC13: =ROUND(AC12,0) -> 0 | AN13: Enter amounts received as alimony or separate maintenance pursuant to a divorce or separation agreement entered into on or before December 31, 2018, unless that agreement was changed after December 31, 2018, to expressly provide that alimony received isn't included in your income. Alimony received is not included in your income if you entered into a divorce or separation agreement after December 31, 2018. If you are including alimony in your income, you must let the person who made the payments know your social security number. If you don’t, you may have to pay a penalty. For more details, see Pub. 504. If you are including alimony payments from more than one divorce or separation agreement in your income, enter the total of all alimony received on line 2a.
C14: 3 | D14: Business income or (loss). Attach Schedule C | AA14: . . . . . . . . . . . . . . . . . . | AB14: 3 | AC14: =IF(AJ14<>"",ROUND(AJ14,0),Business_Profit) -> 0 | AL14: Sch. C
C15: 4 | D15: Other gains or (losses). Attach Form 4797 | AA15: . . . . . . . . . . . . . . . . . . . . | AB15: 4 | AL15: =ROUND(AC15,0) -> 0
C16: 5 | D16: Rental real estate, royalties, partnerships, S corporations, trusts, etc. Attach Schedule E | AA16: . | AB16: 5 | AC16: =IF(AJ16<>"",ROUND(AJ16,0),SUM(ScheduleE1,ScheduleE2,ScheduleE3,ScheduleE4)) -> 0 | AL16: Sch. E
C17: 6 | D17: Farm income or (loss). Attach Schedule F | AA17: . . . . . . . . . . . . . . . . . . . . | AB17: 6 | AC17: =IF(AJ17<>"",ROUND(AJ17,0),FarmProfitNet) -> 0 | AL17: Sch. F
C18: 7 | D18: Unemployment compensation | AA18: =IF(AK19<>"",". . . . . . . . . . . . . . . . . . . . Repaid ",". . . . . . . . . . . . . . . . . . . . . . . ") -> . . . . . . . . . . . . . . . . . . . . . . . | AB18: 7 | AC18: =IF(AJ18<>"",ROUND(AJ18,0),UnemployComp) -> 0 | AI18: =SUM(AC11,AC12,BusinessIncomeLoss,ROUND(AC15,0),SchE_IncomeLoss,FarmIncomeLoss,UnEmploymentComp) -> 0 | AL18: Form 1099-G
C19: 8 | D19: Other income: | AL19: =IF(AND(UnEmploymentComp<>"",UnEmploymentComp>0),"Check if UEC was REPAID.","")
C20: a | D20: Net operating loss | U20: . . . . . . . . . . . . . . . . . . . . | V20: 8a | W20: ( | AA20: ) | AC20: =-ROUND(X20,0) -> 0
C21: b | D21: Gambling income | U21: . . . . . . . . . . . . . . . . . . . . | V21: 8b | AC21: =ROUND(W21,0) -> 0
C22: c | D22: Cancellation of debt | U22: . . . . . . . . . . . . . . . . . . . | V22: 8c | AC22: =ROUND(W22,0) -> 0
C23: d | D23: Foreign earned income exclusion from Form 2555 | U23: . . . . . . . . | V23: 8d | W23: ( | X23: =IF(AND(AJ23<>"",AJ23<0),-ROUND(AJ23,0),IF(AJ23<>"",ROUND(AJ23,0),F2555_Line45)) -> 0 | AA23: ) | AC23: =-ROUND(X23,0) -> 0
C24: e | D24: Taxable Health Savings Account distribution | U24: . . . . . . . . . . | V24: 8e | W24: =IF(AJ24<>"",ROUND(AJ24,0),'8889'!K141) -> 0 | AC24: =ROUND(W24,0) -> 0
C25: f | D25: Alaska Permanent Fund dividends | U25: . . . . . . . . . . . . . . | V25: 8f | AC25: =ROUND(W25,0) -> 0
C26: g | D26: Jury duty pay | U26: . . . . . . . . . . . . . . . . . . . . . . | V26: 8g | AC26: =ROUND(W26,0) -> 0
C27: h | D27: Prizes and awards | U27: . . . . . . . . . . . . . . . . . . . . | V27: 8h | AC27: =ROUND(W27,0) -> 0
C28: i | D28: Activity not engaged in for profit income | U28: . . . . . . . . . . . | V28: 8i | AC28: =ROUND(W28,0) -> 0
C29: j | D29: Stock options | U29: . . . . . . . . . . . . . . . . . . . . . . | V29: 8j | AC29: =ROUND(W29,0) -> 0
C30: k | D30: Income from the rental of personal property if you engaged in
D31: the rental for profit but were not in the business of renting such
D32: property | U32: . . . . . . . . . . . . . . . . . . . . . . . . | V32: 8k | AC32: =ROUND(W32,0) -> 0
C33: l | D33: Olympic and Paralympic medals and USOC prize money (see
D34: instructions) | U34: . . . . . . . . . . . . . . . . . . . . . . . | V34: 8l | AC34: =ROUND(W34,0) -> 0
C35: m | D35: Section 951(a) inclusion (see instructions) | U35: . . . . . . . . . . . | V35: 8m | AC35: =ROUND(W35,0) -> 0
C36: n | D36: Section 951A(a) inclusion (see instructions) | U36: . . . . . . . . . . | V36: 8n | AC36: =ROUND(W36,0) -> 0
C37: o | D37: Section 461(l) excess business loss adjustment | U37: . . . . . . . . | V37: 8o | AC37: =ROUND(W37,0) -> 0 | AM37: Line 8z Entry
C38: p | D38: Taxable distributions from an ABLE account (see instructions) | U38: . . . | V38: 8p | AC38: =ROUND(W38,0) -> 0 | AM38: Type (Code) | AN38: Amount
C39: z | D39: Other income. List type and amount | N39: =IF(F8889_Line20>0,"HSA "& TEXT(F8889_Line20,"$0"),"")
D40: =AM40&" "&AN45&" "&AM41&" "&AN46&" "&AM42&" "&AN47&" "&AM43&" "&AN48 | V40: 8z | W40: =SUM(F8889_Line20,ROUND(AN40,0),ROUND(AN41,0),ROUND(AN42,0),ROUND(AN43,0)) -> 0 | AC40: =IF(W40="",0,ROUND(W40,0)) -> 0
C41: 9 | D41: Total other income. Add lines 8a through 8z | AA41: . . . . . . . . . . . . . . . . . . . | AB41: 9 | AC41: =IF(AJ41<>"",ROUND(AJ41,0),SUM(AC20:AG29,AC32,AC34:AG38,AC40)) -> 0
C42: 10 | D42: Combine lines 1 through 7 and 9. Enter here and on Form 1040, 1040-SR, or
D43: 1040-NR, line 8 | AA43: . . . . . . . . . . . . . . . . . . . . . . . . . . . . . | AB43: 10 | AC43: =IF(AJ43<>"",ROUND(AJ43,0),SUM(AC11,AC12,BusinessIncomeLoss,ROUND(AC15,0),SchE_IncomeLoss,FarmIncomeLoss,UnEmploymentComp,OtherIncome)) -> 0
B44: For Paperwork Reduction Act Notice, see your tax return instructions. | U44: Cat. No. 71479F | AG44: ="Schedule 1 (Form 1040) "&TaxYear -> Schedule 1 (Form 1040) 2021
B45: ="Schedule 1 (Form 1040) " & TaxYear -> Schedule 1 (Form 1040) 2021 | AG45: Page 2 | AN45: =IF(AN40<>"",TEXT(AN40,"$0"),"")
B46: Part II | F46: Adjustments to Income | AL46: =IF(OR(F8889_Line16>0,F8889_Line20),"HSA = "&TEXT(SUM(F8889_Line16,F8889_Line20),"$0"),"") | AN46: =IF(AN41<>"",TEXT(AN41,"$0"),"")
C47: 11 | D47: Educator expenses | AA47: . . . . . . . . . . . . . . . . . . . . . . . . . . . . . | AB47: 11 | AL47: =IF(AJ91="","",IF(AJ91>999,AI90&" - "&TEXT(AJ91,"$0,000"),AI90&" - "&TEXT(AJ91,"$0"))) | AN47: =IF(AN42<>"",TEXT(AN42,"$0"),"")
C48: 12 | D48: Certain business expenses of reservists, performing artists, and fee-basis government | AL48: =IF('2555'!AE175>0,"Form 2555 = ("&TEXT(F2555_Line45,"$0")&")","") | AN48: =IF(AN43<>"",TEXT(AN43,"$0"),"")
D49: officials. Attach Form 2106 | AA49: . . . . . . . . . . . . . . . . . . . . . . . . . | AB49: 12 | AL49: =IF(F1099G_TaxGrants>0,"Grants = "&TEXT(F1099G_TaxGrants,"$0"),"")
C50: 13 | D50: Health savings account deduction. Attach Form 8889 | AA50: . . . . . . . . . . . . | AB50: 13 | AC50: =IF(AJ50<>"",ROUND(AJ50,0),F8889_Line13) -> 0 | AL50: Sheet "8889", line 13
C51: 14 | D51: Moving expenses for members of the Armed Forces. Attach Form 3903 | AA51: . . . . | AB51: 14
C52: 15 | D52: Deductible part of self-employment tax. Attach Schedule SE | AA52: . . . . . . . . . | AB52: 15 | AC52: =IF(AJ52<>"",ROUND(AJ52,0),SchSE_Deduction) -> 0 | AL52: Sch. SE, line 13 (Sum of both forms) | AN52: =AND(AlimonyPaid>0,OR(V58="",V58>=$AN$9)) -> FALSE
C53: 16 | D53: Self-employed SEP, SIMPLE, and qualified plans | AA53: . . . . . . . . . . . . . . | AB53: 16 | AJ53: =IF($AI$54,"Line 17 - Your SE Health Insurance deduction cannot","") | AN53: TIP
C54: 17 | D54: Self-employed health insurance deduction | AA54: . . . . . . . . . . . . . . . . . | AB54: 17 | AI54: =AND(SEHealthInsDeduct<>"",SEHealthInsDeduct>SUM(SchSE_Profit1,SchSE_Profit2)) -> FALSE | AJ54: =IF($AI$54,"be more than your Schedule SE business profit.","") | AN54: If you made payments to or for your spouse or former spouse under a divorce or separation agreement entered into on or before December 31, 2018, you may be able to take this deduction. You can't take a deduction for alimony payments you made to or for your spouse if you entered into your divorce or separation agreement after December 31, 2018, or if you entered into the agreement on or before December 31, 2018, and the agreement was changed after December 31, 2018, to expressly provide that alimony received is not included in your former spouse's income. Use Tax Topic 452 or see Pub. 504.
C55: 18 | D55: Penalty on early withdrawal of savings | AA55: . . . . . . . . . . . . . . . . . . . . | AB55: 18 | AC55: =IF(AJ55<>"",ROUND(AJ55,0),Penalty4EW) -> 0 | AL55: Sheet "1099-INT", Line 2
C56: 19a | D56: Alimony paid | AA56: . . . . . . . . . . . . . . . . . . . . . . . . . . . . . . | AB56: 19a | AI56: =IF(AN52,"See TIP. >>","")
C57: b | D57: Recipient's SSN | U57: . . . . . . . . . . . . . . . . . . . .
C58: c | D58: Date of original divorce or separation agreement (see instructions)
C59: 20 | D59: IRA deduction | AA59: =IF(LivedApart,". . . . . . . . . . . . . . . . . . . . . . . . . . . . . D ",". . . . . . . . . . . . . . . . . . . . . . . . . . . . . . ") -> . . . . . . . . . . . . . . . . . . . . . . . . . . . . . . | AB59: 20 | AC59: =IF(AJ59<>"",ROUND(AJ59,0),IRA_Deduction) | AL59: Sheet "Sch. 1, Line 20 (IRA)"
C60: 21 | D60: Student loan interest deduction | AA60: . . . . . . . . . . . . . . . . . . . . . . | AB60: 21 | AC60: =IF(AJ60<>"",ROUND(AJ60,0),StuLoanIntDeduct) | AL60: Sheet "Line 21 (Stu Loan)"
